Workbook

Sheet Presentation brief
A2: Halloween assortment — team presentation brief
A4: Decision status | B4: =IF(B8>0,"Pending: "&B8&" products need a team decision",IF(AND('Team summary'!H25="Within limits",'Team summary'!I25="OK",'Team summary'!B45="OK",D8=0),"Ready for presentation review","Review constraints or missing rationale")) -> Review constraints or missing rationale
A6: Store products | B6: Count | C6: Store facings | D6: Target 16 | E6: Online products | F6: Maximum 4
A7: Chosen | B7: ='Team summary'!B25 -> 13 | C7: Used | D7: ='Team summary'!C25 -> 16 | E7: Chosen | F7: ='Team summary'!D25 -> 4
A8: Pending decisions | B8: =26-(COUNTIFS('Product decisions'!$J$7:$J$32,"In-Store")+COUNTIFS('Product decisions'!$J$7:$J$32,"Online-Only")+COUNTIFS('Product decisions'!$J$7:$J$32,"Removed")) -> 0 | C8: Decided, no rationale | D8: =COUNTIFS('Product decisions'!J7:J32,"In-Store",'Product decisions'!M7:M32,"")+COUNTIFS('Product decisions'!J7:J32,"Online-Only",'Product decisions'!M7:M32,"")+COUNTIFS('Product decisions'!J7:J32,"Removed",'Product decisions'!M7:M32,"") -> 26 | E8: Categories in-store | F8: =IF('Team summary'!E25>0,1,0)+IF('Team summary'!F25>0,1,0)+IF('Team summary'!G25>0,1,0) -> 3
A10: Compare the AI approaches — these are options, not your team’s selections.
A11: Approach | B11: Purpose | C11: Product spend | D11: Base profit* | E11: Downside profit* | F11: Store / online items
A12: Balanced | B12: Balance profit, variety and cash exposure. | C12: ='Team summary'!C7 -> 15130500 | D12: ='Team summary'!F7 -> 14367432 | E12: ='Team summary'!F8 -> 6209304 | F12: ='Team summary'!B22&" / "&'Team summary'!D22 -> 13 / 4
A13: Maximum profit | B13: Maximize modeled profit; no buying budget. | C13: ='Team summary'!C10 -> 27609500 | D13: ='Team summary'!F10 -> 22227912 | E13: ='Team summary'!F11 -> 9060568.1 | F13: ='Team summary'!B23&" / "&'Team summary'!D23 -> 11 / 4
A14: Lower investment | B14: Minimize spend; keep ≥90% of Balanced base profit. | C14: ='Team summary'!C13 -> 12124500 | D14: ='Team summary'!F13 -> 13118779 | E14: ='Team summary'!F14 -> 6321193.9 | F14: ='Team summary'!B24&" / "&'Team summary'!D24 -> 12 / 3
A15: Team choice | B15: Your selections; still pending until all products are decided. | C15: =IF(B8>0,"Pending",'Team summary'!C16) -> 13804500 | D15: =IF(B8>0,"Pending",'Team summary'!F16) -> 13899147 | E15: =IF(B8>0,"Pending",'Team summary'!F17) -> 6233204.8 | F15: ='Team summary'!B25&" / "&'Team summary'!D25 -> 13 / 4
A17: *Modeled profit = sales minus the cost of the entire order, including unsold units. It excludes operating expenses. The downside is a stress scenario, not a forecast.
A19: How the team uses this workbook
A20: 1. Review Product evidence; compare the three AI options on Product decisions.
A21: 2. Change Team choice from Undecided to In-Store, Online-Only or Removed. Add your team’s reason in Team rationale.
A22: 3. Use the chosen rows, reasons and completed totals for slides. Address tradeoffs, then add the required bonus-product pitch and honest AI reflection.
A24: Where the information came from | B24: What to say in the presentation
A25: Supplied event documents | B25: Historical performance, unit costs, prices, facings, ratings and review counts; supplier minimum order quantities and claims. Rules: exactly 16 store facings, up to four online-only items, and all three categories.
A26: Your priorities and edits | B26: Use store space efficiently; consider margin dollars, return on product spending and mandatory buys; compare current and new items; pair ratings with review counts; use channel shares. You set all 26 choices to Undecided for team review.
A27: AI calculations | B27: Channel unit shares, margin and return calculations, clearance exposure, and complete alternative assortments. Calculated results are derived from supplied inputs; they are not additional observed sales.
A28: AI judgment and assumptions | B28: Balanced recommendation, product tradeoffs and demand stress cases. New-item demand, channel recapture and clearance outcomes are assumptions in Assumptions. The optimizer does not measure traffic-building or cannibalization.
A29: Team decisions — still pending | B29: The Team choice and Team rationale fields belong to your team. AI suggestions remain separate. Undecided is excluded from partial selected totals and prevents a final presentation total.
A31: Source / limitation | B31: Reference
A32: Source workbook | B32: Halloween_Line Review Case Study_Data - Copy.xlsx — Student Data rows 6–21 and 27–36; Glossary. Original supplied file remains unchanged.
A33: Event instructions | B33: Hometown AI Innovation Challenge Case Study_Instructions - Students.pdf — pages 1–3. VP audience; eight minutes, maximum 10 slides; bonus item and AI reflection required.
A34: Interpretation limits | B34: Channel shares are units, not revenue. Prior online-only availability explains 100% online share. New items have no supplied sales or reviews. All current items recovered product cost in last season’s data.
A35: Detailed support | B35: The original analysis and source tabs are retained but hidden to keep the working view compact. Unhide them if you need to trace a figure. Edit demand and purchase controls on Assumptions.

Sheet Product decisions
A2: Team decisions — compare, choose, explain
A4: AI options: Balanced, Maximum profit, Lower investment. Your decision: Team choice. Keep Undecided until discussed; write your reason in Team rationale.
A6: Product | B6: Current / new | C6: Balanced | D6: Required facings | E6: Why keep, move, remove or pass | F6: Average stars | G6: Review count | H6: Maximum profit | I6: Lower investment | J6: Team choice | K6: Category | L6: Optimizer tradeoff | M6: Team rationale | O6: Team choice
A7: 12 ft Giant Skeleton | B7: Current | C7: In-Store | D7: =VLOOKUP(A7,'Source data'!$A$7:$D$32,4,FALSE) -> 3 | E7: ="KEEP: proven centerpiece. $6.62m historical gross profit; 95% full-price sell-through. Three facings earn strong profit. 4.5 stars from 1,200 reviews. Traffic-building value is not captured in the optimizer."&" Historical unit mix: "&TEXT(VLOOKUP(A7,'Channel evidence'!$A$7:$E$32,4,FALSE),"0%")&" store / "&TEXT(VLOOKUP(A7,'Channel evidence'!$A$7:$E$32,5,FALSE),"0%")&" online." -> KEEP: proven centerpiece. $6.62m historical gross profit; 95% full-price sell-through. Three facings earn strong profit. 4.5 stars from 1,200 reviews. Traffic-building value is not captured in the optimizer. Historical unit mix: 45% store / 55% online. | F7: 4.5 | G7: 1200 | H7: Online-Only | I7: Online-Only | J7: In-Store | K7: Giants & Animatronics | L7: Maximum profit: Online-Only. Lower investment: Online-Only. Both optimizers ignore unmeasured store traffic benefits.
A8: 9 ft Animated Pirate Ship | B8: Current | C8: Online-Only | D8: =VLOOKUP(A8,'Source data'!$A$7:$D$32,4,FALSE) -> 2 | E8: ="MOVE ONLINE: 70% of units sold online; frees two facings. Only 60% full-price sell-through. Reduce future buying exposure if supplier terms allow; the model keeps last season’s quantity for comparability."&" Historical unit mix: "&TEXT(VLOOKUP(A8,'Channel evidence'!$A$7:$E$32,4,FALSE),"0%")&" store / "&TEXT(VLOOKUP(A8,'Channel evidence'!$A$7:$E$32,5,FALSE),"0%")&" online." -> MOVE ONLINE: 70% of units sold online; frees two facings. Only 60% full-price sell-through. Reduce future buying exposure if supplier terms allow; the model keeps last season’s quantity for comparability. Historical unit mix: 30% store / 70% online. | F8: 4.3 | G8: 95 | H8: Online-Only | I8: Removed | J8: Online-Only | K8: Giants & Animatronics | L8: Lower investment: Removed.
A9: 7 ft Animated Reaper | B9: Current | C9: In-Store | D9: =VLOOKUP(A9,'Source data'!$A$7:$D$32,4,FALSE) -> 1 | E9: ="KEEP: $1.81m historical gross profit from one facing; 85% full-price sell-through. 4.6 stars from 265 reviews. Strong use of limited store space."&" Historical unit mix: "&TEXT(VLOOKUP(A9,'Channel evidence'!$A$7:$E$32,4,FALSE),"0%")&" store / "&TEXT(VLOOKUP(A9,'Channel evidence'!$A$7:$E$32,5,FALSE),"0%")&" online." -> KEEP: $1.81m historical gross profit from one facing; 85% full-price sell-through. 4.6 stars from 265 reviews. Strong use of limited store space. Historical unit mix: 50% store / 50% online. | F9: 4.6 | G9: 265 | H9: In-Store | I9: In-Store | J9: In-Store | K9: Giants & Animatronics | L9: Same placement in all three options.
A10: 5.5 ft LED Skeleton Pony | B10: Current | C10: In-Store | D10: =VLOOKUP(A10,'Source data'!$A$7:$D$32,4,FALSE) -> 1 | E10: ="KEEP: $129 middle price point, 63.8% realized margin and $1.04m historical gross profit. 4.1 stars from 100 reviews warrant investigating quality feedback."&" Historical unit mix: "&TEXT(VLOOKUP(A10,'Channel evidence'!$A$7:$E$32,4,FALSE),"0%")&" store / "&TEXT(VLOOKUP(A10,'Channel evidence'!$A$7:$E$32,5,FALSE),"0%")&" online." -> KEEP: $129 middle price point, 63.8% realized margin and $1.04m historical gross profit. 4.1 stars from 100 reviews warrant investigating quality feedback. Historical unit mix: 55% store / 45% online. | F10: 4.1 | G10: 100 | H10: In-Store | I10: In-Store | J10: In-Store | K10: Giants & Animatronics | L10: Same placement in all three options.
A11: 10.5 ft Licensed Character Inflatable | B11: Current | C11: Removed | D11: =VLOOKUP(A11,'Source data'!$A$7:$D$32,4,FALSE) -> 2 | E11: ="REMOVE: two facings generated only $46,600 gross profit, a 4.2% margin. Cost $132 against $149 retail leaves little clearance cushion. 4.8 stars from 220 reviews do not overcome weak economics."&" Historical unit mix: "&TEXT(VLOOKUP(A11,'Channel evidence'!$A$7:$E$32,4,FALSE),"0%")&" store / "&TEXT(VLOOKUP(A11,'Channel evidence'!$A$7:$E$32,5,FALSE),"0%")&" online." -> REMOVE: two facings generated only $46,600 gross profit, a 4.2% margin. Cost $132 against $149 retail leaves little clearance cushion. 4.8 stars from 220 reviews do not overcome weak economics. Historical unit mix: 40% store / 60% online. | F11: 4.8 | G11: 220 | H11: Removed | I11: Removed | J11: Removed | K11: Inflatables | L11: Same placement in all three options.
A12: 9.5 ft Licensed Sandworm Inflatable | B12: Current | C12: In-Store | D12: =VLOOKUP(A12,'Source data'!$A$7:$D$32,4,FALSE) -> 1 | E12: ="KEEP: licensed variety in one facing, 80% full-price sell-through and $410,500 gross profit. 4.7 stars from 205 reviews. A deliberate variety choice; 65% online unit share makes channel placement debatable."&" Historical unit mix: "&TEXT(VLOOKUP(A12,'Channel evidence'!$A$7:$E$32,4,FALSE),"0%")&" store / "&TEXT(VLOOKUP(A12,'Channel evidence'!$A$7:$E$32,5,FALSE),"0%")&" online." -> KEEP: licensed variety in one facing, 80% full-price sell-through and $410,500 gross profit. 4.7 stars from 205 reviews. A deliberate variety choice; 65% online unit share makes channel placement debatable. Historical unit mix: 35% store / 65% online. | F12: 4.7 | G12: 205 | H12: Removed | I12: Removed | J12: In-Store | K12: Inflatables | L12: Maximum profit: Removed. Lower investment: Removed.
A13: 12 ft Reaper Inflatable | B13: Current | C13: Removed | D13: =VLOOKUP(A13,'Source data'!$A$7:$D$32,4,FALSE) -> 1 | E13: ="REMOVE: only $13,500 gross profit, a 2.5% margin, with half the purchase on clearance. 4.8 stars from 75 reviews suggest satisfaction but do not establish adequate full-price demand."&" Historical unit mix: "&TEXT(VLOOKUP(A13,'Channel evidence'!$A$7:$E$32,4,FALSE),"0%")&" store / "&TEXT(VLOOKUP(A13,'Channel evidence'!$A$7:$E$32,5,FALSE),"0%")&" online." -> REMOVE: only $13,500 gross profit, a 2.5% margin, with half the purchase on clearance. 4.8 stars from 75 reviews suggest satisfaction but do not establish adequate full-price demand. Historical unit mix: 45% store / 55% online. | F13: 4.8 | G13: 75 | H13: Removed | I13: Removed | J13: Removed | K13: Inflatables | L13: Same placement in all three options.
A14: 6 ft Scarecrow Inflatable | B14: Current | C14: In-Store | D14: =VLOOKUP(A14,'Source data'!$A$7:$D$32,4,FALSE) -> 1 | E14: ="KEEP: accessible $59 inflatable, 85% full-price sell-through, 65% store unit share. 4.6 stars from 60 reviews. Preserves an affordable inflatable price point."&" Historical unit mix: "&TEXT(VLOOKUP(A14,'Channel evidence'!$A$7:$E$32,4,FALSE),"0%")&" store / "&TEXT(VLOOKUP(A14,'Channel evidence'!$A$7:$E$32,5,FALSE),"0%")&" online." -> KEEP: accessible $59 inflatable, 85% full-price sell-through, 65% store unit share. 4.6 stars from 60 reviews. Preserves an affordable inflatable price point. Historical unit mix: 65% store / 35% online. | F14: 4.6 | G14: 60 | H14: Removed | I14: Removed | J14: In-Store | K14: Inflatables | L14: Maximum profit: Removed. Lower investment: Removed.
A15: 24 in Metal Tombstone | B15: Current | C15: In-Store | D15: =VLOOKUP(A15,'Source data'!$A$7:$D$32,4,FALSE) -> 1 | E15: ="KEEP: $24.98 entry price and 81.1% realized margin. $546,960 gross profit. Five-star average has only six reviews; do not treat it as definitive evidence of superior quality."&" Historical unit mix: "&TEXT(VLOOKUP(A15,'Channel evidence'!$A$7:$E$32,4,FALSE),"0%")&" store / "&TEXT(VLOOKUP(A15,'Channel evidence'!$A$7:$E$32,5,FALSE),"0%")&" online." -> KEEP: $24.98 entry price and 81.1% realized margin. $546,960 gross profit. Five-star average has only six reviews; do not treat it as definitive evidence of superior quality. Historical unit mix: 70% store / 30% online. | F15: 5 | G15: 6 | H15: In-Store | I15: In-Store | J15: In-Store | K15: Decor & Accessories | L15: Same placement in all three options.
A16: 5 ft Skeleton Tombstone | B16: Current | C16: In-Store | D16: =VLOOKUP(A16,'Source data'!$A$7:$D$32,4,FALSE) -> 1 | E16: ="KEEP: $574,700 gross profit and 61.2% realized margin from one facing. 4.8 stars is based on only 10 reviews. Economics are more persuasive than the small rating sample."&" Historical unit mix: "&TEXT(VLOOKUP(A16,'Channel evidence'!$A$7:$E$32,4,FALSE),"0%")&" store / "&TEXT(VLOOKUP(A16,'Channel evidence'!$A$7:$E$32,5,FALSE),"0%")&" online." -> KEEP: $574,700 gross profit and 61.2% realized margin from one facing. 4.8 stars is based on only 10 reviews. Economics are more persuasive than the small rating sample. Historical unit mix: 45% store / 55% online. | F16: 4.8 | G16: 10 | H16: In-Store | I16: In-Store | J16: In-Store | K16: Decor & Accessories | L16: Same placement in all three options.
A17: LED Fog Machine | B17: Current | C17: Removed | D17: =VLOOKUP(A17,'Source data'!$A$7:$D$32,4,FALSE) -> 1 | E17: ="REMOVE: 17,000 of 25,000 units sold on clearance. Only 32% full-price sell-through; $48,500 profit on $925,000 product cost. Cost was recovered, but little profit remained. 4.2 stars from 3,400 reviews."&" Historical unit mix: "&TEXT(VLOOKUP(A17,'Channel evidence'!$A$7:$E$32,4,FALSE),"0%")&" store / "&TEXT(VLOOKUP(A17,'Channel evidence'!$A$7:$E$32,5,FALSE),"0%")&" online." -> REMOVE: 17,000 of 25,000 units sold on clearance. Only 32% full-price sell-through; $48,500 profit on $925,000 product cost. Cost was recovered, but little profit remained. 4.2 stars from 3,400 reviews. Historical unit mix: 60% store / 40% online. | F17: 4.2 | G17: 3400 | H17: Removed | I17: Removed | J17: Removed | K17: Decor & Accessories | L17: Same placement in all three options.
A18: Pathway Light Set (6-piece) | B18: Current | C18: In-Store | D18: =VLOOKUP(A18,'Source data'!$A$7:$D$32,4,FALSE) -> 1 | E18: ="KEEP: 85% full-price sell-through, 62.9% realized margin and 70% store unit share. 4.4 stars from 480 reviews. Practical complementary purchase."&" Historical unit mix: "&TEXT(VLOOKUP(A18,'Channel evidence'!$A$7:$E$32,4,FALSE),"0%")&" store / "&TEXT(VLOOKUP(A18,'Channel evidence'!$A$7:$E$32,5,FALSE),"0%")&" online." -> KEEP: 85% full-price sell-through, 62.9% realized margin and 70% store unit share. 4.4 stars from 480 reviews. Practical complementary purchase. Historical unit mix: 70% store / 30% online. | F18: 4.4 | G18: 480 | H18: In-Store | I18: In-Store | J18: In-Store | K18: Decor & Accessories | L18: Same placement in all three options.
A19: 16 ft Inflatable Haunted Archway | B19: Current | C19: Online-Only | D19: =VLOOKUP(A19,'Source data'!$A$7:$D$32,4,FALSE) -> 3 | E19: ="KEEP ONLINE: proven online sales, 85% full-price sell-through and $534,450 gross profit. Avoids three store facings. 4.6 stars from 340 reviews."&" Historical unit mix: "&TEXT(VLOOKUP(A19,'Channel evidence'!$A$7:$E$32,4,FALSE),"0%")&" store / "&TEXT(VLOOKUP(A19,'Channel evidence'!$A$7:$E$32,5,FALSE),"0%")&" online." -> KEEP ONLINE: proven online sales, 85% full-price sell-through and $534,450 gross profit. Avoids three store facings. 4.6 stars from 340 reviews. Historical unit mix: 0% store / 100% online. | F19: 4.6 | G19: 340 | H19: Online-Only | I19: In-Store | J19: Online-Only | K19: Inflatables | L19: Lower investment: In-Store.
A20: Life-Size Animated Butler | B20: Current | C20: Online-Only | D20: =VLOOKUP(A20,'Source data'!$A$7:$D$32,4,FALSE) -> 2 | E20: ="KEEP ONLINE: 90% full-price sell-through, $916,200 gross profit and 60.4% realized margin. 4.7 stars from 210 reviews. Avoids two facings."&" Historical unit mix: "&TEXT(VLOOKUP(A20,'Channel evidence'!$A$7:$E$32,4,FALSE),"0%")&" store / "&TEXT(VLOOKUP(A20,'Channel evidence'!$A$7:$E$32,5,FALSE),"0%")&" online." -> KEEP ONLINE: 90% full-price sell-through, $916,200 gross profit and 60.4% realized margin. 4.7 stars from 210 reviews. Avoids two facings. Historical unit mix: 0% store / 100% online. | F20: 4.7 | G20: 210 | H20: Online-Only | I20: Online-Only | J20: Online-Only | K20: Giants & Animatronics | L20: Same placement in all three options.
A21: Animated Witch Cauldron | B21: Current | C21: Removed | D21: =VLOOKUP(A21,'Source data'!$A$7:$D$32,4,FALSE) -> 1 | E21: ="REMOVE FOR CAPACITY: healthy 58.9% margin, 85% full-price sell-through and 4.5 stars from 180 reviews. Its $215,375 gross profit loses the four-slot online competition. Not a loss-making product."&" Historical unit mix: "&TEXT(VLOOKUP(A21,'Channel evidence'!$A$7:$E$32,4,FALSE),"0%")&" store / "&TEXT(VLOOKUP(A21,'Channel evidence'!$A$7:$E$32,5,FALSE),"0%")&" online." -> REMOVE FOR CAPACITY: healthy 58.9% margin, 85% full-price sell-through and 4.5 stars from 180 reviews. Its $215,375 gross profit loses the four-slot online competition. Not a loss-making product. Historical unit mix: 0% store / 100% online. | F21: 4.5 | G21: 180 | H21: Removed | I21: Online-Only | J21: Online-Only | K21: Decor & Accessories | L21: Lower investment: Online-Only.
A22: Halloween Doormat Assortment | B22: Current | C22: Removed | D22: =VLOOKUP(A22,'Source data'!$A$7:$D$32,4,FALSE) -> 1 | E22: ="REMOVE: only 45% full-price sell-through and $22,370 gross profit. 4.0 stars from 55 reviews. Cheap inventory alone is not a strong customer proposition."&" Historical unit mix: "&TEXT(VLOOKUP(A22,'Channel evidence'!$A$7:$E$32,4,FALSE),"0%")&" store / "&TEXT(VLOOKUP(A22,'Channel evidence'!$A$7:$E$32,5,FALSE),"0%")&" online." -> REMOVE: only 45% full-price sell-through and $22,370 gross profit. 4.0 stars from 55 reviews. Cheap inventory alone is not a strong customer proposition. Historical unit mix: 0% store / 100% online. | F22: 4 | G22: 55 | H22: Removed | I22: Removed | J22: Removed | K22: Decor & Accessories | L22: Same placement in all three options. The up-to-four online limit removes the need for low-cost space filling.
A23: 14 ft Giant Animated Dragon | B23: New | C23: Removed | D23: =VLOOKUP(A23,'Source data'!$A$7:$D$32,4,FALSE) -> 4 | E23: PASS: mandatory 45,000 units cost $10.8m and require four facings. No supplied demand or review history. Vendor sellout claim is unverified. $224.50 half-price clearance is below $240 unit cost. Strong modeled upside, but concentrated cash and demand risk. | H23: In-Store | I23: Removed | J23: Removed | K23: Giants & Animatronics | L23: Maximum profit: In-Store.
A24: 6 ft Licensed Movie Villain | B24: New | C24: Removed | D24: =VLOOKUP(A24,'Source data'!$A$7:$D$32,4,FALSE) -> 2 | E24: PASS: 14,000-unit minimum costs $3.01m. Licensed royalty is already in cost. 34.7% full-price margin, falling to 27.4% at 80% full-price sell-through. Sitcom option requires less cash and offers better return on cost. | H24: In-Store | I24: Removed | J24: Removed | K24: Giants & Animatronics | L24: Maximum profit: In-Store.
A25: 9 ft Licensed Franchise Inflatable | B25: New | C25: Removed | D25: =VLOOKUP(A25,'Source data'!$A$7:$D$32,4,FALSE) -> 2 | E25: PASS: 12,000-unit minimum costs $1.656m. Only $21 margin at full price. Half-price clearance loses $58.50 per unit. At 80% full-price sell-through, modeled margin is just 3.6%. No ratings supplied. | H25: Removed | I25: Removed | J25: Removed | K25: Inflatables | L25: Same placement in all three options.
A26: 7 ft Licensed Sitcom Character | B26: New | C26: In-Store | D26: =VLOOKUP(A26,'Source data'!$A$7:$D$32,4,FALSE) -> 2 | E26: ADD: licensed animation with 41.2% full-price margin. 9,000-unit mandatory buy costs $1.476m versus $3.01m for Movie Villain. Still unproven and requires two facings. Source note incorrectly claims the existing Reaper has the same footprint. | H26: In-Store | I26: In-Store | J26: Removed | K26: Giants & Animatronics | L26: Same placement in all three options.
A27: 8 ft Inflatable Black Cat | B27: New | C27: In-Store | D27: =VLOOKUP(A27,'Source data'!$A$7:$D$32,4,FALSE) -> 1 | E27: ADD: classic $79 inflatable; 16,000-unit buy costs $640,000. $39 full-price unit margin. More cushion than licensed inflatable candidates, but demand remains unproven. | H27: In-Store | I27: In-Store | J27: In-Store | K27: Inflatables | L27: Same placement in all three options.
A28: 12 ft Inflatable Haunted Tree | B28: New | C28: Online-Only | D28: =VLOOKUP(A28,'Source data'!$A$7:$D$32,4,FALSE) -> 2 | E28: ADD ONLINE: 7,000-unit minimum costs $616,000. Extends oversized variety without two store facings. Vendor notes compact shipping carton. No historical online demand or ratings; model applies an 80% online demand factor. | H28: Removed | I28: In-Store | J28: In-Store | K28: Inflatables | L28: Maximum profit: Removed. Lower investment: In-Store.
A29: Fog Machine w/ Bluetooth Sound | B29: New | C29: Removed | D29: =VLOOKUP(A29,'Source data'!$A$7:$D$32,4,FALSE) -> 1 | E29: PASS: 20,000-unit minimum costs $1.04m, versus only 8,000 full-price units sold for old fog. Features do not prove a demand fix. At the old 32% full-price rate with remaining units half-price, profit would be $134,800 before other expenses. | H29: In-Store | I29: Removed | J29: Removed | K29: Decor & Accessories | L29: Maximum profit: In-Store.
A30: Animated Talking Portrait | B30: New | C30: In-Store | D30: =VLOOKUP(A30,'Source data'!$A$7:$D$32,4,FALSE) -> 1 | E30: ADD: 9,000-unit minimum costs only $63,000. 82.5% full-price margin and $39.98 price. Lower total profit than large products, but efficient capital use and in-store discovery potential. No ratings supplied. | H30: Removed | I30: In-Store | J30: In-Store | K30: Decor & Accessories | L30: Maximum profit: Removed.
A31: Solar Pathway Ghosts (4-pc) | B31: New | C31: In-Store | D31: =VLOOKUP(A31,'Source data'!$A$7:$D$32,4,FALSE) -> 1 | E31: ADD: 12,000-unit minimum costs $192,000. 64.4% full-price margin. Solar functionality adds variety; half-price clearance remains above unit cost. Check overlap with existing pathway lights. | H31: Removed | I31: In-Store | J31: In-Store | K31: Decor & Accessories | L31: Maximum profit: Removed.
A32: 24 in Light-Up Pumpkin Stack | B32: New | C32: In-Store | D32: =VLOOKUP(A32,'Source data'!$A$7:$D$32,4,FALSE) -> 1 | E32: ADD: $29.98 entry item; 22,000-unit minimum costs $198,000. 70.0% full-price margin. Half-price clearance still earns $5.99 per unit before expenses. Quantity is substantial but cash exposure is relatively low. | H32: In-Store | I32: In-Store | J32: In-Store | K32: Decor & Accessories | L32: Same placement in all three options.

Sheet Product evidence
A2: Product evidence — facts first, AI interpretation last
A4: Current items: supplied historical results. Channel shares use units sold; ratings show the average and number of reviews.
A6: Current product | B6: Actual gross profit / margin | C6: Full-price sell-through | D6: Store / online units % | E6: Stars (reviews) | F6: AI consideration
A7: ='Source data'!A7 -> 12 ft Giant Skeleton | B7: =TEXT('Source data'!O7,"$#,##0")&" / "&TEXT('Source data'!O7/'Source data'!N7,"0.0%") -> $6,621,000 / 56.8% | C7: ='Source data'!H7/'Source data'!G7 -> 0.95 | D7: =TEXT('Source data'!J7/SUM('Source data'!J7:K7),"0%")&" / "&TEXT('Source data'!K7/SUM('Source data'!J7:K7),"0%") -> 45% / 55% | E7: =TEXT('Source data'!L7,"0.0")&" ("&TEXT('Source data'!M7,"#,##0")&")" -> 4.5 (1,200) | F7: Proven hero; 3 facings. Keeping it in-store is a deliberate traffic/demo judgment despite 55% online sales.
A8: ='Source data'!A8 -> 9 ft Animated Pirate Ship | B8: =TEXT('Source data'!O8,"$#,##0")&" / "&TEXT('Source data'!O8/'Source data'!N8,"0.0%") -> $1,216,800 / 42.4% | C8: ='Source data'!H8/'Source data'!G8 -> 0.6 | D8: =TEXT('Source data'!J8/SUM('Source data'!J8:K8),"0%")&" / "&TEXT('Source data'!K8/SUM('Source data'!J8:K8),"0%") -> 30% / 70% | E8: =TEXT('Source data'!L8,"0.0")&" ("&TEXT('Source data'!M8,"#,##0")&")" -> 4.3 (95) | F8: 70% online supports moving it online; low full-price sell-through suggests purchase risk.
A9: ='Source data'!A9 -> 7 ft Animated Reaper | B9: =TEXT('Source data'!O9,"$#,##0")&" / "&TEXT('Source data'!O9/'Source data'!N9,"0.0%") -> $1,812,900 / 58.5% | C9: ='Source data'!H9/'Source data'!G9 -> 0.85 | D9: =TEXT('Source data'!J9/SUM('Source data'!J9:K9),"0%")&" / "&TEXT('Source data'!K9/SUM('Source data'!J9:K9),"0%") -> 50% / 50% | E9: =TEXT('Source data'!L9,"0.0")&" ("&TEXT('Source data'!M9,"#,##0")&")" -> 4.6 (265) | F9: Strong profit from one facing; equal store/online split.
A10: ='Source data'!A10 -> 5.5 ft LED Skeleton Pony | B10: =TEXT('Source data'!O10,"$#,##0")&" / "&TEXT('Source data'!O10/'Source data'!N10,"0.0%") -> $1,037,400 / 63.8% | C10: ='Source data'!H10/'Source data'!G10 -> 0.8 | D10: =TEXT('Source data'!J10/SUM('Source data'!J10:K10),"0%")&" / "&TEXT('Source data'!K10/SUM('Source data'!J10:K10),"0%") -> 55% / 45% | E10: =TEXT('Source data'!L10,"0.0")&" ("&TEXT('Source data'!M10,"#,##0")&")" -> 4.1 (100) | F10: Healthy margin and mid-price option; investigate the 4.1-star feedback.
A11: ='Source data'!A11 -> 10.5 ft Licensed Character Inflatable | B11: =TEXT('Source data'!O11,"$#,##0")&" / "&TEXT('Source data'!O11/'Source data'!N11,"0.0%") -> $46,600 / 4.2% | C11: ='Source data'!H11/'Source data'!G11 -> 0.85 | D11: =TEXT('Source data'!J11/SUM('Source data'!J11:K11),"0%")&" / "&TEXT('Source data'!K11/SUM('Source data'!J11:K11),"0%") -> 40% / 60% | E11: =TEXT('Source data'!L11,"0.0")&" ("&TEXT('Source data'!M11,"#,##0")&")" -> 4.8 (220) | F11: Only 4.2% realized margin across two facings; ratings do not fix the economics.
A12: ='Source data'!A12 -> 9.5 ft Licensed Sandworm Inflatable | B12: =TEXT('Source data'!O12,"$#,##0")&" / "&TEXT('Source data'!O12/'Source data'!N12,"0.0%") -> $410,500 / 33.9% | C12: ='Source data'!H12/'Source data'!G12 -> 0.8 | D12: =TEXT('Source data'!J12/SUM('Source data'!J12:K12),"0%")&" / "&TEXT('Source data'!K12/SUM('Source data'!J12:K12),"0%") -> 35% / 65% | E12: =TEXT('Source data'!L12,"0.0")&" ("&TEXT('Source data'!M12,"#,##0")&")" -> 4.7 (205) | F12: Licensed variety in one facing; 65% online challenges the store recommendation.
A13: ='Source data'!A13 -> 12 ft Reaper Inflatable | B13: =TEXT('Source data'!O13,"$#,##0")&" / "&TEXT('Source data'!O13/'Source data'!N13,"0.0%") -> $13,500 / 2.5% | C13: ='Source data'!H13/'Source data'!G13 -> 0.5 | D13: =TEXT('Source data'!J13/SUM('Source data'!J13:K13),"0%")&" / "&TEXT('Source data'!K13/SUM('Source data'!J13:K13),"0%") -> 45% / 55% | E13: =TEXT('Source data'!L13,"0.0")&" ("&TEXT('Source data'!M13,"#,##0")&")" -> 4.8 (75) | F13: Half sold on clearance; only 2.5% realized margin.
A14: ='Source data'!A14 -> 6 ft Scarecrow Inflatable | B14: =TEXT('Source data'!O14,"$#,##0")&" / "&TEXT('Source data'!O14/'Source data'!N14,"0.0%") -> $391,500 / 35.9% | C14: ='Source data'!H14/'Source data'!G14 -> 0.85 | D14: =TEXT('Source data'!J14/SUM('Source data'!J14:K14),"0%")&" / "&TEXT('Source data'!K14/SUM('Source data'!J14:K14),"0%") -> 65% / 35% | E14: =TEXT('Source data'!L14,"0.0")&" ("&TEXT('Source data'!M14,"#,##0")&")" -> 4.6 (60) | F14: Affordable inflatable; 65% store share supports store placement.
A15: ='Source data'!A15 -> 24 in Metal Tombstone | B15: =TEXT('Source data'!O15,"$#,##0")&" / "&TEXT('Source data'!O15/'Source data'!N15,"0.0%") -> $546,960 / 81.1% | C15: ='Source data'!H15/'Source data'!G15 -> 0.8 | D15: =TEXT('Source data'!J15/SUM('Source data'!J15:K15),"0%")&" / "&TEXT('Source data'!K15/SUM('Source data'!J15:K15),"0%") -> 70% / 30% | E15: =TEXT('Source data'!L15,"0.0")&" ("&TEXT('Source data'!M15,"#,##0")&")" -> 5.0 (6) | F15: High margin and 70% store share; only six reviews behind the five-star average.
A16: ='Source data'!A16 -> 5 ft Skeleton Tombstone | B16: =TEXT('Source data'!O16,"$#,##0")&" / "&TEXT('Source data'!O16/'Source data'!N16,"0.0%") -> $574,700 / 61.2% | C16: ='Source data'!H16/'Source data'!G16 -> 0.8 | D16: =TEXT('Source data'!J16/SUM('Source data'!J16:K16),"0%")&" / "&TEXT('Source data'!K16/SUM('Source data'!J16:K16),"0%") -> 45% / 55% | E16: =TEXT('Source data'!L16,"0.0")&" ("&TEXT('Source data'!M16,"#,##0")&")" -> 4.8 (10) | F16: Healthy one-facing profit; high rating is based on only 10 reviews.
A17: ='Source data'!A17 -> LED Fog Machine | B17: =TEXT('Source data'!O17,"$#,##0")&" / "&TEXT('Source data'!O17/'Source data'!N17,"0.0%") -> $48,500 / 5.0% | C17: ='Source data'!H17/'Source data'!G17 -> 0.32 | D17: =TEXT('Source data'!J17/SUM('Source data'!J17:K17),"0%")&" / "&TEXT('Source data'!K17/SUM('Source data'!J17:K17),"0%") -> 60% / 40% | E17: =TEXT('Source data'!L17,"0.0")&" ("&TEXT('Source data'!M17,"#,##0")&")" -> 4.2 (3,400) | F17: 68% sold on clearance. Recovered product cost, but left only $48,500 gross profit.
A18: ='Source data'!A18 -> Pathway Light Set (6-piece) | B18: =TEXT('Source data'!O18,"$#,##0")&" / "&TEXT('Source data'!O18/'Source data'!N18,"0.0%") -> $366,417 / 62.9% | C18: ='Source data'!H18/'Source data'!G18 -> 0.85 | D18: =TEXT('Source data'!J18/SUM('Source data'!J18:K18),"0%")&" / "&TEXT('Source data'!K18/SUM('Source data'!J18:K18),"0%") -> 70% / 30% | E18: =TEXT('Source data'!L18,"0.0")&" ("&TEXT('Source data'!M18,"#,##0")&")" -> 4.4 (480) | F18: Strong full-price demand; 70% store share supports keeping it in-store.
... A22: ='Source data'!A22 -> Halloween Doormat Assortment | B22: =TEXT('Source data'!O22,"$#,##0")&" / "&TEXT('Source data'!O22/'Source data'!N22,"0.0%") -> $22,370 / 17.2% | C22: ='Source data'!H22/'Source data'!G22 -> 0.45 | D22: =TEXT('Source data'!J22/SUM('Source data'!J22:K22),"0%")&" / "&TEXT('Source data'!K22/SUM('Source data'!J22:K22),"0%") -> 0% / 100% | E22: =TEXT('Source data'!L22,"0.0")&" ("&TEXT('Source data'!M22,"#,##0")&")" -> 4.0 (55) | F22: Weak full-price demand and low gross profit; 100% online reflects availability.
A24: New items: supplier terms, not sales forecasts. Minimum investment = mandatory quantity × unit cost. No historical channel sales or reviews supplied.
A26: New product | B26: Retail / unit cost | C26: Mandatory units | D26: Minimum investment | E26: Full-price margin | F26: AI consideration
A27: ='Source data'!A23 -> 14 ft Giant Animated Dragon | B27: =TEXT('Source data'!E23,"$0.00")&" / "&TEXT('Source data'!F23,"$0.00") -> $449.00 / $240.00 | C27: ='Source data'!G23 -> 45000 | D27: ='Source data'!G23*'Source data'!F23 -> 10800000 | E27: =1-'Source data'!F23/'Source data'!E23 -> 0.46547884 | F27: $10.8m minimum buy and four facings. High upside; unproven demand. Half-price clearance loses $15.50 per unit.
A28: ='Source data'!A24 -> 6 ft Licensed Movie Villain | B28: =TEXT('Source data'!E24,"$0.00")&" / "&TEXT('Source data'!F24,"$0.00") -> $329.00 / $215.00 | C28: ='Source data'!G24 -> 14000 | D28: ='Source data'!G24*'Source data'!F24 -> 3010000 | E28: =1-'Source data'!F24/'Source data'!E24 -> 0.34650456 | F28: $3.01m minimum buy. Lower return on cost than the sitcom option; no review history.
A29: ='Source data'!A25 -> 9 ft Licensed Franchise Inflatable | B29: =TEXT('Source data'!E25,"$0.00")&" / "&TEXT('Source data'!F25,"$0.00") -> $159.00 / $138.00 | C29: ='Source data'!G25 -> 12000 | D29: ='Source data'!G25*'Source data'!F25 -> 1656000 | E29: =1-'Source data'!F25/'Source data'!E25 -> 0.13207547 | F29: Thin full-price margin. Half-price clearance loses $58.50 per unit.
A30: ='Source data'!A26 -> 7 ft Licensed Sitcom Character | B30: =TEXT('Source data'!E26,"$0.00")&" / "&TEXT('Source data'!F26,"$0.00") -> $279.00 / $164.00 | C30: ='Source data'!G26 -> 9000 | D30: ='Source data'!G26*'Source data'!F26 -> 1476000 | E30: =1-'Source data'!F26/'Source data'!E26 -> 0.41218638 | F30: Lower cash exposure than Movie Villain; still an unproven 9,000-unit buy. Requires two facings.
A31: ='Source data'!A27 -> 8 ft Inflatable Black Cat | B31: =TEXT('Source data'!E27,"$0.00")&" / "&TEXT('Source data'!F27,"$0.00") -> $79.00 / $40.00 | C31: ='Source data'!G27 -> 16000 | D31: ='Source data'!G27*'Source data'!F27 -> 640000 | E31: =1-'Source data'!F27/'Source data'!E27 -> 0.49367089 | F31: Classic lower-price inflatable; healthier unit margin than licensed candidates. Demand unproven.
A32: ='Source data'!A28 -> 12 ft Inflatable Haunted Tree | B32: =TEXT('Source data'!E28,"$0.00")&" / "&TEXT('Source data'!F28,"$0.00") -> $179.00 / $88.00 | C32: ='Source data'!G28 -> 7000 | D32: ='Source data'!G28*'Source data'!F28 -> 616000 | E32: =1-'Source data'!F28/'Source data'!E28 -> 0.50837989 | F32: Large footprint supports online placement. Compact carton is a supplied merchant note, not verified fulfillment cost.
A33: ='Source data'!A29 -> Fog Machine w/ Bluetooth Sound | B33: =TEXT('Source data'!E29,"$0.00")&" / "&TEXT('Source data'!F29,"$0.00") -> $89.00 / $52.00 | C33: ='Source data'!G29 -> 20000 | D33: ='Source data'!G29*'Source data'!F29 -> 1040000 | E33: =1-'Source data'!F29/'Source data'!E29 -> 0.41573034 | F33: Minimum 20,000 units versus 8,000 full-price units for old fog. Features do not establish demand.
A34: ='Source data'!A30 -> Animated Talking Portrait | B34: =TEXT('Source data'!E30,"$0.00")&" / "&TEXT('Source data'!F30,"$0.00") -> $39.98 / $7.00 | C34: ='Source data'!G30 -> 9000 | D34: ='Source data'!G30*'Source data'!F30 -> 63000 | E34: =1-'Source data'!F30/'Source data'!E30 -> 0.82491246 | F34: Low cash commitment and high margin; smaller total profit. No review history.
A35: ='Source data'!A31 -> Solar Pathway Ghosts (4-pc) | B35: =TEXT('Source data'!E31,"$0.00")&" / "&TEXT('Source data'!F31,"$0.00") -> $44.98 / $16.00 | C35: ='Source data'!G31 -> 12000 | D35: ='Source data'!G31*'Source data'!F31 -> 192000 | E35: =1-'Source data'!F31/'Source data'!E31 -> 0.64428635 | F35: Healthy unit margin and modest cash commitment. Check overlap with existing pathway lights.
A36: ='Source data'!A32 -> 24 in Light-Up Pumpkin Stack | B36: =TEXT('Source data'!E32,"$0.00")&" / "&TEXT('Source data'!F32,"$0.00") -> $29.98 / $9.00 | C36: ='Source data'!G32 -> 22000 | D36: ='Source data'!G32*'Source data'!F32 -> 198000 | E36: =1-'Source data'!F32/'Source data'!E32 -> 0.69979987 | F36: Affordable entry item; half-price clearance still earns $5.99 per unit before expenses.

Sheet Assumptions
A2: Inputs and assumptions — AI modeling choices
A4: Yellow cells are editable model inputs, not supplied forecasts. Origins and limitations are on Presentation brief.
A6: Demand case | B6: Full-price demand multiplier | C6: Remaining stock sold on clearance | D6: Clearance price / retail
A7: Base | B7: 1 | C7: 1 | D7: 0.5
A8: Downside | B8: 0.7 | C8: 0.5 | D8: 0.5
A9: Upside | B9: 1.15 | C9: 1 | D9: 0.5
A12: Shared driver | B12: Value | C12: Meaning
A13: New product full-price demand / minimum | B13: 0.8 | C13: Base store demand assumption; not a vendor forecast.
A14: New online demand / store demand | B14: 0.8 | C14: Conservative online-only demand assumption for new products.
A15: Recapture of other-channel current demand | B15: 0.5 | C15: Example: store-only gets prior store units + 50% of prior online units.
A16: Lower-investment base profit floor | B16: 0.9 | C16: Solver minimizes product spend while keeping at least 90% of balanced base profit.
A20: Product | B20: Order quantity | C20: Minimum allowed | D20: Quantity check
A21: 12 ft Giant Skeleton | B21: 40000 | C21: 0 | D21: =IF(AND(ISNUMBER(B21),B21>=C21,B21>=0,MOD(B21,1)=0),"OK","Fix quantity") -> OK
A22: 9 ft Animated Pirate Ship | B22: 9000 | C22: 0 | D22: =IF(AND(ISNUMBER(B22),B22>=C22,B22>=0,MOD(B22,1)=0),"OK","Fix quantity") -> OK
A23: 7 ft Animated Reaper | B23: 12000 | C23: 0 | D23: =IF(AND(ISNUMBER(B23),B23>=C23,B23>=0,MOD(B23,1)=0),"OK","Fix quantity") -> OK
A24: 5.5 ft LED Skeleton Pony | B24: 14000 | C24: 0 | D24: =IF(AND(ISNUMBER(B24),B24>=C24,B24>=0,MOD(B24,1)=0),"OK","Fix quantity") -> OK
A25: 10.5 ft Licensed Character Inflatable | B25: 8000 | C25: 0 | D25: =IF(AND(ISNUMBER(B25),B25>=C25,B25>=0,MOD(B25,1)=0),"OK","Fix quantity") -> OK
A26: 9.5 ft Licensed Sandworm Inflatable | B26: 5000 | C26: 0 | D26: =IF(AND(ISNUMBER(B26),B26>=C26,B26>=0,MOD(B26,1)=0),"OK","Fix quantity") -> OK
A27: 12 ft Reaper Inflatable | B27: 6000 | C27: 0 | D27: =IF(AND(ISNUMBER(B27),B27>=C27,B27>=0,MOD(B27,1)=0),"OK","Fix quantity") -> OK
A28: 6 ft Scarecrow Inflatable | B28: 20000 | C28: 0 | D28: =IF(AND(ISNUMBER(B28),B28>=C28,B28>=0,MOD(B28,1)=0),"OK","Fix quantity") -> OK
A29: 24 in Metal Tombstone | B29: 30000 | C29: 0 | D29: =IF(AND(ISNUMBER(B29),B29>=C29,B29>=0,MOD(B29,1)=0),"OK","Fix quantity") -> OK
A30: 5 ft Skeleton Tombstone | B30: 7000 | C30: 0 | D30: =IF(AND(ISNUMBER(B30),B30>=C30,B30>=0,MOD(B30,1)=0),"OK","Fix quantity") -> OK
A31: LED Fog Machine | B31: 25000 | C31: 0 | D31: =IF(AND(ISNUMBER(B31),B31>=C31,B31>=0,MOD(B31,1)=0),"OK","Fix quantity") -> OK
A32: Pathway Light Set (6-piece) | B32: 18000 | C32: 0 | D32: =IF(AND(ISNUMBER(B32),B32>=C32,B32>=0,MOD(B32,1)=0),"OK","Fix quantity") -> OK
... A46: 24 in Light-Up Pumpkin Stack | B46: 22000 | C46: 22000 | D46: =IF(AND(ISNUMBER(B46),B46>=C46,B46>=0,MOD(B46,1)=0),"OK","Fix quantity") -> OK
A49: Model meaning
A50: Profit after full buy cost = sales revenue less the cost of every unit ordered.
A51: Unsold units receive zero recovery in that conservative measure; unsold inventory cost is shown separately.
A52: Gross profit on sold units is also available in Profit model; neither measure includes freight, returns, labor, royalties beyond supplied cost, or other operating expenses.
A53: Current quantity defaults to last season’s purchase, not a supplier minimum. New quantity may increase but may not fall below the mandatory minimum.
A54: Scenario placements were optimized once at the original assumptions. Formulas revalue them live; they do not rerun the discrete optimizer after edits.
A55: Demand cases use one shared row-based calculation engine. Product demand is independent; cannibalization and store traffic benefits are not estimated.

Sheet Team summary
A2: Halloween assortment: team decision brief
A4: What I Recommendation: Balanced - it has exactly 16 facings, 4 online-only items, all three categories in-store.
A6: Assortment | B6: Demand case | C6: Product purchases | D6: New-product purchases | E6: Sales revenue | F6: Profit after full buy cost | G6: Return on buy cost | H6: Unsold inventory cost | I6: Profit vs balanced | J6: Sales vs last year
A7: Balanced | B7: Base | C7: =SUMIFS('Profit model'!$L$7:$L$162,'Profit model'!$C$7:$C$162,B7,'Profit model'!$Q$7:$Q$162,1) -> 15130500 | D7: =SUMIFS('Profit model'!$U$7:$U$162,'Profit model'!$C$7:$C$162,B7,'Profit model'!$Q$7:$Q$162,1) -> 3185000 | E7: =SUMIFS('Profit model'!$K$7:$K$162,'Profit model'!$C$7:$C$162,B7,'Profit model'!$Q$7:$Q$162,1) -> 29497932 | F7: =SUMIFS('Profit model'!$N$7:$N$162,'Profit model'!$C$7:$C$162,B7,'Profit model'!$Q$7:$Q$162,1) -> 14367432 | G7: =IF(C7=0,0,F7/C7) -> 0.94956756 | H7: =SUMIFS('Profit model'!$O$7:$O$162,'Profit model'!$C$7:$C$162,B7,'Profit model'!$Q$7:$Q$162,1) -> 0 | I7: =F7-F7 -> 0 | J7: =E7-SUM('Source data'!$N$7:$N$22) -> 16260.45
A8: Balanced | B8: Downside | C8: =SUMIFS('Profit model'!$L$7:$L$162,'Profit model'!$C$7:$C$162,B8,'Profit model'!$Q$7:$Q$162,1) -> 15130500 | D8: =SUMIFS('Profit model'!$U$7:$U$162,'Profit model'!$C$7:$C$162,B8,'Profit model'!$Q$7:$Q$162,1) -> 3185000 | E8: =SUMIFS('Profit model'!$K$7:$K$162,'Profit model'!$C$7:$C$162,B8,'Profit model'!$Q$7:$Q$162,1) -> 21339804 | F8: =SUMIFS('Profit model'!$N$7:$N$162,'Profit model'!$C$7:$C$162,B8,'Profit model'!$Q$7:$Q$162,1) -> 6209304 | G8: =IF(C8=0,0,F8/C8) -> 0.41038327 | H8: =SUMIFS('Profit model'!$O$7:$O$162,'Profit model'!$C$7:$C$162,B8,'Profit model'!$Q$7:$Q$162,1) -> 3942867.2 | I8: =F8-F8 -> 0 | J8: =E8-SUM('Source data'!$N$7:$N$22) -> -8141867.5
A9: Balanced | B9: Upside | C9: =SUMIFS('Profit model'!$L$7:$L$162,'Profit model'!$C$7:$C$162,B9,'Profit model'!$Q$7:$Q$162,1) -> 15130500 | D9: =SUMIFS('Profit model'!$U$7:$U$162,'Profit model'!$C$7:$C$162,B9,'Profit model'!$Q$7:$Q$162,1) -> 3185000 | E9: =SUMIFS('Profit model'!$K$7:$K$162,'Profit model'!$C$7:$C$162,B9,'Profit model'!$Q$7:$Q$162,1) -> 31267503 | F9: =SUMIFS('Profit model'!$N$7:$N$162,'Profit model'!$C$7:$C$162,B9,'Profit model'!$Q$7:$Q$162,1) -> 16137003 | G9: =IF(C9=0,0,F9/C9) -> 1.0665215 | H9: =SUMIFS('Profit model'!$O$7:$O$162,'Profit model'!$C$7:$C$162,B9,'Profit model'!$Q$7:$Q$162,1) -> 0 | I9: =F9-F9 -> 0 | J9: =E9-SUM('Source data'!$N$7:$N$22) -> 1785831.7
A10: Maximum profit | B10: Base | C10: =SUMIFS('Profit model'!$L$7:$L$162,'Profit model'!$C$7:$C$162,B10,'Profit model'!$R$7:$R$162,1) -> 27609500 | D10: =SUMIFS('Profit model'!$U$7:$U$162,'Profit model'!$C$7:$C$162,B10,'Profit model'!$R$7:$R$162,1) -> 17164000 | E10: =SUMIFS('Profit model'!$K$7:$K$162,'Profit model'!$C$7:$C$162,B10,'Profit model'!$R$7:$R$162,1) -> 49837412 | F10: =SUMIFS('Profit model'!$N$7:$N$162,'Profit model'!$C$7:$C$162,B10,'Profit model'!$R$7:$R$162,1) -> 22227912 | G10: =IF(C10=0,0,F10/C10) -> 0.80508204 | H10: =SUMIFS('Profit model'!$O$7:$O$162,'Profit model'!$C$7:$C$162,B10,'Profit model'!$R$7:$R$162,1) -> 0 | I10: =F10-F7 -> 7860480.5 | J10: =E10-SUM('Source data'!$N$7:$N$22) -> 20355741
A11: Maximum profit | B11: Downside | C11: =SUMIFS('Profit model'!$L$7:$L$162,'Profit model'!$C$7:$C$162,B11,'Profit model'!$R$7:$R$162,1) -> 27609500 | D11: =SUMIFS('Profit model'!$U$7:$U$162,'Profit model'!$C$7:$C$162,B11,'Profit model'!$R$7:$R$162,1) -> 17164000 | E11: =SUMIFS('Profit model'!$K$7:$K$162,'Profit model'!$C$7:$C$162,B11,'Profit model'!$R$7:$R$162,1) -> 36670068 | F11: =SUMIFS('Profit model'!$N$7:$N$162,'Profit model'!$C$7:$C$162,B11,'Profit model'!$R$7:$R$162,1) -> 9060568.1 | G11: =IF(C11=0,0,F11/C11) -> 0.3281685 | H11: =SUMIFS('Profit model'!$O$7:$O$162,'Profit model'!$C$7:$C$162,B11,'Profit model'!$R$7:$R$162,1) -> 6472967.5 | I11: =F11-F8 -> 2851264 | J11: =E11-SUM('Source data'!$N$7:$N$22) -> 7188396.6
A12: Maximum profit | B12: Upside | C12: =SUMIFS('Profit model'!$L$7:$L$162,'Profit model'!$C$7:$C$162,B12,'Profit model'!$R$7:$R$162,1) -> 27609500 | D12: =SUMIFS('Profit model'!$U$7:$U$162,'Profit model'!$C$7:$C$162,B12,'Profit model'!$R$7:$R$162,1) -> 17164000 | E12: =SUMIFS('Profit model'!$K$7:$K$162,'Profit model'!$C$7:$C$162,B12,'Profit model'!$R$7:$R$162,1) -> 53014399 | F12: =SUMIFS('Profit model'!$N$7:$N$162,'Profit model'!$C$7:$C$162,B12,'Profit model'!$R$7:$R$162,1) -> 25404899 | G12: =IF(C12=0,0,F12/C12) -> 0.92015065 | H12: =SUMIFS('Profit model'!$O$7:$O$162,'Profit model'!$C$7:$C$162,B12,'Profit model'!$R$7:$R$162,1) -> 0 | I12: =F12-F9 -> 9267896.1 | J12: =E12-SUM('Source data'!$N$7:$N$22) -> 23532728
A13: Lower investment | B13: Base | C13: =SUMIFS('Profit model'!$L$7:$L$162,'Profit model'!$C$7:$C$162,B13,'Profit model'!$S$7:$S$162,1) -> 12124500 | D13: =SUMIFS('Profit model'!$U$7:$U$162,'Profit model'!$C$7:$C$162,B13,'Profit model'!$S$7:$S$162,1) -> 3185000 | E13: =SUMIFS('Profit model'!$K$7:$K$162,'Profit model'!$C$7:$C$162,B13,'Profit model'!$S$7:$S$162,1) -> 25243279 | F13: =SUMIFS('Profit model'!$N$7:$N$162,'Profit model'!$C$7:$C$162,B13,'Profit model'!$S$7:$S$162,1) -> 13118779 | G13: =IF(C13=0,0,F13/C13) -> 1.0820058 | H13: =SUMIFS('Profit model'!$O$7:$O$162,'Profit model'!$C$7:$C$162,B13,'Profit model'!$S$7:$S$162,1) -> 0 | I13: =F13-F7 -> -1248652.5 | J13: =E13-SUM('Source data'!$N$7:$N$22) -> -4238392
A14: Lower investment | B14: Downside | C14: =SUMIFS('Profit model'!$L$7:$L$162,'Profit model'!$C$7:$C$162,B14,'Profit model'!$S$7:$S$162,1) -> 12124500 | D14: =SUMIFS('Profit model'!$U$7:$U$162,'Profit model'!$C$7:$C$162,B14,'Profit model'!$S$7:$S$162,1) -> 3185000 | E14: =SUMIFS('Profit model'!$K$7:$K$162,'Profit model'!$C$7:$C$162,B14,'Profit model'!$S$7:$S$162,1) -> 18445694 | F14: =SUMIFS('Profit model'!$N$7:$N$162,'Profit model'!$C$7:$C$162,B14,'Profit model'!$S$7:$S$162,1) -> 6321193.9 | G14: =IF(C14=0,0,F14/C14) -> 0.52135708 | H14: =SUMIFS('Profit model'!$O$7:$O$162,'Profit model'!$C$7:$C$162,B14,'Profit model'!$S$7:$S$162,1) -> 2980346 | I14: =F14-F8 -> 111889.88 | J14: =E14-SUM('Source data'!$N$7:$N$22) -> -11035978
A15: Lower investment | B15: Upside | C15: =SUMIFS('Profit model'!$L$7:$L$162,'Profit model'!$C$7:$C$162,B15,'Profit model'!$S$7:$S$162,1) -> 12124500 | D15: =SUMIFS('Profit model'!$U$7:$U$162,'Profit model'!$C$7:$C$162,B15,'Profit model'!$S$7:$S$162,1) -> 3185000 | E15: =SUMIFS('Profit model'!$K$7:$K$162,'Profit model'!$C$7:$C$162,B15,'Profit model'!$S$7:$S$162,1) -> 26803728 | F15: =SUMIFS('Profit model'!$N$7:$N$162,'Profit model'!$C$7:$C$162,B15,'Profit model'!$S$7:$S$162,1) -> 14679228 | G15: =IF(C15=0,0,F15/C15) -> 1.2107079 | H15: =SUMIFS('Profit model'!$O$7:$O$162,'Profit model'!$C$7:$C$162,B15,'Profit model'!$S$7:$S$162,1) -> 0 | I15: =F15-F9 -> -1457775.4 | J15: =E15-SUM('Source data'!$N$7:$N$22) -> -2677943.6
A16: =IF(26-(COUNTIFS('Product decisions'!$J$7:$J$32,"In-Store")+COUNTIFS('Product decisions'!$J$7:$J$32,"Online-Only")+COUNTIFS('Product decisions'!$J$7:$J$32,"Removed"))>0,"Team choice (partial)","Team choice") -> Team choice | B16: Base | C16: =SUMIFS('Profit model'!$L$7:$L$162,'Profit model'!$C$7:$C$162,B16,'Profit model'!$T$7:$T$162,1) -> 13804500 | D16: =SUMIFS('Profit model'!$U$7:$U$162,'Profit model'!$C$7:$C$162,B16,'Profit model'!$T$7:$T$162,1) -> 1709000 | E16: =SUMIFS('Profit model'!$K$7:$K$162,'Profit model'!$C$7:$C$162,B16,'Profit model'!$T$7:$T$162,1) -> 27703647 | F16: =SUMIFS('Profit model'!$N$7:$N$162,'Profit model'!$C$7:$C$162,B16,'Profit model'!$T$7:$T$162,1) -> 13899147 | G16: =IF(C16=0,0,F16/C16) -> 1.0068562 | H16: =SUMIFS('Profit model'!$O$7:$O$162,'Profit model'!$C$7:$C$162,B16,'Profit model'!$T$7:$T$162,1) -> 0 | I16: =F16-F7 -> -468285 | J16: =E16-SUM('Source data'!$N$7:$N$22) -> -1778024.6
A17: =IF(26-(COUNTIFS('Product decisions'!$J$7:$J$32,"In-Store")+COUNTIFS('Product decisions'!$J$7:$J$32,"Online-Only")+COUNTIFS('Product decisions'!$J$7:$J$32,"Removed"))>0,"Team choice (partial)","Team choice") -> Team choice | B17: Downside | C17: =SUMIFS('Profit model'!$L$7:$L$162,'Profit model'!$C$7:$C$162,B17,'Profit model'!$T$7:$T$162,1) -> 13804500 | D17: =SUMIFS('Profit model'!$U$7:$U$162,'Profit model'!$C$7:$C$162,B17,'Profit model'!$T$7:$T$162,1) -> 1709000 | E17: =SUMIFS('Profit model'!$K$7:$K$162,'Profit model'!$C$7:$C$162,B17,'Profit model'!$T$7:$T$162,1) -> 20037705 | F17: =SUMIFS('Profit model'!$N$7:$N$162,'Profit model'!$C$7:$C$162,B17,'Profit model'!$T$7:$T$162,1) -> 6233204.8 | G17: =IF(C17=0,0,F17/C17) -> 0.45153427 | H17: =SUMIFS('Profit model'!$O$7:$O$162,'Profit model'!$C$7:$C$162,B17,'Profit model'!$T$7:$T$162,1) -> 3614026.2 | I17: =F17-F8 -> 23900.75 | J17: =E17-SUM('Source data'!$N$7:$N$22) -> -9443966.7
A18: =IF(26-(COUNTIFS('Product decisions'!$J$7:$J$32,"In-Store")+COUNTIFS('Product decisions'!$J$7:$J$32,"Online-Only")+COUNTIFS('Product decisions'!$J$7:$J$32,"Removed"))>0,"Team choice (partial)","Team choice") -> Team choice | B18: Upside | C18: =SUMIFS('Profit model'!$L$7:$L$162,'Profit model'!$C$7:$C$162,B18,'Profit model'!$T$7:$T$162,1) -> 13804500 | D18: =SUMIFS('Profit model'!$U$7:$U$162,'Profit model'!$C$7:$C$162,B18,'Profit model'!$T$7:$T$162,1) -> 1709000 | E18: =SUMIFS('Profit model'!$K$7:$K$162,'Profit model'!$C$7:$C$162,B18,'Profit model'!$T$7:$T$162,1) -> 29362775 | F18: =SUMIFS('Profit model'!$N$7:$N$162,'Profit model'!$C$7:$C$162,B18,'Profit model'!$T$7:$T$162,1) -> 15558275 | G18: =IF(C18=0,0,F18/C18) -> 1.1270438 | H18: =SUMIFS('Profit model'!$O$7:$O$162,'Profit model'!$C$7:$C$162,B18,'Profit model'!$T$7:$T$162,1) -> 0 | I18: =F18-F9 -> -578727.75 | J18: =E18-SUM('Source data'!$N$7:$N$22) -> -118896.01
A21: Assortment | B21: Store products | C21: Store facings | D21: Online items | E21: Giants in-store | F21: Inflatables in-store | G21: Decor in-store | H21: Placement check | I21: Quantity checks | J21: Lower-cost floor
A22: Balanced | B22: =COUNTIFS('Product decisions'!$C$7:$C$32,"In-Store") -> 13 | C22: =SUMIFS('Profit model'!$V$7:$V$162,'Profit model'!$C$7:$C$162,"Base",'Profit model'!$B$7:$B$162,"In-Store",'Profit model'!$Q$7:$Q$162,1) -> 16 | D22: =COUNTIFS('Product decisions'!$C$7:$C$32,"Online-Only") -> 4 | E22: =COUNTIFS('Product decisions'!$C$7:$C$32,"In-Store",'Source data'!$C$7:$C$32,"Giants & Animatronics") -> 4 | F22: =COUNTIFS('Product decisions'!$C$7:$C$32,"In-Store",'Source data'!$C$7:$C$32,"Inflatables") -> 3 | G22: =COUNTIFS('Product decisions'!$C$7:$C$32,"In-Store",'Source data'!$C$7:$C$32,"Decor & Accessories") -> 6 | H22: =IF(AND(C22=16,D22<=4,E22>0,F22>0,G22>0,COUNTIFS('Product decisions'!$C$7:$C$32,"In-Store")+COUNTIFS('Product decisions'!$C$7:$C$32,"Online-Only")+COUNTIFS('Product decisions'!$C$7:$C$32,"Removed")=26),"Within limits","Review choices") -> Within limits | I22: =IF(AND(COUNTIFS(Assumptions!$D$21:$D$46,"Fix quantity")=0,COUNTIFS('Profit model'!$C$7:$C$162,"Base",'Profit model'!$Q$7:$Q$162,1,'Profit model'!$D$7:$D$162,"<=0")=0),"OK","Fix quantity") -> OK
A23: Maximum profit | B23: =COUNTIFS('Product decisions'!$H$7:$H$32,"In-Store") -> 11 | C23: =SUMIFS('Profit model'!$V$7:$V$162,'Profit model'!$C$7:$C$162,"Base",'Profit model'!$B$7:$B$162,"In-Store",'Profit model'!$R$7:$R$162,1) -> 16 | D23: =COUNTIFS('Product decisions'!$H$7:$H$32,"Online-Only") -> 4 | E23: =COUNTIFS('Product decisions'!$H$7:$H$32,"In-Store",'Source data'!$C$7:$C$32,"Giants & Animatronics") -> 5 | F23: =COUNTIFS('Product decisions'!$H$7:$H$32,"In-Store",'Source data'!$C$7:$C$32,"Inflatables") -> 1 | G23: =COUNTIFS('Product decisions'!$H$7:$H$32,"In-Store",'Source data'!$C$7:$C$32,"Decor & Accessories") -> 5 | H23: =IF(AND(C23=16,D23<=4,E23>0,F23>0,G23>0,COUNTIFS('Product decisions'!$H$7:$H$32,"In-Store")+COUNTIFS('Product decisions'!$H$7:$H$32,"Online-Only")+COUNTIFS('Product decisions'!$H$7:$H$32,"Removed")=26),"Within limits","Review choices") -> Within limits | I23: =IF(AND(COUNTIFS(Assumptions!$D$21:$D$46,"Fix quantity")=0,COUNTIFS('Profit model'!$C$7:$C$162,"Base",'Profit model'!$R$7:$R$162,1,'Profit model'!$D$7:$D$162,"<=0")=0),"OK","Fix quantity") -> OK
A24: Lower investment | B24: =COUNTIFS('Product decisions'!$I$7:$I$32,"In-Store") -> 12 | C24: =SUMIFS('Profit model'!$V$7:$V$162,'Profit model'!$C$7:$C$162,"Base",'Profit model'!$B$7:$B$162,"In-Store",'Profit model'!$S$7:$S$162,1) -> 16 | D24: =COUNTIFS('Product decisions'!$I$7:$I$32,"Online-Only") -> 3 | E24: =COUNTIFS('Product decisions'!$I$7:$I$32,"In-Store",'Source data'!$C$7:$C$32,"Giants & Animatronics") -> 3 | F24: =COUNTIFS('Product decisions'!$I$7:$I$32,"In-Store",'Source data'!$C$7:$C$32,"Inflatables") -> 3 | G24: =COUNTIFS('Product decisions'!$I$7:$I$32,"In-Store",'Source data'!$C$7:$C$32,"Decor & Accessories") -> 6 | H24: =IF(AND(C24=16,D24<=4,E24>0,F24>0,G24>0,COUNTIFS('Product decisions'!$I$7:$I$32,"In-Store")+COUNTIFS('Product decisions'!$I$7:$I$32,"Online-Only")+COUNTIFS('Product decisions'!$I$7:$I$32,"Removed")=26),"Within limits","Review choices") -> Within limits | I24: =IF(AND(COUNTIFS(Assumptions!$D$21:$D$46,"Fix quantity")=0,COUNTIFS('Profit model'!$C$7:$C$162,"Base",'Profit model'!$S$7:$S$162,1,'Profit model'!$D$7:$D$162,"<=0")=0),"OK","Fix quantity") -> OK | J24: =IF(F13>=F7*Assumptions!$B$16,"Meets floor","Below floor") -> Meets floor
A25: Team choice | B25: =COUNTIFS('Product decisions'!$J$7:$J$32,"In-Store") -> 13 | C25: =SUMIFS('Profit model'!$V$7:$V$162,'Profit model'!$C$7:$C$162,"Base",'Profit model'!$B$7:$B$162,"In-Store",'Profit model'!$T$7:$T$162,1) -> 16 | D25: =COUNTIFS('Product decisions'!$J$7:$J$32,"Online-Only") -> 4 | E25: =COUNTIFS('Product decisions'!$J$7:$J$32,"In-Store",'Source data'!$C$7:$C$32,"Giants & Animatronics") -> 3 | F25: =COUNTIFS('Product decisions'!$J$7:$J$32,"In-Store",'Source data'!$C$7:$C$32,"Inflatables") -> 4 | G25: =COUNTIFS('Product decisions'!$J$7:$J$32,"In-Store",'Source data'!$C$7:$C$32,"Decor & Accessories") -> 6 | H25: =IF(26-(COUNTIFS('Product decisions'!$J$7:$J$32,"In-Store")+COUNTIFS('Product decisions'!$J$7:$J$32,"Online-Only")+COUNTIFS('Product decisions'!$J$7:$J$32,"Removed"))>0,"Pending: "&(26-(COUNTIFS('Product decisions'!$J$7:$J$32,"In-Store")+COUNTIFS('Product decisions'!$J$7:$J$32,"Online-Only")+COUNTIFS('Product decisions'!$J$7:$J$32,"Removed"))),IF(AND(C25=16,D25<=4,E25>0,F25>0,G25>0),"Within limits","Review choices")) -> Within limits | I25: =IF(AND(COUNTIFS(Assumptions!$D$21:$D$46,"Fix quantity")=0,COUNTIFS('Profit model'!$C$7:$C$162,"Base",'Profit model'!$T$7:$T$162,1,'Profit model'!$D$7:$D$162,"<=0")=0),"OK","Fix quantity") -> OK
A28: Decision guide | B28: Explanation
A29: Balanced recommendation | B29: Keeps the proven Giant Skeleton in stores, affordable inflatables and accessories, plus licensed variety. Trades some modeled profit for range and lower new-product exposure.
A30: Maximum profit | B30: Exact dynamic-programming optimum at original base assumptions: maximize profit after full buy cost with exactly 16 facings, zero to four online items and all categories in-store. No purchase budget or required hero placement.
A31: Lower investment | B31: Minimum product spend at original base assumptions, retaining at least 90% of balanced base profit, exactly 16 facings and up to four online items. The updated solution uses three online items. This is an analytical alternative, not a stated team budget.
A32: What changes live | B32: Edit Team choice on Product decisions, order quantities on Assumptions, and demand/clearance inputs. All twelve comparison rows update. Solver-generated placements remain fixed until the optimization is rerun.
A33: Why models need judgment | B33: Both optimized options move the Giant Skeleton online. Lower investment now removes doormats, keeps the Skeleton Tombstone in-store, and uses three online items. The model cannot value traffic, themes, licensed appeal, or cannibalization.
A34: Historic benchmark | B34: Last year: $29,481,672 sales and $14,775,172 gross profit on $14,706,500 product cost. All current products recovered product cost. Figures cover the supplied business dataset, not one store.
A35: Channel and demand assumptions | B35: Historical sales include both channels. Current exclusive-channel demand retains its past channel units plus 50% of the other channel, then applies historical full-price mix. New store full-price demand starts at 80% of mandatory quantity; new online at 80% of that.
A36: Downside inventory exposure | B36: Downside reduces full-price demand by 30% and clears only half of remaining stock. Unsold stock is not assumed sold; its full cost reduces the conservative profit measure. This is a scenario, not a probability forecast.
A37: Review interpretation | B37: Giant Skeleton: 4.5 average from 1,200 reviews. Metal Tombstone: 5.0 from six. Skeleton Tombstone: 4.8 from 10. Larger samples are more informative, but average ratings are not demand forecasts.
A38: New-product commitments | B38: Mandatory order quantities are not optional. Rejecting the Dragon reflects a $10.8m unproven purchase commitment, not poor modeled profit. Bluetooth fog asks for 20,000 units despite old fog selling only 8,000 at full price.
A39: Source conflict | B39: Sitcom Character requires two facings. Existing Animated Reaper requires one. Use the numeric required-facings fields, not the conflicting vendor-sheet merchant note.
... A41: Event requirements | B41: Student instructions: exactly 16 facings; zero to four online-only items; all three categories; AI reflection; no more than 10 slides and eight minutes. Four online items is a maximum, not a requirement.
A45: Demand input check | B45: =IF(AND(COUNT(Assumptions!B7:D9)=9,COUNT(Assumptions!B13:B16)=4,MIN(Assumptions!B7:D9)>=0,MAX(Assumptions!C7:C9)<=1,MAX(Assumptions!D7:D9)<1,MIN(Assumptions!B13:B16)>=0,MAX(Assumptions!B13:B16)<=1),"OK","Fix assumptions") -> OK

Sheet Assortment guide
A2: What is in each assortment?
A4: Each column is a complete alternative lineup. A product can appear in several alternatives. Definitions follow the list.
A6: Product | B6: Balanced | C6: Maximum profit | D6: Lower investment | E6: Team choice
A7: ='Product decisions'!A7 -> 12 ft Giant Skeleton | B7: =SUBSTITUTE(IF('Product decisions'!C7="In-Store","In-Store ("&VLOOKUP(A7,'Source data'!$A$7:$D$32,4,FALSE)&" facings)",'Product decisions'!C7),"(1 facings)","(1 facing)") -> In-Store (3 facings) | C7: =SUBSTITUTE(IF('Product decisions'!H7="In-Store","In-Store ("&VLOOKUP(A7,'Source data'!$A$7:$D$32,4,FALSE)&" facings)",'Product decisions'!H7),"(1 facings)","(1 facing)") -> Online-Only | D7: =SUBSTITUTE(IF('Product decisions'!I7="In-Store","In-Store ("&VLOOKUP(A7,'Source data'!$A$7:$D$32,4,FALSE)&" facings)",'Product decisions'!I7),"(1 facings)","(1 facing)") -> Online-Only | E7: =SUBSTITUTE(IF('Product decisions'!J7="In-Store","In-Store ("&VLOOKUP(A7,'Source data'!$A$7:$D$32,4,FALSE)&" facings)",'Product decisions'!J7),"(1 facings)","(1 facing)") -> In-Store (3 facings)
A8: ='Product decisions'!A8 -> 9 ft Animated Pirate Ship | B8: =SUBSTITUTE(IF('Product decisions'!C8="In-Store","In-Store ("&VLOOKUP(A8,'Source data'!$A$7:$D$32,4,FALSE)&" facings)",'Product decisions'!C8),"(1 facings)","(1 facing)") -> Online-Only | C8: =SUBSTITUTE(IF('Product decisions'!H8="In-Store","In-Store ("&VLOOKUP(A8,'Source data'!$A$7:$D$32,4,FALSE)&" facings)",'Product decisions'!H8),"(1 facings)","(1 facing)") -> Online-Only | D8: =SUBSTITUTE(IF('Product decisions'!I8="In-Store","In-Store ("&VLOOKUP(A8,'Source data'!$A$7:$D$32,4,FALSE)&" facings)",'Product decisions'!I8),"(1 facings)","(1 facing)") -> Removed | E8: =SUBSTITUTE(IF('Product decisions'!J8="In-Store","In-Store ("&VLOOKUP(A8,'Source data'!$A$7:$D$32,4,FALSE)&" facings)",'Product decisions'!J8),"(1 facings)","(1 facing)") -> Online-Only
A9: ='Product decisions'!A9 -> 7 ft Animated Reaper | B9: =SUBSTITUTE(IF('Product decisions'!C9="In-Store","In-Store ("&VLOOKUP(A9,'Source data'!$A$7:$D$32,4,FALSE)&" facings)",'Product decisions'!C9),"(1 facings)","(1 facing)") -> In-Store (1 facing) | C9: =SUBSTITUTE(IF('Product decisions'!H9="In-Store","In-Store ("&VLOOKUP(A9,'Source data'!$A$7:$D$32,4,FALSE)&" facings)",'Product decisions'!H9),"(1 facings)","(1 facing)") -> In-Store (1 facing) | D9: =SUBSTITUTE(IF('Product decisions'!I9="In-Store","In-Store ("&VLOOKUP(A9,'Source data'!$A$7:$D$32,4,FALSE)&" facings)",'Product decisions'!I9),"(1 facings)","(1 facing)") -> In-Store (1 facing) | E9: =SUBSTITUTE(IF('Product decisions'!J9="In-Store","In-Store ("&VLOOKUP(A9,'Source data'!$A$7:$D$32,4,FALSE)&" facings)",'Product decisions'!J9),"(1 facings)","(1 facing)") -> In-Store (1 facing)
A10: ='Product decisions'!A10 -> 5.5 ft LED Skeleton Pony | B10: =SUBSTITUTE(IF('Product decisions'!C10="In-Store","In-Store ("&VLOOKUP(A10,'Source data'!$A$7:$D$32,4,FALSE)&" facings)",'Product decisions'!C10),"(1 facings)","(1 facing)") -> In-Store (1 facing) | C10: =SUBSTITUTE(IF('Product decisions'!H10="In-Store","In-Store ("&VLOOKUP(A10,'Source data'!$A$7:$D$32,4,FALSE)&" facings)",'Product decisions'!H10),"(1 facings)","(1 facing)") -> In-Store (1 facing) | D10: =SUBSTITUTE(IF('Product decisions'!I10="In-Store","In-Store ("&VLOOKUP(A10,'Source data'!$A$7:$D$32,4,FALSE)&" facings)",'Product decisions'!I10),"(1 facings)","(1 facing)") -> In-Store (1 facing) | E10: =SUBSTITUTE(IF('Product decisions'!J10="In-Store","In-Store ("&VLOOKUP(A10,'Source data'!$A$7:$D$32,4,FALSE)&" facings)",'Product decisions'!J10),"(1 facings)","(1 facing)") -> In-Store (1 facing)
A11: ='Product decisions'!A11 -> 10.5 ft Licensed Character Inflatable | B11: =SUBSTITUTE(IF('Product decisions'!C11="In-Store","In-Store ("&VLOOKUP(A11,'Source data'!$A$7:$D$32,4,FALSE)&" facings)",'Product decisions'!C11),"(1 facings)","(1 facing)") -> Removed | C11: =SUBSTITUTE(IF('Product decisions'!H11="In-Store","In-Store ("&VLOOKUP(A11,'Source data'!$A$7:$D$32,4,FALSE)&" facings)",'Product decisions'!H11),"(1 facings)","(1 facing)") -> Removed | D11: =SUBSTITUTE(IF('Product decisions'!I11="In-Store","In-Store ("&VLOOKUP(A11,'Source data'!$A$7:$D$32,4,FALSE)&" facings)",'Product decisions'!I11),"(1 facings)","(1 facing)") -> Removed | E11: =SUBSTITUTE(IF('Product decisions'!J11="In-Store","In-Store ("&VLOOKUP(A11,'Source data'!$A$7:$D$32,4,FALSE)&" facings)",'Product decisions'!J11),"(1 facings)","(1 facing)") -> Removed
A12: ='Product decisions'!A12 -> 9.5 ft Licensed Sandworm Inflatable | B12: =SUBSTITUTE(IF('Product decisions'!C12="In-Store","In-Store ("&VLOOKUP(A12,'Source data'!$A$7:$D$32,4,FALSE)&" facings)",'Product decisions'!C12),"(1 facings)","(1 facing)") -> In-Store (1 facing) | C12: =SUBSTITUTE(IF('Product decisions'!H12="In-Store","In-Store ("&VLOOKUP(A12,'Source data'!$A$7:$D$32,4,FALSE)&" facings)",'Product decisions'!H12),"(1 facings)","(1 facing)") -> Removed | D12: =SUBSTITUTE(IF('Product decisions'!I12="In-Store","In-Store ("&VLOOKUP(A12,'Source data'!$A$7:$D$32,4,FALSE)&" facings)",'Product decisions'!I12),"(1 facings)","(1 facing)") -> Removed | E12: =SUBSTITUTE(IF('Product decisions'!J12="In-Store","In-Store ("&VLOOKUP(A12,'Source data'!$A$7:$D$32,4,FALSE)&" facings)",'Product decisions'!J12),"(1 facings)","(1 facing)") -> In-Store (1 facing)
A13: ='Product decisions'!A13 -> 12 ft Reaper Inflatable | B13: =SUBSTITUTE(IF('Product decisions'!C13="In-Store","In-Store ("&VLOOKUP(A13,'Source data'!$A$7:$D$32,4,FALSE)&" facings)",'Product decisions'!C13),"(1 facings)","(1 facing)") -> Removed | C13: =SUBSTITUTE(IF('Product decisions'!H13="In-Store","In-Store ("&VLOOKUP(A13,'Source data'!$A$7:$D$32,4,FALSE)&" facings)",'Product decisions'!H13),"(1 facings)","(1 facing)") -> Removed | D13: =SUBSTITUTE(IF('Product decisions'!I13="In-Store","In-Store ("&VLOOKUP(A13,'Source data'!$A$7:$D$32,4,FALSE)&" facings)",'Product decisions'!I13),"(1 facings)","(1 facing)") -> Removed | E13: =SUBSTITUTE(IF('Product decisions'!J13="In-Store","In-Store ("&VLOOKUP(A13,'Source data'!$A$7:$D$32,4,FALSE)&" facings)",'Product decisions'!J13),"(1 facings)","(1 facing)") -> Removed
A14: ='Product decisions'!A14 -> 6 ft Scarecrow Inflatable | B14: =SUBSTITUTE(IF('Product decisions'!C14="In-Store","In-Store ("&VLOOKUP(A14,'Source data'!$A$7:$D$32,4,FALSE)&" facings)",'Product decisions'!C14),"(1 facings)","(1 facing)") -> In-Store (1 facing) | C14: =SUBSTITUTE(IF('Product decisions'!H14="In-Store","In-Store ("&VLOOKUP(A14,'Source data'!$A$7:$D$32,4,FALSE)&" facings)",'Product decisions'!H14),"(1 facings)","(1 facing)") -> Removed | D14: =SUBSTITUTE(IF('Product decisions'!I14="In-Store","In-Store ("&VLOOKUP(A14,'Source data'!$A$7:$D$32,4,FALSE)&" facings)",'Product decisions'!I14),"(1 facings)","(1 facing)") -> Removed | E14: =SUBSTITUTE(IF('Product decisions'!J14="In-Store","In-Store ("&VLOOKUP(A14,'Source data'!$A$7:$D$32,4,FALSE)&" facings)",'Product decisions'!J14),"(1 facings)","(1 facing)") -> In-Store (1 facing)
A15: ='Product decisions'!A15 -> 24 in Metal Tombstone | B15: =SUBSTITUTE(IF('Product decisions'!C15="In-Store","In-Store ("&VLOOKUP(A15,'Source data'!$A$7:$D$32,4,FALSE)&" facings)",'Product decisions'!C15),"(1 facings)","(1 facing)") -> In-Store (1 facing) | C15: =SUBSTITUTE(IF('Product decisions'!H15="In-Store","In-Store ("&VLOOKUP(A15,'Source data'!$A$7:$D$32,4,FALSE)&" facings)",'Product decisions'!H15),"(1 facings)","(1 facing)") -> In-Store (1 facing) | D15: =SUBSTITUTE(IF('Product decisions'!I15="In-Store","In-Store ("&VLOOKUP(A15,'Source data'!$A$7:$D$32,4,FALSE)&" facings)",'Product decisions'!I15),"(1 facings)","(1 facing)") -> In-Store (1 facing) | E15: =SUBSTITUTE(IF('Product decisions'!J15="In-Store","In-Store ("&VLOOKUP(A15,'Source data'!$A$7:$D$32,4,FALSE)&" facings)",'Product decisions'!J15),"(1 facings)","(1 facing)") -> In-Store (1 facing)
A16: ='Product decisions'!A16 -> 5 ft Skeleton Tombstone | B16: =SUBSTITUTE(IF('Product decisions'!C16="In-Store","In-Store ("&VLOOKUP(A16,'Source data'!$A$7:$D$32,4,FALSE)&" facings)",'Product decisions'!C16),"(1 facings)","(1 facing)") -> In-Store (1 facing) | C16: =SUBSTITUTE(IF('Product decisions'!H16="In-Store","In-Store ("&VLOOKUP(A16,'Source data'!$A$7:$D$32,4,FALSE)&" facings)",'Product decisions'!H16),"(1 facings)","(1 facing)") -> In-Store (1 facing) | D16: =SUBSTITUTE(IF('Product decisions'!I16="In-Store","In-Store ("&VLOOKUP(A16,'Source data'!$A$7:$D$32,4,FALSE)&" facings)",'Product decisions'!I16),"(1 facings)","(1 facing)") -> In-Store (1 facing) | E16: =SUBSTITUTE(IF('Product decisions'!J16="In-Store","In-Store ("&VLOOKUP(A16,'Source data'!$A$7:$D$32,4,FALSE)&" facings)",'Product decisions'!J16),"(1 facings)","(1 facing)") -> In-Store (1 facing)
A17: ='Product decisions'!A17 -> LED Fog Machine | B17: =SUBSTITUTE(IF('Product decisions'!C17="In-Store","In-Store ("&VLOOKUP(A17,'Source data'!$A$7:$D$32,4,FALSE)&" facings)",'Product decisions'!C17),"(1 facings)","(1 facing)") -> Removed | C17: =SUBSTITUTE(IF('Product decisions'!H17="In-Store","In-Store ("&VLOOKUP(A17,'Source data'!$A$7:$D$32,4,FALSE)&" facings)",'Product decisions'!H17),"(1 facings)","(1 facing)") -> Removed | D17: =SUBSTITUTE(IF('Product decisions'!I17="In-Store","In-Store ("&VLOOKUP(A17,'Source data'!$A$7:$D$32,4,FALSE)&" facings)",'Product decisions'!I17),"(1 facings)","(1 facing)") -> Removed | E17: =SUBSTITUTE(IF('Product decisions'!J17="In-Store","In-Store ("&VLOOKUP(A17,'Source data'!$A$7:$D$32,4,FALSE)&" facings)",'Product decisions'!J17),"(1 facings)","(1 facing)") -> Removed
A18: ='Product decisions'!A18 -> Pathway Light Set (6-piece) | B18: =SUBSTITUTE(IF('Product decisions'!C18="In-Store","In-Store ("&VLOOKUP(A18,'Source data'!$A$7:$D$32,4,FALSE)&" facings)",'Product decisions'!C18),"(1 facings)","(1 facing)") -> In-Store (1 facing) | C18: =SUBSTITUTE(IF('Product decisions'!H18="In-Store","In-Store ("&VLOOKUP(A18,'Source data'!$A$7:$D$32,4,FALSE)&" facings)",'Product decisions'!H18),"(1 facings)","(1 facing)") -> In-Store (1 facing) | D18: =SUBSTITUTE(IF('Product decisions'!I18="In-Store","In-Store ("&VLOOKUP(A18,'Source data'!$A$7:$D$32,4,FALSE)&" facings)",'Product decisions'!I18),"(1 facings)","(1 facing)") -> In-Store (1 facing) | E18: =SUBSTITUTE(IF('Product decisions'!J18="In-Store","In-Store ("&VLOOKUP(A18,'Source data'!$A$7:$D$32,4,FALSE)&" facings)",'Product decisions'!J18),"(1 facings)","(1 facing)") -> In-Store (1 facing)
... A32: ='Product decisions'!A32 -> 24 in Light-Up Pumpkin Stack | B32: =SUBSTITUTE(IF('Product decisions'!C32="In-Store","In-Store ("&VLOOKUP(A32,'Source data'!$A$7:$D$32,4,FALSE)&" facings)",'Product decisions'!C32),"(1 facings)","(1 facing)") -> In-Store (1 facing) | C32: =SUBSTITUTE(IF('Product decisions'!H32="In-Store","In-Store ("&VLOOKUP(A32,'Source data'!$A$7:$D$32,4,FALSE)&" facings)",'Product decisions'!H32),"(1 facings)","(1 facing)") -> In-Store (1 facing) | D32: =SUBSTITUTE(IF('Product decisions'!I32="In-Store","In-Store ("&VLOOKUP(A32,'Source data'!$A$7:$D$32,4,FALSE)&" facings)",'Product decisions'!I32),"(1 facings)","(1 facing)") -> In-Store (1 facing) | E32: =SUBSTITUTE(IF('Product decisions'!J32="In-Store","In-Store ("&VLOOKUP(A32,'Source data'!$A$7:$D$32,4,FALSE)&" facings)",'Product decisions'!J32),"(1 facings)","(1 facing)") -> In-Store (1 facing)
A34: Check | B34: Balanced | C34: Maximum profit | D34: Lower investment | E34: Team choice
A35: Store products | B35: ='Team summary'!B22 -> 13 | C35: ='Team summary'!B23 -> 11 | D35: ='Team summary'!B24 -> 12 | E35: ='Team summary'!B25 -> 13
A36: Store facings: exactly 16 | B36: ='Team summary'!C22 -> 16 | C36: ='Team summary'!C23 -> 16 | D36: ='Team summary'!C24 -> 16 | E36: ='Team summary'!C25 -> 16
A37: Online products: up to 4 | B37: ='Team summary'!D22 -> 4 | C37: ='Team summary'!D23 -> 4 | D37: ='Team summary'!D24 -> 3 | E37: ='Team summary'!D25 -> 4
A40: Meaning | B40: Explanation
A41: Balanced | B41: Recommended complete lineup: weighs profit, inventory spending, price points, themes and store discovery. Keeps the Giant Skeleton in-store and includes affordable inflatables and accessories.
A42: Maximum profit | B42: Complete alternative that maximizes modeled profit after full purchase cost at the original assumptions. No purchase budget. It can favor expensive new products and move the Skeleton online.
A43: Lower investment | B43: Complete alternative that minimizes product purchases while retaining at least 90% of Balanced base-case profit. Uses three online slots under the up-to-four limit.
A44: Team choice | B44: What we decide

Sheet Channel evidence
A2: Where did customers buy last season?
A4: Unit share = channel units ÷ total units sold. Includes full-price and clearance sales. Channel revenue and profit are not supplied.
A6: Product | B6: Store units | C6: Online units | D6: Store share | E6: Online share | F6: Balanced choice | G6: What the channel evidence means
A7: ='Source data'!A7 -> 12 ft Giant Skeleton | B7: ='Source data'!J7 -> 18000 | C7: ='Source data'!K7 -> 22000 | D7: =IF(B7+C7=0,"Not available",B7/(B7+C7)) -> 0.45 | E7: =IF(B7+C7=0,"Not available",C7/(B7+C7)) -> 0.55 | F7: =VLOOKUP(A7,'Product decisions'!$A$7:$C$32,3,FALSE) -> In-Store | G7: 55% online challenges store placement. Balanced keeps this centerpiece in-store for demonstration and possible traffic benefits, which are not measured. Optimized alternatives choose online.
A8: ='Source data'!A8 -> 9 ft Animated Pirate Ship | B8: ='Source data'!J8 -> 2700 | C8: ='Source data'!K8 -> 6300 | D8: =IF(B8+C8=0,"Not available",B8/(B8+C8)) -> 0.3 | E8: =IF(B8+C8=0,"Not available",C8/(B8+C8)) -> 0.7 | F8: =VLOOKUP(A8,'Product decisions'!$A$7:$C$32,3,FALSE) -> Online-Only | G8: 70% online supports moving online and releasing two facings. Reassess order quantity because only 60% sold full price.
A9: ='Source data'!A9 -> 7 ft Animated Reaper | B9: ='Source data'!J9 -> 6000 | C9: ='Source data'!K9 -> 6000 | D9: =IF(B9+C9=0,"Not available",B9/(B9+C9)) -> 0.5 | E9: =IF(B9+C9=0,"Not available",C9/(B9+C9)) -> 0.5 | F9: =VLOOKUP(A9,'Product decisions'!$A$7:$C$32,3,FALSE) -> In-Store | G9: Equal channel split provides no clear winner. One-facing footprint and strong gross profit support in-store placement.
A10: ='Source data'!A10 -> 5.5 ft LED Skeleton Pony | B10: ='Source data'!J10 -> 7700 | C10: ='Source data'!K10 -> 6300 | D10: =IF(B10+C10=0,"Not available",B10/(B10+C10)) -> 0.55 | E10: =IF(B10+C10=0,"Not available",C10/(B10+C10)) -> 0.45 | F10: =VLOOKUP(A10,'Product decisions'!$A$7:$C$32,3,FALSE) -> In-Store | G10: A modest store majority supports keeping it in-store. Investigate the 4.1-star rating from 100 reviews.
A11: ='Source data'!A11 -> 10.5 ft Licensed Character Inflatable | B11: ='Source data'!J11 -> 3200 | C11: ='Source data'!K11 -> 4800 | D11: =IF(B11+C11=0,"Not available",B11/(B11+C11)) -> 0.4 | E11: =IF(B11+C11=0,"Not available",C11/(B11+C11)) -> 0.6 | F11: =VLOOKUP(A11,'Product decisions'!$A$7:$C$32,3,FALSE) -> Removed | G11: Online majority does not fix the 4.2% realized margin. Remove for weak economics rather than use a limited online slot.
A12: ='Source data'!A12 -> 9.5 ft Licensed Sandworm Inflatable | B12: ='Source data'!J12 -> 1750 | C12: ='Source data'!K12 -> 3250 | D12: =IF(B12+C12=0,"Not available",B12/(B12+C12)) -> 0.35 | E12: =IF(B12+C12=0,"Not available",C12/(B12+C12)) -> 0.65 | F12: =VLOOKUP(A12,'Product decisions'!$A$7:$C$32,3,FALSE) -> In-Store | G12: 65% online challenges the Balanced store decision. Keeping a one-facing licensed inflatable in-store is a deliberate variety tradeoff.
A13: ='Source data'!A13 -> 12 ft Reaper Inflatable | B13: ='Source data'!J13 -> 2700 | C13: ='Source data'!K13 -> 3300 | D13: =IF(B13+C13=0,"Not available",B13/(B13+C13)) -> 0.45 | E13: =IF(B13+C13=0,"Not available",C13/(B13+C13)) -> 0.55 | F13: =VLOOKUP(A13,'Product decisions'!$A$7:$C$32,3,FALSE) -> Removed | G13: A slight online majority does not fix 2.5% margin or 50% full-price sell-through. Remove rather than shift weak economics online.
A14: ='Source data'!A14 -> 6 ft Scarecrow Inflatable | B14: ='Source data'!J14 -> 13000 | C14: ='Source data'!K14 -> 7000 | D14: =IF(B14+C14=0,"Not available",B14/(B14+C14)) -> 0.65 | E14: =IF(B14+C14=0,"Not available",C14/(B14+C14)) -> 0.35 | F14: =VLOOKUP(A14,'Product decisions'!$A$7:$C$32,3,FALSE) -> In-Store | G14: 65% store share supports an affordable in-store inflatable. 85% full-price sell-through strengthens the evidence.
A15: ='Source data'!A15 -> 24 in Metal Tombstone | B15: ='Source data'!J15 -> 21000 | C15: ='Source data'!K15 -> 9000 | D15: =IF(B15+C15=0,"Not available",B15/(B15+C15)) -> 0.7 | E15: =IF(B15+C15=0,"Not available",C15/(B15+C15)) -> 0.3 | F15: =VLOOKUP(A15,'Product decisions'!$A$7:$C$32,3,FALSE) -> In-Store | G15: 70% store share supports store discovery and impulse purchases. High margin helps; the five-star average is based on only six reviews.
A16: ='Source data'!A16 -> 5 ft Skeleton Tombstone | B16: ='Source data'!J16 -> 3150 | C16: ='Source data'!K16 -> 3850 | D16: =IF(B16+C16=0,"Not available",B16/(B16+C16)) -> 0.45 | E16: =IF(B16+C16=0,"Not available",C16/(B16+C16)) -> 0.55 | F16: =VLOOKUP(A16,'Product decisions'!$A$7:$C$32,3,FALSE) -> In-Store | G16: A slight online majority is not decisive. Balanced keeps it in-store for one-facing profitability. Its 4.8 average has only 10 reviews.
A17: ='Source data'!A17 -> LED Fog Machine | B17: ='Source data'!J17 -> 15000 | C17: ='Source data'!K17 -> 10000 | D17: =IF(B17+C17=0,"Not available",B17/(B17+C17)) -> 0.6 | E17: =IF(B17+C17=0,"Not available",C17/(B17+C17)) -> 0.4 | F17: =VLOOKUP(A17,'Product decisions'!$A$7:$C$32,3,FALSE) -> Removed | G17: 60% store share tells us where it sold, not whether it sold profitably. Only 32% sold full price; remove for clearance-heavy economics.
A18: ='Source data'!A18 -> Pathway Light Set (6-piece) | B18: ='Source data'!J18 -> 12600 | C18: ='Source data'!K18 -> 5400 | D18: =IF(B18+C18=0,"Not available",B18/(B18+C18)) -> 0.7 | E18: =IF(B18+C18=0,"Not available",C18/(B18+C18)) -> 0.3 | F18: =VLOOKUP(A18,'Product decisions'!$A$7:$C$32,3,FALSE) -> In-Store | G18: 70% store share supports this complementary in-store item. 85% full-price sell-through strengthens the case.
... A22: ='Source data'!A22 -> Halloween Doormat Assortment | B22: ='Source data'!J22 -> 0 | C22: ='Source data'!K22 -> 9000 | D22: =IF(B22+C22=0,"Not available",B22/(B22+C22)) -> 0 | E22: =IF(B22+C22=0,"Not available",C22/(B22+C22)) -> 1 | F22: =VLOOKUP(A22,'Product decisions'!$A$7:$C$32,3,FALSE) -> Removed | G22: Previously online-only. 100% online does not mean strong demand: 45% full-price sell-through and low gross profit support removal.
A23: ='Source data'!A23 -> 14 ft Giant Animated Dragon | B23: Not supplied | C23: Not supplied | D23: Not supplied | E23: Not supplied | F23: =VLOOKUP(A23,'Product decisions'!$A$7:$C$32,3,FALSE) -> Removed | G23: No historical channel sales supplied. Placement is a hypothesis based on footprint, economics and product role. The online demand factor in Assumptions is a model assumption.
A24: ='Source data'!A24 -> 6 ft Licensed Movie Villain | B24: Not supplied | C24: Not supplied | D24: Not supplied | E24: Not supplied | F24: =VLOOKUP(A24,'Product decisions'!$A$7:$C$32,3,FALSE) -> Removed | G24: No historical channel sales supplied. Placement is a hypothesis based on footprint, economics and product role. The online demand factor in Assumptions is a model assumption.
A25: ='Source data'!A25 -> 9 ft Licensed Franchise Inflatable | B25: Not supplied | C25: Not supplied | D25: Not supplied | E25: Not supplied | F25: =VLOOKUP(A25,'Product decisions'!$A$7:$C$32,3,FALSE) -> Removed | G25: No historical channel sales supplied. Placement is a hypothesis based on footprint, economics and product role. The online demand factor in Assumptions is a model assumption.
A26: ='Source data'!A26 -> 7 ft Licensed Sitcom Character | B26: Not supplied | C26: Not supplied | D26: Not supplied | E26: Not supplied | F26: =VLOOKUP(A26,'Product decisions'!$A$7:$C$32,3,FALSE) -> In-Store | G26: No historical channel sales supplied. Placement is a hypothesis based on footprint, economics and product role. The online demand factor in Assumptions is a model assumption.
A27: ='Source data'!A27 -> 8 ft Inflatable Black Cat | B27: Not supplied | C27: Not supplied | D27: Not supplied | E27: Not supplied | F27: =VLOOKUP(A27,'Product decisions'!$A$7:$C$32,3,FALSE) -> In-Store | G27: No historical channel sales supplied. Placement is a hypothesis based on footprint, economics and product role. The online demand factor in Assumptions is a model assumption.
A28: ='Source data'!A28 -> 12 ft Inflatable Haunted Tree | B28: Not supplied | C28: Not supplied | D28: Not supplied | E28: Not supplied | F28: =VLOOKUP(A28,'Product decisions'!$A$7:$C$32,3,FALSE) -> Online-Only | G28: No historical channel sales supplied. Placement is a hypothesis based on footprint, economics and product role. The online demand factor in Assumptions is a model assumption.
A29: ='Source data'!A29 -> Fog Machine w/ Bluetooth Sound | B29: Not supplied | C29: Not supplied | D29: Not supplied | E29: Not supplied | F29: =VLOOKUP(A29,'Product decisions'!$A$7:$C$32,3,FALSE) -> Removed | G29: No historical channel sales supplied. Placement is a hypothesis based on footprint, economics and product role. The online demand factor in Assumptions is a model assumption.
A30: ='Source data'!A30 -> Animated Talking Portrait | B30: Not supplied | C30: Not supplied | D30: Not supplied | E30: Not supplied | F30: =VLOOKUP(A30,'Product decisions'!$A$7:$C$32,3,FALSE) -> In-Store | G30: No historical channel sales supplied. Placement is a hypothesis based on footprint, economics and product role. The online demand factor in Assumptions is a model assumption.
A31: ='Source data'!A31 -> Solar Pathway Ghosts (4-pc) | B31: Not supplied | C31: Not supplied | D31: Not supplied | E31: Not supplied | F31: =VLOOKUP(A31,'Product decisions'!$A$7:$C$32,3,FALSE) -> In-Store | G31: No historical channel sales supplied. Placement is a hypothesis based on footprint, economics and product role. The online demand factor in Assumptions is a model assumption.
A32: ='Source data'!A32 -> 24 in Light-Up Pumpkin Stack | B32: Not supplied | C32: Not supplied | D32: Not supplied | E32: Not supplied | F32: =VLOOKUP(A32,'Product decisions'!$A$7:$C$32,3,FALSE) -> In-Store | G32: No historical channel sales supplied. Placement is a hypothesis based on footprint, economics and product role. The online demand factor in Assumptions is a model assumption.
A35: A channel majority supports a decision; it does not prove demand will transfer when the other channel is removed.
A37: Source: supplied Student Data columns K–L, current rows 6–21; reproduced in Source data columns J–K. New products have no channel history.

Sheet Customer reviews
A2: Customer ratings need a review count
A4: A 4.5 average from 1,200 reviews does not mean 1,200 people each gave 4.5 stars. Individual ratings and review text are not supplied.
A6: Product | B6: Average stars | C6: Review count | D6: Review evidence | E6: Full-price sell-through | F6: Realized margin | G6: Historical gross profit | H6: Return on full purchase cost | I6: Clearance unit profit | J6: Interpretation
A7: 12 ft Giant Skeleton | B7: 4.5 | C7: 1200 | D7: Larger sample | E7: ='Source data'!H7/'Source data'!G7 -> 0.95 | F7: ='Source data'!O7/'Source data'!N7 -> 0.56779007 | G7: ='Source data'!O7 -> 6621000 | H7: ='Source data'!O7/('Source data'!F7*'Source data'!G7) -> 1.3136905 | I7: ='Source data'!E7*Assumptions!$D$7-'Source data'!F7 -> 23.5 | J7: More observations support the average, but reviews are self-selected and do not measure demand or eliminate bias.
A8: 9 ft Animated Pirate Ship | B8: 4.3 | C8: 95 | D8: Larger sample | E8: ='Source data'!H8/'Source data'!G8 -> 0.6 | F8: ='Source data'!O8/'Source data'!N8 -> 0.4235589 | G8: ='Source data'!O8 -> 1216800 | H8: ='Source data'!O8/('Source data'!F8*'Source data'!G8) -> 0.73478261 | I8: ='Source data'!E8*Assumptions!$D$7-'Source data'!F8 -> 15.5 | J8: More observations support the average, but reviews are self-selected and do not measure demand or eliminate bias.
A9: 7 ft Animated Reaper | B9: 4.6 | C9: 265 | D9: Larger sample | E9: ='Source data'!H9/'Source data'!G9 -> 0.85 | F9: ='Source data'!O9/'Source data'!N9 -> 0.58539184 | G9: ='Source data'!O9 -> 1812900 | H9: ='Source data'!O9/('Source data'!F9*'Source data'!G9) -> 1.4119159 | I9: ='Source data'!E9*Assumptions!$D$7-'Source data'!F9 -> 32.5 | J9: More observations support the average, but reviews are self-selected and do not measure demand or eliminate bias.
A10: 5.5 ft LED Skeleton Pony | B10: 4.1 | C10: 100 | D10: Larger sample | E10: ='Source data'!H10/'Source data'!G10 -> 0.8 | F10: ='Source data'!O10/'Source data'!N10 -> 0.63824289 | G10: ='Source data'!O10 -> 1037400 | H10: ='Source data'!O10/('Source data'!F10*'Source data'!G10) -> 1.7642857 | I10: ='Source data'!E10*Assumptions!$D$7-'Source data'!F10 -> 22.5 | J10: More observations support the average, but reviews are self-selected and do not measure demand or eliminate bias.
A11: 10.5 ft Licensed Character Inflatable | B11: 4.8 | C11: 220 | D11: Larger sample | E11: ='Source data'!H11/'Source data'!G11 -> 0.85 | F11: ='Source data'!O11/'Source data'!N11 -> 0.04226374 | G11: ='Source data'!O11 -> 46600 | H11: ='Source data'!O11/('Source data'!F11*'Source data'!G11) -> 0.044128788 | I11: ='Source data'!E11*Assumptions!$D$7-'Source data'!F11 -> -57.5 | J11: More observations support the average, but reviews are self-selected and do not measure demand or eliminate bias.
A12: 9.5 ft Licensed Sandworm Inflatable | B12: 4.7 | C12: 205 | D12: Larger sample | E12: ='Source data'!H12/'Source data'!G12 -> 0.8 | F12: ='Source data'!O12/'Source data'!N12 -> 0.33911607 | G12: ='Source data'!O12 -> 410500 | H12: ='Source data'!O12/('Source data'!F12*'Source data'!G12) -> 0.513125 | I12: ='Source data'!E12*Assumptions!$D$7-'Source data'!F12 -> -25.5 | J12: More observations support the average, but reviews are self-selected and do not measure demand or eliminate bias.
A13: 12 ft Reaper Inflatable | B13: 4.8 | C13: 75 | D13: Larger sample | E13: ='Source data'!H13/'Source data'!G13 -> 0.5 | F13: ='Source data'!O13/'Source data'!N13 -> 0.025210084 | G13: ='Source data'!O13 -> 13500 | H13: ='Source data'!O13/('Source data'!F13*'Source data'!G13) -> 0.025862069 | I13: ='Source data'!E13*Assumptions!$D$7-'Source data'!F13 -> -27.5 | J13: More observations support the average, but reviews are self-selected and do not measure demand or eliminate bias.
A14: 6 ft Scarecrow Inflatable | B14: 4.6 | C14: 60 | D14: Larger sample | E14: ='Source data'!H14/'Source data'!G14 -> 0.85 | F14: ='Source data'!O14/'Source data'!N14 -> 0.35868071 | G14: ='Source data'!O14 -> 391500 | H14: ='Source data'!O14/('Source data'!F14*'Source data'!G14) -> 0.55928571 | I14: ='Source data'!E14*Assumptions!$D$7-'Source data'!F14 -> -5.5 | J14: More observations support the average, but reviews are self-selected and do not measure demand or eliminate bias.
A15: 24 in Metal Tombstone | B15: 5 | C15: 6 | D15: Small sample: fewer than 30 | E15: ='Source data'!H15/'Source data'!G15 -> 0.8 | F15: ='Source data'!O15/'Source data'!N15 -> 0.81095988 | G15: ='Source data'!O15 -> 546960 | H15: ='Source data'!O15/('Source data'!F15*'Source data'!G15) -> 4.2898824 | I15: ='Source data'!E15*Assumptions!$D$7-'Source data'!F15 -> 8.24 | J15: Treat the high average cautiously. The 30-review cutoff is a display heuristic, not a statistical confidence test.
A16: 5 ft Skeleton Tombstone | B16: 4.8 | C16: 10 | D16: Small sample: fewer than 30 | E16: ='Source data'!H16/'Source data'!G16 -> 0.8 | F16: ='Source data'!O16/'Source data'!N16 -> 0.61222968 | G16: ='Source data'!O16 -> 574700 | H16: ='Source data'!O16/('Source data'!F16*'Source data'!G16) -> 1.5788462 | I16: ='Source data'!E16*Assumptions!$D$7-'Source data'!F16 -> 22.5 | J16: Treat the high average cautiously. The 30-review cutoff is a display heuristic, not a statistical confidence test.
A17: LED Fog Machine | B17: 4.2 | C17: 3400 | D17: Larger sample | E17: ='Source data'!H17/'Source data'!G17 -> 0.32 | F17: ='Source data'!O17/'Source data'!N17 -> 0.049820236 | G17: ='Source data'!O17 -> 48500 | H17: ='Source data'!O17/('Source data'!F17*'Source data'!G17) -> 0.052432432 | I17: ='Source data'!E17*Assumptions!$D$7-'Source data'!F17 -> -7.5 | J17: More observations support the average, but reviews are self-selected and do not measure demand or eliminate bias.
A18: Pathway Light Set (6-piece) | B18: 4.4 | C18: 480 | D18: Larger sample | E18: ='Source data'!H18/'Source data'!G18 -> 0.85 | F18: ='Source data'!O18/'Source data'!N18 -> 0.6291317 | G18: ='Source data'!O18 -> 366417 | H18: ='Source data'!O18/('Source data'!F18*'Source data'!G18) -> 1.696375 | I18: ='Source data'!E18*Assumptions!$D$7-'Source data'!F18 -> 5.49 | J18: More observations support the average, but reviews are self-selected and do not measure demand or eliminate bias.
... A22: Halloween Doormat Assortment | B22: 4 | C22: 55 | D22: Larger sample | E22: ='Source data'!H22/'Source data'!G22 -> 0.45 | F22: ='Source data'!O22/'Source data'!N22 -> 0.17158538 | G22: ='Source data'!O22 -> 22369.5 | H22: ='Source data'!O22/('Source data'!F22*'Source data'!G22) -> 0.207125 | I22: ='Source data'!E22*Assumptions!$D$7-'Source data'!F22 -> -2.01 | J22: More observations support the average, but reviews are self-selected and do not measure demand or eliminate bias.
A23: 14 ft Giant Animated Dragon | D23: No reviews supplied | I23: ='Source data'!E23*Assumptions!$D$7-'Source data'!F23 -> -15.5 | J23: Unproven demand; vendor enthusiasm is not customer evidence.
A24: 6 ft Licensed Movie Villain | D24: No reviews supplied | I24: ='Source data'!E24*Assumptions!$D$7-'Source data'!F24 -> -50.5 | J24: Unproven demand; vendor enthusiasm is not customer evidence.
A25: 9 ft Licensed Franchise Inflatable | D25: No reviews supplied | I25: ='Source data'!E25*Assumptions!$D$7-'Source data'!F25 -> -58.5 | J25: Unproven demand; vendor enthusiasm is not customer evidence.
A26: 7 ft Licensed Sitcom Character | D26: No reviews supplied | I26: ='Source data'!E26*Assumptions!$D$7-'Source data'!F26 -> -24.5 | J26: Unproven demand; vendor enthusiasm is not customer evidence.
A27: 8 ft Inflatable Black Cat | D27: No reviews supplied | I27: ='Source data'!E27*Assumptions!$D$7-'Source data'!F27 -> -0.5 | J27: Unproven demand; vendor enthusiasm is not customer evidence.
A28: 12 ft Inflatable Haunted Tree | D28: No reviews supplied | I28: ='Source data'!E28*Assumptions!$D$7-'Source data'!F28 -> 1.5 | J28: Unproven demand; vendor enthusiasm is not customer evidence.
A29: Fog Machine w/ Bluetooth Sound | D29: No reviews supplied | I29: ='Source data'!E29*Assumptions!$D$7-'Source data'!F29 -> -7.5 | J29: Unproven demand; vendor enthusiasm is not customer evidence.
A30: Animated Talking Portrait | D30: No reviews supplied | I30: ='Source data'!E30*Assumptions!$D$7-'Source data'!F30 -> 12.99 | J30: Unproven demand; vendor enthusiasm is not customer evidence.
A31: Solar Pathway Ghosts (4-pc) | D31: No reviews supplied | I31: ='Source data'!E31*Assumptions!$D$7-'Source data'!F31 -> 6.49 | J31: Unproven demand; vendor enthusiasm is not customer evidence.
A32: 24 in Light-Up Pumpkin Stack | D32: No reviews supplied | I32: ='Source data'!E32*Assumptions!$D$7-'Source data'!F32 -> 5.99 | J32: Unproven demand; vendor enthusiasm is not customer evidence.

Sheet New product risk
A2: New products: purchase commitments and clearance risk
A4: Base and downside below assume in-store placement for comparison. Actual online economics appear in Profit model. All new ratings are unavailable.
A6: Product | B6: Mandatory units | C6: Minimum product cost | D6: Full-price margin | E6: Half-price unit profit | F6: Base profit: store | G6: Downside profit: store | H6: Downside unsold cost | I6: Full-price break-even share | J6: Balanced decision
A7: ='Source data'!A23 -> 14 ft Giant Animated Dragon | B7: ='Source data'!G23 -> 45000 | C7: ='Source data'!F23*'Source data'!G23 -> 10800000 | D7: =1-'Source data'!F23/'Source data'!E23 -> 0.46547884 | E7: ='Source data'!E23*Assumptions!$D$7-'Source data'!F23 -> -15.5 | F7: ='Profit model'!N39 -> 7384500 | G7: ='Profit model'!N91 -> 2737350 | H7: ='Profit model'!O91 -> 2376000 | I7: =MAX(0,('Source data'!F23/'Source data'!E23-Assumptions!$D$7)/(1-Assumptions!$D$7)) -> 0.069042316 | J7: =VLOOKUP(A7,'Product decisions'!$A$7:$C$32,3,FALSE) -> Removed
A8: ='Source data'!A24 -> 6 ft Licensed Movie Villain | B8: ='Source data'!G24 -> 14000 | C8: ='Source data'!F24*'Source data'!G24 -> 3010000 | D8: =1-'Source data'!F24/'Source data'!E24 -> 0.34650456 | E8: ='Source data'!E24*Assumptions!$D$7-'Source data'!F24 -> -50.5 | F8: ='Profit model'!N41 -> 1135400 | G8: ='Profit model'!N93 -> 76020 | H8: ='Profit model'!O93 -> 662200 | I8: =MAX(0,('Source data'!F24/'Source data'!E24-Assumptions!$D$7)/(1-Assumptions!$D$7)) -> 0.30699088 | J8: =VLOOKUP(A8,'Product decisions'!$A$7:$C$32,3,FALSE) -> Removed
A9: ='Source data'!A25 -> 9 ft Licensed Franchise Inflatable | B9: ='Source data'!G25 -> 12000 | C9: ='Source data'!F25*'Source data'!G25 -> 1656000 | D9: =1-'Source data'!F25/'Source data'!E25 -> 0.13207547 | E9: ='Source data'!E25*Assumptions!$D$7-'Source data'!F25 -> -58.5 | F9: ='Profit model'!N43 -> 61200 | G9: ='Profit model'!N95 -> -377640 | H9: ='Profit model'!O95 -> 364320 | I9: =MAX(0,('Source data'!F25/'Source data'!E25-Assumptions!$D$7)/(1-Assumptions!$D$7)) -> 0.73584906 | J9: =VLOOKUP(A9,'Product decisions'!$A$7:$C$32,3,FALSE) -> Removed
A10: ='Source data'!A26 -> 7 ft Licensed Sitcom Character | B10: ='Source data'!G26 -> 9000 | C10: ='Source data'!F26*'Source data'!G26 -> 1476000 | D10: =1-'Source data'!F26/'Source data'!E26 -> 0.41218638 | E10: ='Source data'!E26*Assumptions!$D$7-'Source data'!F26 -> -24.5 | F10: ='Profit model'!N45 -> 783900 | G10: ='Profit model'!N97 -> 206370 | H10: ='Profit model'!O97 -> 324720 | I10: =MAX(0,('Source data'!F26/'Source data'!E26-Assumptions!$D$7)/(1-Assumptions!$D$7)) -> 0.17562724 | J10: =VLOOKUP(A10,'Product decisions'!$A$7:$C$32,3,FALSE) -> In-Store
A11: ='Source data'!A27 -> 8 ft Inflatable Black Cat | B11: ='Source data'!G27 -> 16000 | C11: ='Source data'!F27*'Source data'!G27 -> 640000 | D11: =1-'Source data'!F27/'Source data'!E27 -> 0.49367089 | E11: ='Source data'!E27*Assumptions!$D$7-'Source data'!F27 -> -0.5 | F11: ='Profit model'!N47 -> 497600 | G11: ='Profit model'!N99 -> 206880 | H11: ='Profit model'!O99 -> 140800 | I11: =MAX(0,('Source data'!F27/'Source data'!E27-Assumptions!$D$7)/(1-Assumptions!$D$7)) -> 0.012658228 | J11: =VLOOKUP(A11,'Product decisions'!$A$7:$C$32,3,FALSE) -> In-Store
A12: ='Source data'!A28 -> 12 ft Inflatable Haunted Tree | B12: ='Source data'!G28 -> 7000 | C12: ='Source data'!F28*'Source data'!G28 -> 616000 | D12: =1-'Source data'!F28/'Source data'!E28 -> 0.50837989 | E12: ='Source data'!E28*Assumptions!$D$7-'Source data'!F28 -> 1.5 | F12: ='Profit model'!N49 -> 511700 | G12: ='Profit model'!N101 -> 223510 | H12: ='Profit model'!O101 -> 135520 | I12: =MAX(0,('Source data'!F28/'Source data'!E28-Assumptions!$D$7)/(1-Assumptions!$D$7)) -> 0 | J12: =VLOOKUP(A12,'Product decisions'!$A$7:$C$32,3,FALSE) -> Online-Only
A13: ='Source data'!A29 -> Fog Machine w/ Bluetooth Sound | B13: ='Source data'!G29 -> 20000 | C13: ='Source data'!F29*'Source data'!G29 -> 1040000 | D13: =1-'Source data'!F29/'Source data'!E29 -> 0.41573034 | E13: ='Source data'!E29*Assumptions!$D$7-'Source data'!F29 -> -7.5 | F13: ='Profit model'!N51 -> 562000 | G13: ='Profit model'!N103 -> 152600 | H13: ='Profit model'!O103 -> 228800 | I13: =MAX(0,('Source data'!F29/'Source data'!E29-Assumptions!$D$7)/(1-Assumptions!$D$7)) -> 0.16853933 | J13: =VLOOKUP(A13,'Product decisions'!$A$7:$C$32,3,FALSE) -> Removed
A14: ='Source data'!A30 -> Animated Talking Portrait | B14: ='Source data'!G30 -> 9000 | C14: ='Source data'!F30*'Source data'!G30 -> 63000 | D14: =1-'Source data'!F30/'Source data'!E30 -> 0.82491246 | E14: ='Source data'!E30*Assumptions!$D$7-'Source data'!F30 -> 12.99 | F14: ='Profit model'!N53 -> 260838 | G14: ='Profit model'!N105 -> 178079.4 | H14: ='Profit model'!O105 -> 13860 | I14: =MAX(0,('Source data'!F30/'Source data'!E30-Assumptions!$D$7)/(1-Assumptions!$D$7)) -> 0 | J14: =VLOOKUP(A14,'Product decisions'!$A$7:$C$32,3,FALSE) -> In-Store
A15: ='Source data'!A31 -> Solar Pathway Ghosts (4-pc) | B15: ='Source data'!G31 -> 12000 | C15: ='Source data'!F31*'Source data'!G31 -> 192000 | D15: =1-'Source data'!F31/'Source data'!E31 -> 0.64428635 | E15: ='Source data'!E31*Assumptions!$D$7-'Source data'!F31 -> 6.49 | F15: ='Profit model'!N55 -> 293784 | G15: ='Profit model'!N107 -> 169639.2 | H15: ='Profit model'!O107 -> 42240 | I15: =MAX(0,('Source data'!F31/'Source data'!E31-Assumptions!$D$7)/(1-Assumptions!$D$7)) -> 0 | J15: =VLOOKUP(A15,'Product decisions'!$A$7:$C$32,3,FALSE) -> In-Store
A16: ='Source data'!A32 -> 24 in Light-Up Pumpkin Stack | B16: ='Source data'!G32 -> 22000 | C16: ='Source data'!F32*'Source data'!G32 -> 198000 | D16: =1-'Source data'!F32/'Source data'!E32 -> 0.69979987 | E16: ='Source data'!E32*Assumptions!$D$7-'Source data'!F32 -> 5.99 | F16: ='Profit model'!N57 -> 395604 | G16: ='Profit model'!N109 -> 243905.2 | H16: ='Profit model'!O109 -> 43560 | I16: =MAX(0,('Source data'!F32/'Source data'!E32-Assumptions!$D$7)/(1-Assumptions!$D$7)) -> 0 | J16: =VLOOKUP(A16,'Product decisions'!$A$7:$C$32,3,FALSE) -> In-Store
A19: Break-even share assumes the full mandatory purchase sells, with all remaining units cleared at the base clearance price. It excludes operating expenses.
A20: The downside is not a worst case: full-price demand falls 30%, and half of the remaining units sell on clearance. Unsold units have zero assumed recovery.
A21: Minimum product cost stays tied to the supplier minimum; modeled profit and unsold cost use the editable order quantity.

Sheet Profit model
A2: Profit model: product × channel × demand case
A4: Full buy cost includes unsold inventory. Scenario flags link to Product decisions. All demand assumptions link to Assumptions.
A6: Product | B6: Channel | C6: Demand case | D6: Order quantity | E6: Retail price | F6: Unit cost | G6: Full-price demand | H6: Full-price units sold | I6: Clearance units sold | J6: Unsold units | K6: Sales revenue | L6: Full purchase cost | M6: Gross profit: sold units | N6: Profit after full buy cost | O6: Unsold inventory cost | P6: Profit / facing (store) | Q6: Balanced selected | R6: Maximum profit selected | S6: Lower investment selected | T6: Team selected | U6: New purchase cost | V6: Required facings | W6: Average realized margin | X6: Return on buy cost
A7: 12 ft Giant Skeleton | B7: In-Store | C7: Base | D7: =Assumptions!B21 -> 40000 | E7: ='Source data'!E7 -> 299 | F7: ='Source data'!F7 -> 126 | G7: =IF(B7="In-Store",'Source data'!J7+Assumptions!$B$15*'Source data'!K7,'Source data'!K7+Assumptions!$B$15*'Source data'!J7)*'Source data'!H7/'Source data'!G7*Assumptions!B7 -> 27550 | H7: =MIN(D7,G7) -> 27550 | I7: =(D7-H7)*Assumptions!C7 -> 12450 | J7: =D7-H7-I7 -> 0 | K7: =E7*(H7+I7*Assumptions!D7) -> 10098725 | L7: =D7*F7 -> 5040000 | M7: =K7-(H7+I7)*F7 -> 5058725 | N7: =K7-L7 -> 5058725 | O7: =J7*F7 -> 0 | P7: =IF(B7="In-Store",N7/V7,0) -> 1686241.7 | Q7: =COUNTIFS('Product decisions'!$A$7:$A$32,A7,'Product decisions'!$C$7:$C$32,B7) -> 1 | R7: =COUNTIFS('Product decisions'!$A$7:$A$32,A7,'Product decisions'!$H$7:$H$32,B7) -> 0 | S7: =COUNTIFS('Product decisions'!$A$7:$A$32,A7,'Product decisions'!$I$7:$I$32,B7) -> 0 | T7: =COUNTIFS('Product decisions'!$A$7:$A$32,A7,'Product decisions'!$J$7:$J$32,B7) -> 1 | U7: =0 -> 0 | V7: ='Source data'!D7 -> 3 | W7: =IF(K7=0,0,N7/K7) -> 0.5009271 | X7: =IF(L7=0,0,N7/L7) -> 1.0037153
A8: 12 ft Giant Skeleton | B8: Online-Only | C8: Base | D8: =Assumptions!B21 -> 40000 | E8: ='Source data'!E7 -> 299 | F8: ='Source data'!F7 -> 126 | G8: =IF(B8="In-Store",'Source data'!J7+Assumptions!$B$15*'Source data'!K7,'Source data'!K7+Assumptions!$B$15*'Source data'!J7)*'Source data'!H7/'Source data'!G7*Assumptions!B7 -> 29450 | H8: =MIN(D8,G8) -> 29450 | I8: =(D8-H8)*Assumptions!C7 -> 10550 | J8: =D8-H8-I8 -> 0 | K8: =E8*(H8+I8*Assumptions!D7) -> 10382775 | L8: =D8*F8 -> 5040000 | M8: =K8-(H8+I8)*F8 -> 5342775 | N8: =K8-L8 -> 5342775 | O8: =J8*F8 -> 0 | P8: =IF(B8="In-Store",N8/V8,0) -> 0 | Q8: =COUNTIFS('Product decisions'!$A$7:$A$32,A8,'Product decisions'!$C$7:$C$32,B8) -> 0 | R8: =COUNTIFS('Product decisions'!$A$7:$A$32,A8,'Product decisions'!$H$7:$H$32,B8) -> 1 | S8: =COUNTIFS('Product decisions'!$A$7:$A$32,A8,'Product decisions'!$I$7:$I$32,B8) -> 1 | T8: =COUNTIFS('Product decisions'!$A$7:$A$32,A8,'Product decisions'!$J$7:$J$32,B8) -> 0 | U8: =0 -> 0 | V8: ='Source data'!D7 -> 3 | W8: =IF(K8=0,0,N8/K8) -> 0.51458064 | X8: =IF(L8=0,0,N8/L8) -> 1.0600744
A9: 9 ft Animated Pirate Ship | B9: In-Store | C9: Base | D9: =Assumptions!B22 -> 9000 | E9: ='Source data'!E8 -> 399 | F9: ='Source data'!F8 -> 184 | G9: =IF(B9="In-Store",'Source data'!J8+Assumptions!$B$15*'Source data'!K8,'Source data'!K8+Assumptions!$B$15*'Source data'!J8)*'Source data'!H8/'Source data'!G8*Assumptions!B7 -> 3510 | H9: =MIN(D9,G9) -> 3510 | I9: =(D9-H9)*Assumptions!C7 -> 5490 | J9: =D9-H9-I9 -> 0 | K9: =E9*(H9+I9*Assumptions!D7) -> 2495745 | L9: =D9*F9 -> 1656000 | M9: =K9-(H9+I9)*F9 -> 839745 | N9: =K9-L9 -> 839745 | O9: =J9*F9 -> 0 | P9: =IF(B9="In-Store",N9/V9,0) -> 419872.5 | Q9: =COUNTIFS('Product decisions'!$A$7:$A$32,A9,'Product decisions'!$C$7:$C$32,B9) -> 0 | R9: =COUNTIFS('Product decisions'!$A$7:$A$32,A9,'Product decisions'!$H$7:$H$32,B9) -> 0 | S9: =COUNTIFS('Product decisions'!$A$7:$A$32,A9,'Product decisions'!$I$7:$I$32,B9) -> 0 | T9: =COUNTIFS('Product decisions'!$A$7:$A$32,A9,'Product decisions'!$J$7:$J$32,B9) -> 0 | U9: =0 -> 0 | V9: ='Source data'!D8 -> 2 | W9: =IF(K9=0,0,N9/K9) -> 0.33647067 | X9: =IF(L9=0,0,N9/L9) -> 0.50709239
A10: 9 ft Animated Pirate Ship | B10: Online-Only | C10: Base | D10: =Assumptions!B22 -> 9000 | E10: ='Source data'!E8 -> 399 | F10: ='Source data'!F8 -> 184 | G10: =IF(B10="In-Store",'Source data'!J8+Assumptions!$B$15*'Source data'!K8,'Source data'!K8+Assumptions!$B$15*'Source data'!J8)*'Source data'!H8/'Source data'!G8*Assumptions!B7 -> 4590 | H10: =MIN(D10,G10) -> 4590 | I10: =(D10-H10)*Assumptions!C7 -> 4410 | J10: =D10-H10-I10 -> 0 | K10: =E10*(H10+I10*Assumptions!D7) -> 2711205 | L10: =D10*F10 -> 1656000 | M10: =K10-(H10+I10)*F10 -> 1055205 | N10: =K10-L10 -> 1055205 | O10: =J10*F10 -> 0 | P10: =IF(B10="In-Store",N10/V10,0) -> 0 | Q10: =COUNTIFS('Product decisions'!$A$7:$A$32,A10,'Product decisions'!$C$7:$C$32,B10) -> 1 | R10: =COUNTIFS('Product decisions'!$A$7:$A$32,A10,'Product decisions'!$H$7:$H$32,B10) -> 1 | S10: =COUNTIFS('Product decisions'!$A$7:$A$32,A10,'Product decisions'!$I$7:$I$32,B10) -> 0 | T10: =COUNTIFS('Product decisions'!$A$7:$A$32,A10,'Product decisions'!$J$7:$J$32,B10) -> 1 | U10: =0 -> 0 | V10: ='Source data'!D8 -> 2 | W10: =IF(K10=0,0,N10/K10) -> 0.38920148 | X10: =IF(L10=0,0,N10/L10) -> 0.63720109
A11: 7 ft Animated Reaper | B11: In-Store | C11: Base | D11: =Assumptions!B23 -> 12000 | E11: ='Source data'!E9 -> 279 | F11: ='Source data'!F9 -> 107 | G11: =IF(B11="In-Store",'Source data'!J9+Assumptions!$B$15*'Source data'!K9,'Source data'!K9+Assumptions!$B$15*'Source data'!J9)*'Source data'!H9/'Source data'!G9*Assumptions!B7 -> 7650 | H11: =MIN(D11,G11) -> 7650 | I11: =(D11-H11)*Assumptions!C7 -> 4350 | J11: =D11-H11-I11 -> 0 | K11: =E11*(H11+I11*Assumptions!D7) -> 2741175 | L11: =D11*F11 -> 1284000 | M11: =K11-(H11+I11)*F11 -> 1457175 | N11: =K11-L11 -> 1457175 | O11: =J11*F11 -> 0 | P11: =IF(B11="In-Store",N11/V11,0) -> 1457175 | Q11: =COUNTIFS('Product decisions'!$A$7:$A$32,A11,'Product decisions'!$C$7:$C$32,B11) -> 1 | R11: =COUNTIFS('Product decisions'!$A$7:$A$32,A11,'Product decisions'!$H$7:$H$32,B11) -> 1 | S11: =COUNTIFS('Product decisions'!$A$7:$A$32,A11,'Product decisions'!$I$7:$I$32,B11) -> 1 | T11: =COUNTIFS('Product decisions'!$A$7:$A$32,A11,'Product decisions'!$J$7:$J$32,B11) -> 1 | U11: =0 -> 0 | V11: ='Source data'!D9 -> 1 | W11: =IF(K11=0,0,N11/K11) -> 0.53158773 | X11: =IF(L11=0,0,N11/L11) -> 1.1348715
A12: 7 ft Animated Reaper | B12: Online-Only | C12: Base | D12: =Assumptions!B23 -> 12000 | E12: ='Source data'!E9 -> 279 | F12: ='Source data'!F9 -> 107 | G12: =IF(B12="In-Store",'Source data'!J9+Assumptions!$B$15*'Source data'!K9,'Source data'!K9+Assumptions!$B$15*'Source data'!J9)*'Source data'!H9/'Source data'!G9*Assumptions!B7 -> 7650 | H12: =MIN(D12,G12) -> 7650 | I12: =(D12-H12)*Assumptions!C7 -> 4350 | J12: =D12-H12-I12 -> 0 | K12: =E12*(H12+I12*Assumptions!D7) -> 2741175 | L12: =D12*F12 -> 1284000 | M12: =K12-(H12+I12)*F12 -> 1457175 | N12: =K12-L12 -> 1457175 | O12: =J12*F12 -> 0 | P12: =IF(B12="In-Store",N12/V12,0) -> 0 | Q12: =COUNTIFS('Product decisions'!$A$7:$A$32,A12,'Product decisions'!$C$7:$C$32,B12) -> 0 | R12: =COUNTIFS('Product decisions'!$A$7:$A$32,A12,'Product decisions'!$H$7:$H$32,B12) -> 0 | S12: =COUNTIFS('Product decisions'!$A$7:$A$32,A12,'Product decisions'!$I$7:$I$32,B12) -> 0 | T12: =COUNTIFS('Product decisions'!$A$7:$A$32,A12,'Product decisions'!$J$7:$J$32,B12) -> 0 | U12: =0 -> 0 | V12: ='Source data'!D9 -> 1 | W12: =IF(K12=0,0,N12/K12) -> 0.53158773 | X12: =IF(L12=0,0,N12/L12) -> 1.1348715
A13: 5.5 ft LED Skeleton Pony | B13: In-Store | C13: Base | D13: =Assumptions!B24 -> 14000 | E13: ='Source data'!E10 -> 129 | F13: ='Source data'!F10 -> 42 | G13: =IF(B13="In-Store",'Source data'!J10+Assumptions!$B$15*'Source data'!K10,'Source data'!K10+Assumptions!$B$15*'Source data'!J10)*'Source data'!H10/'Source data'!G10*Assumptions!B7 -> 8680 | H13: =MIN(D13,G13) -> 8680 | I13: =(D13-H13)*Assumptions!C7 -> 5320 | J13: =D13-H13-I13 -> 0 | K13: =E13*(H13+I13*Assumptions!D7) -> 1462860 | L13: =D13*F13 -> 588000 | M13: =K13-(H13+I13)*F13 -> 874860 | N13: =K13-L13 -> 874860 | O13: =J13*F13 -> 0 | P13: =IF(B13="In-Store",N13/V13,0) -> 874860 | Q13: =COUNTIFS('Product decisions'!$A$7:$A$32,A13,'Product decisions'!$C$7:$C$32,B13) -> 1 | R13: =COUNTIFS('Product decisions'!$A$7:$A$32,A13,'Product decisions'!$H$7:$H$32,B13) -> 1 | S13: =COUNTIFS('Product decisions'!$A$7:$A$32,A13,'Product decisions'!$I$7:$I$32,B13) -> 1 | T13: =COUNTIFS('Product decisions'!$A$7:$A$32,A13,'Product decisions'!$J$7:$J$32,B13) -> 1 | U13: =0 -> 0 | V13: ='Source data'!D10 -> 1 | W13: =IF(K13=0,0,N13/K13) -> 0.59804766 | X13: =IF(L13=0,0,N13/L13) -> 1.4878571
A14: 5.5 ft LED Skeleton Pony | B14: Online-Only | C14: Base | D14: =Assumptions!B24 -> 14000 | E14: ='Source data'!E10 -> 129 | F14: ='Source data'!F10 -> 42 | G14: =IF(B14="In-Store",'Source data'!J10+Assumptions!$B$15*'Source data'!K10,'Source data'!K10+Assumptions!$B$15*'Source data'!J10)*'Source data'!H10/'Source data'!G10*Assumptions!B7 -> 8120 | H14: =MIN(D14,G14) -> 8120 | I14: =(D14-H14)*Assumptions!C7 -> 5880 | J14: =D14-H14-I14 -> 0 | K14: =E14*(H14+I14*Assumptions!D7) -> 1426740 | L14: =D14*F14 -> 588000 | M14: =K14-(H14+I14)*F14 -> 838740 | N14: =K14-L14 -> 838740 | O14: =J14*F14 -> 0 | P14: =IF(B14="In-Store",N14/V14,0) -> 0 | Q14: =COUNTIFS('Product decisions'!$A$7:$A$32,A14,'Product decisions'!$C$7:$C$32,B14) -> 0 | R14: =COUNTIFS('Product decisions'!$A$7:$A$32,A14,'Product decisions'!$H$7:$H$32,B14) -> 0 | S14: =COUNTIFS('Product decisions'!$A$7:$A$32,A14,'Product decisions'!$I$7:$I$32,B14) -> 0 | T14: =COUNTIFS('Product decisions'!$A$7:$A$32,A14,'Product decisions'!$J$7:$J$32,B14) -> 0 | U14: =0 -> 0 | V14: ='Source data'!D10 -> 1 | W14: =IF(K14=0,0,N14/K14) -> 0.58787165 | X14: =IF(L14=0,0,N14/L14) -> 1.4264286
A15: 10.5 ft Licensed Character Inflatable | B15: In-Store | C15: Base | D15: =Assumptions!B25 -> 8000 | E15: ='Source data'!E11 -> 149 | F15: ='Source data'!F11 -> 132 | G15: =IF(B15="In-Store",'Source data'!J11+Assumptions!$B$15*'Source data'!K11,'Source data'!K11+Assumptions!$B$15*'Source data'!J11)*'Source data'!H11/'Source data'!G11*Assumptions!B7 -> 4760 | H15: =MIN(D15,G15) -> 4760 | I15: =(D15-H15)*Assumptions!C7 -> 3240 | J15: =D15-H15-I15 -> 0 | K15: =E15*(H15+I15*Assumptions!D7) -> 950620 | L15: =D15*F15 -> 1056000 | M15: =K15-(H15+I15)*F15 -> -105380 | N15: =K15-L15 -> -105380 | O15: =J15*F15 -> 0 | P15: =IF(B15="In-Store",N15/V15,0) -> -52690 | Q15: =COUNTIFS('Product decisions'!$A$7:$A$32,A15,'Product decisions'!$C$7:$C$32,B15) -> 0 | R15: =COUNTIFS('Product decisions'!$A$7:$A$32,A15,'Product decisions'!$H$7:$H$32,B15) -> 0 | S15: =COUNTIFS('Product decisions'!$A$7:$A$32,A15,'Product decisions'!$I$7:$I$32,B15) -> 0 | T15: =COUNTIFS('Product decisions'!$A$7:$A$32,A15,'Product decisions'!$J$7:$J$32,B15) -> 0 | U15: =0 -> 0 | V15: ='Source data'!D11 -> 2 | W15: =IF(K15=0,0,N15/K15) -> -0.11085397 | X15: =IF(L15=0,0,N15/L15) -> -0.099791667
A16: 10.5 ft Licensed Character Inflatable | B16: Online-Only | C16: Base | D16: =Assumptions!B25 -> 8000 | E16: ='Source data'!E11 -> 149 | F16: ='Source data'!F11 -> 132 | G16: =IF(B16="In-Store",'Source data'!J11+Assumptions!$B$15*'Source data'!K11,'Source data'!K11+Assumptions!$B$15*'Source data'!J11)*'Source data'!H11/'Source data'!G11*Assumptions!B7 -> 5440 | H16: =MIN(D16,G16) -> 5440 | I16: =(D16-H16)*Assumptions!C7 -> 2560 | J16: =D16-H16-I16 -> 0 | K16: =E16*(H16+I16*Assumptions!D7) -> 1001280 | L16: =D16*F16 -> 1056000 | M16: =K16-(H16+I16)*F16 -> -54720 | N16: =K16-L16 -> -54720 | O16: =J16*F16 -> 0 | P16: =IF(B16="In-Store",N16/V16,0) -> 0 | Q16: =COUNTIFS('Product decisions'!$A$7:$A$32,A16,'Product decisions'!$C$7:$C$32,B16) -> 0 | R16: =COUNTIFS('Product decisions'!$A$7:$A$32,A16,'Product decisions'!$H$7:$H$32,B16) -> 0 | S16: =COUNTIFS('Product decisions'!$A$7:$A$32,A16,'Product decisions'!$I$7:$I$32,B16) -> 0 | T16: =COUNTIFS('Product decisions'!$A$7:$A$32,A16,'Product decisions'!$J$7:$J$32,B16) -> 0 | U16: =0 -> 0 | V16: ='Source data'!D11 -> 2 | W16: =IF(K16=0,0,N16/K16) -> -0.054650048 | X16: =IF(L16=0,0,N16/L16) -> -0.051818182
A17: 9.5 ft Licensed Sandworm Inflatable | B17: In-Store | C17: Base | D17: =Assumptions!B26 -> 5000 | E17: ='Source data'!E12 -> 269 | F17: ='Source data'!F12 -> 160 | G17: =IF(B17="In-Store",'Source data'!J12+Assumptions!$B$15*'Source data'!K12,'Source data'!K12+Assumptions!$B$15*'Source data'!J12)*'Source data'!H12/'Source data'!G12*Assumptions!B7 -> 2700 | H17: =MIN(D17,G17) -> 2700 | I17: =(D17-H17)*Assumptions!C7 -> 2300 | J17: =D17-H17-I17 -> 0 | K17: =E17*(H17+I17*Assumptions!D7) -> 1035650 | L17: =D17*F17 -> 800000 | M17: =K17-(H17+I17)*F17 -> 235650 | N17: =K17-L17 -> 235650 | O17: =J17*F17 -> 0 | P17: =IF(B17="In-Store",N17/V17,0) -> 235650 | Q17: =COUNTIFS('Product decisions'!$A$7:$A$32,A17,'Product decisions'!$C$7:$C$32,B17) -> 1 | R17: =COUNTIFS('Product decisions'!$A$7:$A$32,A17,'Product decisions'!$H$7:$H$32,B17) -> 0 | S17: =COUNTIFS('Product decisions'!$A$7:$A$32,A17,'Product decisions'!$I$7:$I$32,B17) -> 0 | T17: =COUNTIFS('Product decisions'!$A$7:$A$32,A17,'Product decisions'!$J$7:$J$32,B17) -> 1 | U17: =0 -> 0 | V17: ='Source data'!D12 -> 1 | W17: =IF(K17=0,0,N17/K17) -> 0.22753826 | X17: =IF(L17=0,0,N17/L17) -> 0.2945625
A18: 9.5 ft Licensed Sandworm Inflatable | B18: Online-Only | C18: Base | D18: =Assumptions!B26 -> 5000 | E18: ='Source data'!E12 -> 269 | F18: ='Source data'!F12 -> 160 | G18: =IF(B18="In-Store",'Source data'!J12+Assumptions!$B$15*'Source data'!K12,'Source data'!K12+Assumptions!$B$15*'Source data'!J12)*'Source data'!H12/'Source data'!G12*Assumptions!B7 -> 3300 | H18: =MIN(D18,G18) -> 3300 | I18: =(D18-H18)*Assumptions!C7 -> 1700 | J18: =D18-H18-I18 -> 0 | K18: =E18*(H18+I18*Assumptions!D7) -> 1116350 | L18: =D18*F18 -> 800000 | M18: =K18-(H18+I18)*F18 -> 316350 | N18: =K18-L18 -> 316350 | O18: =J18*F18 -> 0 | P18: =IF(B18="In-Store",N18/V18,0) -> 0 | Q18: =COUNTIFS('Product decisions'!$A$7:$A$32,A18,'Product decisions'!$C$7:$C$32,B18) -> 0 | R18: =COUNTIFS('Product decisions'!$A$7:$A$32,A18,'Product decisions'!$H$7:$H$32,B18) -> 0 | S18: =COUNTIFS('Product decisions'!$A$7:$A$32,A18,'Product decisions'!$I$7:$I$32,B18) -> 0 | T18: =COUNTIFS('Product decisions'!$A$7:$A$32,A18,'Product decisions'!$J$7:$J$32,B18) -> 0 | U18: =0 -> 0 | V18: ='Source data'!D12 -> 1 | W18: =IF(K18=0,0,N18/K18) -> 0.28337887 | X18: =IF(L18=0,0,N18/L18) -> 0.3954375
A19: 12 ft Reaper Inflatable | B19: In-Store | C19: Base | D19: =Assumptions!B27 -> 6000 | E19: ='Source data'!E13 -> 119 | F19: ='Source data'!F13 -> 87 | G19: =IF(B19="In-Store",'Source data'!J13+Assumptions!$B$15*'Source data'!K13,'Source data'!K13+Assumptions!$B$15*'Source data'!J13)*'Source data'!H13/'Source data'!G13*Assumptions!B7 -> 2175 | H19: =MIN(D19,G19) -> 2175 | I19: =(D19-H19)*Assumptions!C7 -> 3825 | J19: =D19-H19-I19 -> 0 | K19: =E19*(H19+I19*Assumptions!D7) -> 486412.5 | L19: =D19*F19 -> 522000 | M19: =K19-(H19+I19)*F19 -> -35587.5 | N19: =K19-L19 -> -35587.5 | O19: =J19*F19 -> 0 | P19: =IF(B19="In-Store",N19/V19,0) -> -35587.5 | Q19: =COUNTIFS('Product decisions'!$A$7:$A$32,A19,'Product decisions'!$C$7:$C$32,B19) -> 0 | R19: =COUNTIFS('Product decisions'!$A$7:$A$32,A19,'Product decisions'!$H$7:$H$32,B19) -> 0 | S19: =COUNTIFS('Product decisions'!$A$7:$A$32,A19,'Product decisions'!$I$7:$I$32,B19) -> 0 | T19: =COUNTIFS('Product decisions'!$A$7:$A$32,A19,'Product decisions'!$J$7:$J$32,B19) -> 0 | U19: =0 -> 0 | V19: ='Source data'!D13 -> 1 | W19: =IF(K19=0,0,N19/K19) -> -0.07316321 | X19: =IF(L19=0,0,N19/L19) -> -0.068175287
A20: 12 ft Reaper Inflatable | B20: Online-Only | C20: Base | D20: =Assumptions!B27 -> 6000 | E20: ='Source data'!E13 -> 119 | F20: ='Source data'!F13 -> 87 | G20: =IF(B20="In-Store",'Source data'!J13+Assumptions!$B$15*'Source data'!K13,'Source data'!K13+Assumptions!$B$15*'Source data'!J13)*'Source data'!H13/'Source data'!G13*Assumptions!B7 -> 2325 | H20: =MIN(D20,G20) -> 2325 | I20: =(D20-H20)*Assumptions!C7 -> 3675 | J20: =D20-H20-I20 -> 0 | K20: =E20*(H20+I20*Assumptions!D7) -> 495337.5 | L20: =D20*F20 -> 522000 | M20: =K20-(H20+I20)*F20 -> -26662.5 | N20: =K20-L20 -> -26662.5 | O20: =J20*F20 -> 0 | P20: =IF(B20="In-Store",N20/V20,0) -> 0 | Q20: =COUNTIFS('Product decisions'!$A$7:$A$32,A20,'Product decisions'!$C$7:$C$32,B20) -> 0 | R20: =COUNTIFS('Product decisions'!$A$7:$A$32,A20,'Product decisions'!$H$7:$H$32,B20) -> 0 | S20: =COUNTIFS('Product decisions'!$A$7:$A$32,A20,'Product decisions'!$I$7:$I$32,B20) -> 0 | T20: =COUNTIFS('Product decisions'!$A$7:$A$32,A20,'Product decisions'!$J$7:$J$32,B20) -> 0 | U20: =0 -> 0 | V20: ='Source data'!D13 -> 1 | W20: =IF(K20=0,0,N20/K20) -> -0.053826936 | X20: =IF(L20=0,0,N20/L20) -> -0.051077586
A21: 6 ft Scarecrow Inflatable | B21: In-Store | C21: Base | D21: =Assumptions!B28 -> 20000 | E21: ='Source data'!E14 -> 59 | F21: ='Source data'!F14 -> 35 | G21: =IF(B21="In-Store",'Source data'!J14+Assumptions!$B$15*'Source data'!K14,'Source data'!K14+Assumptions!$B$15*'Source data'!J14)*'Source data'!H14/'Source data'!G14*Assumptions!B7 -> 14025 | H21: =MIN(D21,G21) -> 14025 | I21: =(D21-H21)*Assumptions!C7 -> 5975 | J21: =D21-H21-I21 -> 0 | K21: =E21*(H21+I21*Assumptions!D7) -> 1003737.5 | L21: =D21*F21 -> 700000 | M21: =K21-(H21+I21)*F21 -> 303737.5 | N21: =K21-L21 -> 303737.5 | O21: =J21*F21 -> 0 | P21: =IF(B21="In-Store",N21/V21,0) -> 303737.5 | Q21: =COUNTIFS('Product decisions'!$A$7:$A$32,A21,'Product decisions'!$C$7:$C$32,B21) -> 1 | R21: =COUNTIFS('Product decisions'!$A$7:$A$32,A21,'Product decisions'!$H$7:$H$32,B21) -> 0 | S21: =COUNTIFS('Product decisions'!$A$7:$A$32,A21,'Product decisions'!$I$7:$I$32,B21) -> 0 | T21: =COUNTIFS('Product decisions'!$A$7:$A$32,A21,'Product decisions'!$J$7:$J$32,B21) -> 1 | U21: =0 -> 0 | V21: ='Source data'!D14 -> 1 | W21: =IF(K21=0,0,N21/K21) -> 0.30260651 | X21: =IF(L21=0,0,N21/L21) -> 0.43391071
A22: 6 ft Scarecrow Inflatable | B22: Online-Only | C22: Base | D22: =Assumptions!B28 -> 20000 | E22: ='Source data'!E14 -> 59 | F22: ='Source data'!F14 -> 35 | G22: =IF(B22="In-Store",'Source data'!J14+Assumptions!$B$15*'Source data'!K14,'Source data'!K14+Assumptions!$B$15*'Source data'!J14)*'Source data'!H14/'Source data'!G14*Assumptions!B7 -> 11475 | H22: =MIN(D22,G22) -> 11475 | I22: =(D22-H22)*Assumptions!C7 -> 8525 | J22: =D22-H22-I22 -> 0 | K22: =E22*(H22+I22*Assumptions!D7) -> 928512.5 | L22: =D22*F22 -> 700000 | M22: =K22-(H22+I22)*F22 -> 228512.5 | N22: =K22-L22 -> 228512.5 | O22: =J22*F22 -> 0 | P22: =IF(B22="In-Store",N22/V22,0) -> 0 | Q22: =COUNTIFS('Product decisions'!$A$7:$A$32,A22,'Product decisions'!$C$7:$C$32,B22) -> 0 | R22: =COUNTIFS('Product decisions'!$A$7:$A$32,A22,'Product decisions'!$H$7:$H$32,B22) -> 0 | S22: =COUNTIFS('Product decisions'!$A$7:$A$32,A22,'Product decisions'!$I$7:$I$32,B22) -> 0 | T22: =COUNTIFS('Product decisions'!$A$7:$A$32,A22,'Product decisions'!$J$7:$J$32,B22) -> 0 | U22: =0 -> 0 | V22: ='Source data'!D14 -> 1 | W22: =IF(K22=0,0,N22/K22) -> 0.246106 | X22: =IF(L22=0,0,N22/L22) -> 0.32644643
A23: 24 in Metal Tombstone | B23: In-Store | C23: Base | D23: =Assumptions!B29 -> 30000 | E23: ='Source data'!E15 -> 24.98 | F23: ='Source data'!F15 -> 4.25 | G23: =IF(B23="In-Store",'Source data'!J15+Assumptions!$B$15*'Source data'!K15,'Source data'!K15+Assumptions!$B$15*'Source data'!J15)*'Source data'!H15/'Source data'!G15*Assumptions!B7 -> 20400 | H23: =MIN(D23,G23) -> 20400 | I23: =(D23-H23)*Assumptions!C7 -> 9600 | J23: =D23-H23-I23 -> 0 | K23: =E23*(H23+I23*Assumptions!D7) -> 629496 | L23: =D23*F23 -> 127500 | M23: =K23-(H23+I23)*F23 -> 501996 | N23: =K23-L23 -> 501996 | O23: =J23*F23 -> 0 | P23: =IF(B23="In-Store",N23/V23,0) -> 501996 | Q23: =COUNTIFS('Product decisions'!$A$7:$A$32,A23,'Product decisions'!$C$7:$C$32,B23) -> 1 | R23: =COUNTIFS('Product decisions'!$A$7:$A$32,A23,'Product decisions'!$H$7:$H$32,B23) -> 1 | S23: =COUNTIFS('Product decisions'!$A$7:$A$32,A23,'Product decisions'!$I$7:$I$32,B23) -> 1 | T23: =COUNTIFS('Product decisions'!$A$7:$A$32,A23,'Product decisions'!$J$7:$J$32,B23) -> 1 | U23: =0 -> 0 | V23: ='Source data'!D15 -> 1 | W23: =IF(K23=0,0,N23/K23) -> 0.79745701 | X23: =IF(L23=0,0,N23/L23) -> 3.9372235
A24: 24 in Metal Tombstone | B24: Online-Only | C24: Base | D24: =Assumptions!B29 -> 30000 | E24: ='Source data'!E15 -> 24.98 | F24: ='Source data'!F15 -> 4.25 | G24: =IF(B24="In-Store",'Source data'!J15+Assumptions!$B$15*'Source data'!K15,'Source data'!K15+Assumptions!$B$15*'Source data'!J15)*'Source data'!H15/'Source data'!G15*Assumptions!B7 -> 15600 | H24: =MIN(D24,G24) -> 15600 | I24: =(D24-H24)*Assumptions!C7 -> 14400 | J24: =D24-H24-I24 -> 0 | K24: =E24*(H24+I24*Assumptions!D7) -> 569544 | L24: =D24*F24 -> 127500 | M24: =K24-(H24+I24)*F24 -> 442044 | N24: =K24-L24 -> 442044 | O24: =J24*F24 -> 0 | P24: =IF(B24="In-Store",N24/V24,0) -> 0 | Q24: =COUNTIFS('Product decisions'!$A$7:$A$32,A24,'Product decisions'!$C$7:$C$32,B24) -> 0 | R24: =COUNTIFS('Product decisions'!$A$7:$A$32,A24,'Product decisions'!$H$7:$H$32,B24) -> 0 | S24: =COUNTIFS('Product decisions'!$A$7:$A$32,A24,'Product decisions'!$I$7:$I$32,B24) -> 0 | T24: =COUNTIFS('Product decisions'!$A$7:$A$32,A24,'Product decisions'!$J$7:$J$32,B24) -> 0 | U24: =0 -> 0 | V24: ='Source data'!D15 -> 1 | W24: =IF(K24=0,0,N24/K24) -> 0.7761367 | X24: =IF(L24=0,0,N24/L24) -> 3.4670118
A25: 5 ft Skeleton Tombstone | B25: In-Store | C25: Base | D25: =Assumptions!B30 -> 7000 | E25: ='Source data'!E16 -> 149 | F25: ='Source data'!F16 -> 52 | G25: =IF(B25="In-Store",'Source data'!J16+Assumptions!$B$15*'Source data'!K16,'Source data'!K16+Assumptions!$B$15*'Source data'!J16)*'Source data'!H16/'Source data'!G16*Assumptions!B7 -> 4060 | H25: =MIN(D25,G25) -> 4060 | I25: =(D25-H25)*Assumptions!C7 -> 2940 | J25: =D25-H25-I25 -> 0 | K25: =E25*(H25+I25*Assumptions!D7) -> 823970 | L25: =D25*F25 -> 364000 | M25: =K25-(H25+I25)*F25 -> 459970 | N25: =K25-L25 -> 459970 | O25: =J25*F25 -> 0 | P25: =IF(B25="In-Store",N25/V25,0) -> 459970 | Q25: =COUNTIFS('Product decisions'!$A$7:$A$32,A25,'Product decisions'!$C$7:$C$32,B25) -> 1 | R25: =COUNTIFS('Product decisions'!$A$7:$A$32,A25,'Product decisions'!$H$7:$H$32,B25) -> 1 | S25: =COUNTIFS('Product decisions'!$A$7:$A$32,A25,'Product decisions'!$I$7:$I$32,B25) -> 1 | T25: =COUNTIFS('Product decisions'!$A$7:$A$32,A25,'Product decisions'!$J$7:$J$32,B25) -> 1 | U25: =0 -> 0 | V25: ='Source data'!D16 -> 1 | W25: =IF(K25=0,0,N25/K25) -> 0.55823634 | X25: =IF(L25=0,0,N25/L25) -> 1.2636538
A26: 5 ft Skeleton Tombstone | B26: Online-Only | C26: Base | D26: =Assumptions!B30 -> 7000 | E26: ='Source data'!E16 -> 149 | F26: ='Source data'!F16 -> 52 | G26: =IF(B26="In-Store",'Source data'!J16+Assumptions!$B$15*'Source data'!K16,'Source data'!K16+Assumptions!$B$15*'Source data'!J16)*'Source data'!H16/'Source data'!G16*Assumptions!B7 -> 4340 | H26: =MIN(D26,G26) -> 4340 | I26: =(D26-H26)*Assumptions!C7 -> 2660 | J26: =D26-H26-I26 -> 0 | K26: =E26*(H26+I26*Assumptions!D7) -> 844830 | L26: =D26*F26 -> 364000 | M26: =K26-(H26+I26)*F26 -> 480830 | N26: =K26-L26 -> 480830 | O26: =J26*F26 -> 0 | P26: =IF(B26="In-Store",N26/V26,0) -> 0 | Q26: =COUNTIFS('Product decisions'!$A$7:$A$32,A26,'Product decisions'!$C$7:$C$32,B26) -> 0 | R26: =COUNTIFS('Product decisions'!$A$7:$A$32,A26,'Product decisions'!$H$7:$H$32,B26) -> 0 | S26: =COUNTIFS('Product decisions'!$A$7:$A$32,A26,'Product decisions'!$I$7:$I$32,B26) -> 0 | T26: =COUNTIFS('Product decisions'!$A$7:$A$32,A26,'Product decisions'!$J$7:$J$32,B26) -> 0 | U26: =0 -> 0 | V26: ='Source data'!D16 -> 1 | W26: =IF(K26=0,0,N26/K26) -> 0.56914409 | X26: =IF(L26=0,0,N26/L26) -> 1.3209615
A27: LED Fog Machine | B27: In-Store | C27: Base | D27: =Assumptions!B31 -> 25000 | E27: ='Source data'!E17 -> 59 | F27: ='Source data'!F17 -> 37 | G27: =IF(B27="In-Store",'Source data'!J17+Assumptions!$B$15*'Source data'!K17,'Source data'!K17+Assumptions!$B$15*'Source data'!J17)*'Source data'!H17/'Source data'!G17*Assumptions!B7 -> 6400 | H27: =MIN(D27,G27) -> 6400 | I27: =(D27-H27)*Assumptions!C7 -> 18600 | J27: =D27-H27-I27 -> 0 | K27: =E27*(H27+I27*Assumptions!D7) -> 926300 | L27: =D27*F27 -> 925000 | M27: =K27-(H27+I27)*F27 -> 1300 | N27: =K27-L27 -> 1300 | O27: =J27*F27 -> 0 | P27: =IF(B27="In-Store",N27/V27,0) -> 1300 | Q27: =COUNTIFS('Product decisions'!$A$7:$A$32,A27,'Product decisions'!$C$7:$C$32,B27) -> 0 | R27: =COUNTIFS('Product decisions'!$A$7:$A$32,A27,'Product decisions'!$H$7:$H$32,B27) -> 0 | S27: =COUNTIFS('Product decisions'!$A$7:$A$32,A27,'Product decisions'!$I$7:$I$32,B27) -> 0 | T27: =COUNTIFS('Product decisions'!$A$7:$A$32,A27,'Product decisions'!$J$7:$J$32,B27) -> 0 | U27: =0 -> 0 | V27: ='Source data'!D17 -> 1 | W27: =IF(K27=0,0,N27/K27) -> 0.001403433 | X27: =IF(L27=0,0,N27/L27) -> 0.0014054054
A28: LED Fog Machine | B28: Online-Only | C28: Base | D28: =Assumptions!B31 -> 25000 | E28: ='Source data'!E17 -> 59 | F28: ='Source data'!F17 -> 37 | G28: =IF(B28="In-Store",'Source data'!J17+Assumptions!$B$15*'Source data'!K17,'Source data'!K17+Assumptions!$B$15*'Source data'!J17)*'Source data'!H17/'Source data'!G17*Assumptions!B7 -> 5600 | H28: =MIN(D28,G28) -> 5600 | I28: =(D28-H28)*Assumptions!C7 -> 19400 | J28: =D28-H28-I28 -> 0 | K28: =E28*(H28+I28*Assumptions!D7) -> 902700 | L28: =D28*F28 -> 925000 | M28: =K28-(H28+I28)*F28 -> -22300 | N28: =K28-L28 -> -22300 | O28: =J28*F28 -> 0 | P28: =IF(B28="In-Store",N28/V28,0) -> 0 | Q28: =COUNTIFS('Product decisions'!$A$7:$A$32,A28,'Product decisions'!$C$7:$C$32,B28) -> 0 | R28: =COUNTIFS('Product decisions'!$A$7:$A$32,A28,'Product decisions'!$H$7:$H$32,B28) -> 0 | S28: =COUNTIFS('Product decisions'!$A$7:$A$32,A28,'Product decisions'!$I$7:$I$32,B28) -> 0 | T28: =COUNTIFS('Product decisions'!$A$7:$A$32,A28,'Product decisions'!$J$7:$J$32,B28) -> 0 | U28: =0 -> 0 | V28: ='Source data'!D17 -> 1 | W28: =IF(K28=0,0,N28/K28) -> -0.024703667 | X28: =IF(L28=0,0,N28/L28) -> -0.024108108
A29: Pathway Light Set (6-piece) | B29: In-Store | C29: Base | D29: =Assumptions!B32 -> 18000 | E29: ='Source data'!E18 -> 34.98 | F29: ='Source data'!F18 -> 12 | G29: =IF(B29="In-Store",'Source data'!J18+Assumptions!$B$15*'Source data'!K18,'Source data'!K18+Assumptions!$B$15*'Source data'!J18)*'Source data'!H18/'Source data'!G18*Assumptions!B7 -> 13005 | H29: =MIN(D29,G29) -> 13005 | I29: =(D29-H29)*Assumptions!C7 -> 4995 | J29: =D29-H29-I29 -> 0 | K29: =E29*(H29+I29*Assumptions!D7) -> 542277.45 | L29: =D29*F29 -> 216000 | M29: =K29-(H29+I29)*F29 -> 326277.45 | N29: =K29-L29 -> 326277.45 | O29: =J29*F29 -> 0 | P29: =IF(B29="In-Store",N29/V29,0) -> 326277.45 | Q29: =COUNTIFS('Product decisions'!$A$7:$A$32,A29,'Product decisions'!$C$7:$C$32,B29) -> 1 | R29: =COUNTIFS('Product decisions'!$A$7:$A$32,A29,'Product decisions'!$H$7:$H$32,B29) -> 1 | S29: =COUNTIFS('Product decisions'!$A$7:$A$32,A29,'Product decisions'!$I$7:$I$32,B29) -> 1 | T29: =COUNTIFS('Product decisions'!$A$7:$A$32,A29,'Product decisions'!$J$7:$J$32,B29) -> 1 | U29: =0 -> 0 | V29: ='Source data'!D18 -> 1 | W29: =IF(K29=0,0,N29/K29) -> 0.60167991 | X29: =IF(L29=0,0,N29/L29) -> 1.5105438
A30: Pathway Light Set (6-piece) | B30: Online-Only | C30: Base | D30: =Assumptions!B32 -> 18000 | E30: ='Source data'!E18 -> 34.98 | F30: ='Source data'!F18 -> 12 | G30: =IF(B30="In-Store",'Source data'!J18+Assumptions!$B$15*'Source data'!K18,'Source data'!K18+Assumptions!$B$15*'Source data'!J18)*'Source data'!H18/'Source data'!G18*Assumptions!B7 -> 9945 | H30: =MIN(D30,G30) -> 9945 | I30: =(D30-H30)*Assumptions!C7 -> 8055 | J30: =D30-H30-I30 -> 0 | K30: =E30*(H30+I30*Assumptions!D7) -> 488758.05 | L30: =D30*F30 -> 216000 | M30: =K30-(H30+I30)*F30 -> 272758.05 | N30: =K30-L30 -> 272758.05 | O30: =J30*F30 -> 0 | P30: =IF(B30="In-Store",N30/V30,0) -> 0 | Q30: =COUNTIFS('Product decisions'!$A$7:$A$32,A30,'Product decisions'!$C$7:$C$32,B30) -> 0 | R30: =COUNTIFS('Product decisions'!$A$7:$A$32,A30,'Product decisions'!$H$7:$H$32,B30) -> 0 | S30: =COUNTIFS('Product decisions'!$A$7:$A$32,A30,'Product decisions'!$I$7:$I$32,B30) -> 0 | T30: =COUNTIFS('Product decisions'!$A$7:$A$32,A30,'Product decisions'!$J$7:$J$32,B30) -> 0 | U30: =0 -> 0 | V30: ='Source data'!D18 -> 1 | W30: =IF(K30=0,0,N30/K30) -> 0.55806354 | X30: =IF(L30=0,0,N30/L30) -> 1.2627687
A31: 16 ft Inflatable Haunted Archway | B31: In-Store | C31: Base | D31: =Assumptions!B33 -> 6000 | E31: ='Source data'!E19 -> 199 | F31: ='Source data'!F19 -> 95 | G31: =IF(B31="In-Store",'Source data'!J19+Assumptions!$B$15*'Source data'!K19,'Source data'!K19+Assumptions!$B$15*'Source data'!J19)*'Source data'!H19/'Source data'!G19*Assumptions!B7 -> 2550 | H31: =MIN(D31,G31) -> 2550 | I31: =(D31-H31)*Assumptions!C7 -> 3450 | J31: =D31-H31-I31 -> 0 | K31: =E31*(H31+I31*Assumptions!D7) -> 850725 | L31: =D31*F31 -> 570000 | M31: =K31-(H31+I31)*F31 -> 280725 | N31: =K31-L31 -> 280725 | O31: =J31*F31 -> 0 | P31: =IF(B31="In-Store",N31/V31,0) -> 93575 | Q31: =COUNTIFS('Product decisions'!$A$7:$A$32,A31,'Product decisions'!$C$7:$C$32,B31) -> 0 | R31: =COUNTIFS('Product decisions'!$A$7:$A$32,A31,'Product decisions'!$H$7:$H$32,B31) -> 0 | S31: =COUNTIFS('Product decisions'!$A$7:$A$32,A31,'Product decisions'!$I$7:$I$32,B31) -> 1 | T31: =COUNTIFS('Product decisions'!$A$7:$A$32,A31,'Product decisions'!$J$7:$J$32,B31) -> 0 | U31: =0 -> 0 | V31: ='Source data'!D19 -> 3 | W31: =IF(K31=0,0,N31/K31) -> 0.32998325 | X31: =IF(L31=0,0,N31/L31) -> 0.4925
A32: 16 ft Inflatable Haunted Archway | B32: Online-Only | C32: Base | D32: =Assumptions!B33 -> 6000 | E32: ='Source data'!E19 -> 199 | F32: ='Source data'!F19 -> 95 | G32: =IF(B32="In-Store",'Source data'!J19+Assumptions!$B$15*'Source data'!K19,'Source data'!K19+Assumptions!$B$15*'Source data'!J19)*'Source data'!H19/'Source data'!G19*Assumptions!B7 -> 5100 | H32: =MIN(D32,G32) -> 5100 | I32: =(D32-H32)*Assumptions!C7 -> 900 | J32: =D32-H32-I32 -> 0 | K32: =E32*(H32+I32*Assumptions!D7) -> 1104450 | L32: =D32*F32 -> 570000 | M32: =K32-(H32+I32)*F32 -> 534450 | N32: =K32-L32 -> 534450 | O32: =J32*F32 -> 0 | P32: =IF(B32="In-Store",N32/V32,0) -> 0 | Q32: =COUNTIFS('Product decisions'!$A$7:$A$32,A32,'Product decisions'!$C$7:$C$32,B32) -> 1 | R32: =COUNTIFS('Product decisions'!$A$7:$A$32,A32,'Product decisions'!$H$7:$H$32,B32) -> 1 | S32: =COUNTIFS('Product decisions'!$A$7:$A$32,A32,'Product decisions'!$I$7:$I$32,B32) -> 0 | T32: =COUNTIFS('Product decisions'!$A$7:$A$32,A32,'Product decisions'!$J$7:$J$32,B32) -> 1 | U32: =0 -> 0 | V32: ='Source data'!D19 -> 3 | W32: =IF(K32=0,0,N32/K32) -> 0.48390602 | X32: =IF(L32=0,0,N32/L32) -> 0.93763158
A33: Life-Size Animated Butler | B33: In-Store | C33: Base | D33: =Assumptions!B34 -> 4000 | E33: ='Source data'!E20 -> 399 | F33: ='Source data'!F20 -> 150 | G33: =IF(B33="In-Store",'Source data'!J20+Assumptions!$B$15*'Source data'!K20,'Source data'!K20+Assumptions!$B$15*'Source data'!J20)*'Source data'!H20/'Source data'!G20*Assumptions!B7 -> 1800 | H33: =MIN(D33,G33) -> 1800 | I33: =(D33-H33)*Assumptions!C7 -> 2200 | J33: =D33-H33-I33 -> 0 | K33: =E33*(H33+I33*Assumptions!D7) -> 1157100 | L33: =D33*F33 -> 600000 | M33: =K33-(H33+I33)*F33 -> 557100 | N33: =K33-L33 -> 557100 | O33: =J33*F33 -> 0 | P33: =IF(B33="In-Store",N33/V33,0) -> 278550 | Q33: =COUNTIFS('Product decisions'!$A$7:$A$32,A33,'Product decisions'!$C$7:$C$32,B33) -> 0 | R33: =COUNTIFS('Product decisions'!$A$7:$A$32,A33,'Product decisions'!$H$7:$H$32,B33) -> 0 | S33: =COUNTIFS('Product decisions'!$A$7:$A$32,A33,'Product decisions'!$I$7:$I$32,B33) -> 0 | T33: =COUNTIFS('Product decisions'!$A$7:$A$32,A33,'Product decisions'!$J$7:$J$32,B33) -> 0 | U33: =0 -> 0 | V33: ='Source data'!D20 -> 2 | W33: =IF(K33=0,0,N33/K33) -> 0.48146228 | X33: =IF(L33=0,0,N33/L33) -> 0.9285
A34: Life-Size Animated Butler | B34: Online-Only | C34: Base | D34: =Assumptions!B34 -> 4000 | E34: ='Source data'!E20 -> 399 | F34: ='Source data'!F20 -> 150 | G34: =IF(B34="In-Store",'Source data'!J20+Assumptions!$B$15*'Source data'!K20,'Source data'!K20+Assumptions!$B$15*'Source data'!J20)*'Source data'!H20/'Source data'!G20*Assumptions!B7 -> 3600 | H34: =MIN(D34,G34) -> 3600 | I34: =(D34-H34)*Assumptions!C7 -> 400 | J34: =D34-H34-I34 -> 0 | K34: =E34*(H34+I34*Assumptions!D7) -> 1516200 | L34: =D34*F34 -> 600000 | M34: =K34-(H34+I34)*F34 -> 916200 | N34: =K34-L34 -> 916200 | O34: =J34*F34 -> 0 | P34: =IF(B34="In-Store",N34/V34,0) -> 0 | Q34: =COUNTIFS('Product decisions'!$A$7:$A$32,A34,'Product decisions'!$C$7:$C$32,B34) -> 1 | R34: =COUNTIFS('Product decisions'!$A$7:$A$32,A34,'Product decisions'!$H$7:$H$32,B34) -> 1 | S34: =COUNTIFS('Product decisions'!$A$7:$A$32,A34,'Product decisions'!$I$7:$I$32,B34) -> 1 | T34: =COUNTIFS('Product decisions'!$A$7:$A$32,A34,'Product decisions'!$J$7:$J$32,B34) -> 1 | U34: =0 -> 0 | V34: ='Source data'!D20 -> 2 | W34: =IF(K34=0,0,N34/K34) -> 0.60427384 | X34: =IF(L34=0,0,N34/L34) -> 1.527
A35: Animated Witch Cauldron | B35: In-Store | C35: Base | D35: =Assumptions!B35 -> 5000 | E35: ='Source data'!E21 -> 79 | F35: ='Source data'!F21 -> 30 | G35: =IF(B35="In-Store",'Source data'!J21+Assumptions!$B$15*'Source data'!K21,'Source data'!K21+Assumptions!$B$15*'Source data'!J21)*'Source data'!H21/'Source data'!G21*Assumptions!B7 -> 2125 | H35: =MIN(D35,G35) -> 2125 | I35: =(D35-H35)*Assumptions!C7 -> 2875 | J35: =D35-H35-I35 -> 0 | K35: =E35*(H35+I35*Assumptions!D7) -> 281437.5 | L35: =D35*F35 -> 150000 | M35: =K35-(H35+I35)*F35 -> 131437.5 | N35: =K35-L35 -> 131437.5 | O35: =J35*F35 -> 0 | P35: =IF(B35="In-Store",N35/V35,0) -> 131437.5 | Q35: =COUNTIFS('Product decisions'!$A$7:$A$32,A35,'Product decisions'!$C$7:$C$32,B35) -> 0 | R35: =COUNTIFS('Product decisions'!$A$7:$A$32,A35,'Product decisions'!$H$7:$H$32,B35) -> 0 | S35: =COUNTIFS('Product decisions'!$A$7:$A$32,A35,'Product decisions'!$I$7:$I$32,B35) -> 0 | T35: =COUNTIFS('Product decisions'!$A$7:$A$32,A35,'Product decisions'!$J$7:$J$32,B35) -> 0 | U35: =0 -> 0 | V35: ='Source data'!D21 -> 1 | W35: =IF(K35=0,0,N35/K35) -> 0.46702199 | X35: =IF(L35=0,0,N35/L35) -> 0.87625
A36: Animated Witch Cauldron | B36: Online-Only | C36: Base | D36: =Assumptions!B35 -> 5000 | E36: ='Source data'!E21 -> 79 | F36: ='Source data'!F21 -> 30 | G36: =IF(B36="In-Store",'Source data'!J21+Assumptions!$B$15*'Source data'!K21,'Source data'!K21+Assumptions!$B$15*'Source data'!J21)*'Source data'!H21/'Source data'!G21*Assumptions!B7 -> 4250 | H36: =MIN(D36,G36) -> 4250 | I36: =(D36-H36)*Assumptions!C7 -> 750 | J36: =D36-H36-I36 -> 0 | K36: =E36*(H36+I36*Assumptions!D7) -> 365375 | L36: =D36*F36 -> 150000 | M36: =K36-(H36+I36)*F36 -> 215375 | N36: =K36-L36 -> 215375 | O36: =J36*F36 -> 0 | P36: =IF(B36="In-Store",N36/V36,0) -> 0 | Q36: =COUNTIFS('Product decisions'!$A$7:$A$32,A36,'Product decisions'!$C$7:$C$32,B36) -> 0 | R36: =COUNTIFS('Product decisions'!$A$7:$A$32,A36,'Product decisions'!$H$7:$H$32,B36) -> 0 | S36: =COUNTIFS('Product decisions'!$A$7:$A$32,A36,'Product decisions'!$I$7:$I$32,B36) -> 1 | T36: =COUNTIFS('Product decisions'!$A$7:$A$32,A36,'Product decisions'!$J$7:$J$32,B36) -> 1 | U36: =0 -> 0 | V36: ='Source data'!D21 -> 1 | W36: =IF(K36=0,0,N36/K36) -> 0.58946288 | X36: =IF(L36=0,0,N36/L36) -> 1.4358333
A37: Halloween Doormat Assortment | B37: In-Store | C37: Base | D37: =Assumptions!B36 -> 9000 | E37: ='Source data'!E22 -> 19.98 | F37: ='Source data'!F22 -> 12 | G37: =IF(B37="In-Store",'Source data'!J22+Assumptions!$B$15*'Source data'!K22,'Source data'!K22+Assumptions!$B$15*'Source data'!J22)*'Source data'!H22/'Source data'!G22*Assumptions!B7 -> 2025 | H37: =MIN(D37,G37) -> 2025 | I37: =(D37-H37)*Assumptions!C7 -> 6975 | J37: =D37-H37-I37 -> 0 | K37: =E37*(H37+I37*Assumptions!D7) -> 110139.75 | L37: =D37*F37 -> 108000 | M37: =K37-(H37+I37)*F37 -> 2139.75 | N37: =K37-L37 -> 2139.75 | O37: =J37*F37 -> 0 | P37: =IF(B37="In-Store",N37/V37,0) -> 2139.75 | Q37: =COUNTIFS('Product decisions'!$A$7:$A$32,A37,'Product decisions'!$C$7:$C$32,B37) -> 0 | R37: =COUNTIFS('Product decisions'!$A$7:$A$32,A37,'Product decisions'!$H$7:$H$32,B37) -> 0 | S37: =COUNTIFS('Product decisions'!$A$7:$A$32,A37,'Product decisions'!$I$7:$I$32,B37) -> 0 | T37: =COUNTIFS('Product decisions'!$A$7:$A$32,A37,'Product decisions'!$J$7:$J$32,B37) -> 0 | U37: =0 -> 0 | V37: ='Source data'!D22 -> 1 | W37: =IF(K37=0,0,N37/K37) -> 0.019427591 | X37: =IF(L37=0,0,N37/L37) -> 0.0198125
A38: Halloween Doormat Assortment | B38: Online-Only | C38: Base | D38: =Assumptions!B36 -> 9000 | E38: ='Source data'!E22 -> 19.98 | F38: ='Source data'!F22 -> 12 | G38: =IF(B38="In-Store",'Source data'!J22+Assumptions!$B$15*'Source data'!K22,'Source data'!K22+Assumptions!$B$15*'Source data'!J22)*'Source data'!H22/'Source data'!G22*Assumptions!B7 -> 4050 | H38: =MIN(D38,G38) -> 4050 | I38: =(D38-H38)*Assumptions!C7 -> 4950 | J38: =D38-H38-I38 -> 0 | K38: =E38*(H38+I38*Assumptions!D7) -> 130369.5 | L38: =D38*F38 -> 108000 | M38: =K38-(H38+I38)*F38 -> 22369.5 | N38: =K38-L38 -> 22369.5 | O38: =J38*F38 -> 0 | P38: =IF(B38="In-Store",N38/V38,0) -> 0 | Q38: =COUNTIFS('Product decisions'!$A$7:$A$32,A38,'Product decisions'!$C$7:$C$32,B38) -> 0 | R38: =COUNTIFS('Product decisions'!$A$7:$A$32,A38,'Product decisions'!$H$7:$H$32,B38) -> 0 | S38: =COUNTIFS('Product decisions'!$A$7:$A$32,A38,'Product decisions'!$I$7:$I$32,B38) -> 0 | T38: =COUNTIFS('Product decisions'!$A$7:$A$32,A38,'Product decisions'!$J$7:$J$32,B38) -> 0 | U38: =0 -> 0 | V38: ='Source data'!D22 -> 1 | W38: =IF(K38=0,0,N38/K38) -> 0.17158538 | X38: =IF(L38=0,0,N38/L38) -> 0.207125
A39: 14 ft Giant Animated Dragon | B39: In-Store | C39: Base | D39: =Assumptions!B37 -> 45000 | E39: ='Source data'!E23 -> 449 | F39: ='Source data'!F23 -> 240 | G39: ='Source data'!G23*Assumptions!$B$13*IF(B39="In-Store",1,Assumptions!$B$14)*Assumptions!B7 -> 36000 | H39: =MIN(D39,G39) -> 36000 | I39: =(D39-H39)*Assumptions!C7 -> 9000 | J39: =D39-H39-I39 -> 0 | K39: =E39*(H39+I39*Assumptions!D7) -> 18184500 | L39: =D39*F39 -> 10800000 | M39: =K39-(H39+I39)*F39 -> 7384500 | N39: =K39-L39 -> 7384500 | O39: =J39*F39 -> 0 | P39: =IF(B39="In-Store",N39/V39,0) -> 1846125 | Q39: =COUNTIFS('Product decisions'!$A$7:$A$32,A39,'Product decisions'!$C$7:$C$32,B39) -> 0 | R39: =COUNTIFS('Product decisions'!$A$7:$A$32,A39,'Product decisions'!$H$7:$H$32,B39) -> 1 | S39: =COUNTIFS('Product decisions'!$A$7:$A$32,A39,'Product decisions'!$I$7:$I$32,B39) -> 0 | T39: =COUNTIFS('Product decisions'!$A$7:$A$32,A39,'Product decisions'!$J$7:$J$32,B39) -> 0 | U39: =L39 -> 10800000 | V39: ='Source data'!D23 -> 4 | W39: =IF(K39=0,0,N39/K39) -> 0.4060876 | X39: =IF(L39=0,0,N39/L39) -> 0.68375
A40: 14 ft Giant Animated Dragon | B40: Online-Only | C40: Base | D40: =Assumptions!B37 -> 45000 | E40: ='Source data'!E23 -> 449 | F40: ='Source data'!F23 -> 240 | G40: ='Source data'!G23*Assumptions!$B$13*IF(B40="In-Store",1,Assumptions!$B$14)*Assumptions!B7 -> 28800 | H40: =MIN(D40,G40) -> 28800 | I40: =(D40-H40)*Assumptions!C7 -> 16200 | J40: =D40-H40-I40 -> 0 | K40: =E40*(H40+I40*Assumptions!D7) -> 16568100 | L40: =D40*F40 -> 10800000 | M40: =K40-(H40+I40)*F40 -> 5768100 | N40: =K40-L40 -> 5768100 | O40: =J40*F40 -> 0 | P40: =IF(B40="In-Store",N40/V40,0) -> 0 | Q40: =COUNTIFS('Product decisions'!$A$7:$A$32,A40,'Product decisions'!$C$7:$C$32,B40) -> 0 | R40: =COUNTIFS('Product decisions'!$A$7:$A$32,A40,'Product decisions'!$H$7:$H$32,B40) -> 0 | S40: =COUNTIFS('Product decisions'!$A$7:$A$32,A40,'Product decisions'!$I$7:$I$32,B40) -> 0 | T40: =COUNTIFS('Product decisions'!$A$7:$A$32,A40,'Product decisions'!$J$7:$J$32,B40) -> 0 | U40: =L40 -> 10800000 | V40: ='Source data'!D23 -> 4 | W40: =IF(K40=0,0,N40/K40) -> 0.34814493 | X40: =IF(L40=0,0,N40/L40) -> 0.53408333
A41: 6 ft Licensed Movie Villain | B41: In-Store | C41: Base | D41: =Assumptions!B38 -> 14000 | E41: ='Source data'!E24 -> 329 | F41: ='Source data'!F24 -> 215 | G41: ='Source data'!G24*Assumptions!$B$13*IF(B41="In-Store",1,Assumptions!$B$14)*Assumptions!B7 -> 11200 | H41: =MIN(D41,G41) -> 11200 | I41: =(D41-H41)*Assumptions!C7 -> 2800 | J41: =D41-H41-I41 -> 0 | K41: =E41*(H41+I41*Assumptions!D7) -> 4145400 | L41: =D41*F41 -> 3010000 | M41: =K41-(H41+I41)*F41 -> 1135400 | N41: =K41-L41 -> 1135400 | O41: =J41*F41 -> 0 | P41: =IF(B41="In-Store",N41/V41,0) -> 567700 | Q41: =COUNTIFS('Product decisions'!$A$7:$A$32,A41,'Product decisions'!$C$7:$C$32,B41) -> 0 | R41: =COUNTIFS('Product decisions'!$A$7:$A$32,A41,'Product decisions'!$H$7:$H$32,B41) -> 1 | S41: =COUNTIFS('Product decisions'!$A$7:$A$32,A41,'Product decisions'!$I$7:$I$32,B41) -> 0 | T41: =COUNTIFS('Product decisions'!$A$7:$A$32,A41,'Product decisions'!$J$7:$J$32,B41) -> 0 | U41: =L41 -> 3010000 | V41: ='Source data'!D24 -> 2 | W41: =IF(K41=0,0,N41/K41) -> 0.27389395 | X41: =IF(L41=0,0,N41/L41) -> 0.3772093
A42: 6 ft Licensed Movie Villain | B42: Online-Only | C42: Base | D42: =Assumptions!B38 -> 14000 | E42: ='Source data'!E24 -> 329 | F42: ='Source data'!F24 -> 215 | G42: ='Source data'!G24*Assumptions!$B$13*IF(B42="In-Store",1,Assumptions!$B$14)*Assumptions!B7 -> 8960 | H42: =MIN(D42,G42) -> 8960 | I42: =(D42-H42)*Assumptions!C7 -> 5040 | J42: =D42-H42-I42 -> 0 | K42: =E42*(H42+I42*Assumptions!D7) -> 3776920 | L42: =D42*F42 -> 3010000 | M42: =K42-(H42+I42)*F42 -> 766920 | N42: =K42-L42 -> 766920 | O42: =J42*F42 -> 0 | P42: =IF(B42="In-Store",N42/V42,0) -> 0 | Q42: =COUNTIFS('Product decisions'!$A$7:$A$32,A42,'Product decisions'!$C$7:$C$32,B42) -> 0 | R42: =COUNTIFS('Product decisions'!$A$7:$A$32,A42,'Product decisions'!$H$7:$H$32,B42) -> 0 | S42: =COUNTIFS('Product decisions'!$A$7:$A$32,A42,'Product decisions'!$I$7:$I$32,B42) -> 0 | T42: =COUNTIFS('Product decisions'!$A$7:$A$32,A42,'Product decisions'!$J$7:$J$32,B42) -> 0 | U42: =L42 -> 3010000 | V42: ='Source data'!D24 -> 2 | W42: =IF(K42=0,0,N42/K42) -> 0.20305434 | X42: =IF(L42=0,0,N42/L42) -> 0.2547907
A43: 9 ft Licensed Franchise Inflatable | B43: In-Store | C43: Base | D43: =Assumptions!B39 -> 12000 | E43: ='Source data'!E25 -> 159 | F43: ='Source data'!F25 -> 138 | G43: ='Source data'!G25*Assumptions!$B$13*IF(B43="In-Store",1,Assumptions!$B$14)*Assumptions!B7 -> 9600 | H43: =MIN(D43,G43) -> 9600 | I43: =(D43-H43)*Assumptions!C7 -> 2400 | J43: =D43-H43-I43 -> 0 | K43: =E43*(H43+I43*Assumptions!D7) -> 1717200 | L43: =D43*F43 -> 1656000 | M43: =K43-(H43+I43)*F43 -> 61200 | N43: =K43-L43 -> 61200 | O43: =J43*F43 -> 0 | P43: =IF(B43="In-Store",N43/V43,0) -> 30600 | Q43: =COUNTIFS('Product decisions'!$A$7:$A$32,A43,'Product decisions'!$C$7:$C$32,B43) -> 0 | R43: =COUNTIFS('Product decisions'!$A$7:$A$32,A43,'Product decisions'!$H$7:$H$32,B43) -> 0 | S43: =COUNTIFS('Product decisions'!$A$7:$A$32,A43,'Product decisions'!$I$7:$I$32,B43) -> 0 | T43: =COUNTIFS('Product decisions'!$A$7:$A$32,A43,'Product decisions'!$J$7:$J$32,B43) -> 0 | U43: =L43 -> 1656000 | V43: ='Source data'!D25 -> 2 | W43: =IF(K43=0,0,N43/K43) -> 0.035639413 | X43: =IF(L43=0,0,N43/L43) -> 0.036956522
A44: 9 ft Licensed Franchise Inflatable | B44: Online-Only | C44: Base | D44: =Assumptions!B39 -> 12000 | E44: ='Source data'!E25 -> 159 | F44: ='Source data'!F25 -> 138 | G44: ='Source data'!G25*Assumptions!$B$13*IF(B44="In-Store",1,Assumptions!$B$14)*Assumptions!B7 -> 7680 | H44: =MIN(D44,G44) -> 7680 | I44: =(D44-H44)*Assumptions!C7 -> 4320 | J44: =D44-H44-I44 -> 0 | K44: =E44*(H44+I44*Assumptions!D7) -> 1564560 | L44: =D44*F44 -> 1656000 | M44: =K44-(H44+I44)*F44 -> -91440 | N44: =K44-L44 -> -91440 | O44: =J44*F44 -> 0 | P44: =IF(B44="In-Store",N44/V44,0) -> 0 | Q44: =COUNTIFS('Product decisions'!$A$7:$A$32,A44,'Product decisions'!$C$7:$C$32,B44) -> 0 | R44: =COUNTIFS('Product decisions'!$A$7:$A$32,A44,'Product decisions'!$H$7:$H$32,B44) -> 0 | S44: =COUNTIFS('Product decisions'!$A$7:$A$32,A44,'Product decisions'!$I$7:$I$32,B44) -> 0 | T44: =COUNTIFS('Product decisions'!$A$7:$A$32,A44,'Product decisions'!$J$7:$J$32,B44) -> 0 | U44: =L44 -> 1656000 | V44: ='Source data'!D25 -> 2 | W44: =IF(K44=0,0,N44/K44) -> -0.058444547 | X44: =IF(L44=0,0,N44/L44) -> -0.055217391
A45: 7 ft Licensed Sitcom Character | B45: In-Store | C45: Base | D45: =Assumptions!B40 -> 9000 | E45: ='Source data'!E26 -> 279 | F45: ='Source data'!F26 -> 164 | G45: ='Source data'!G26*Assumptions!$B$13*IF(B45="In-Store",1,Assumptions!$B$14)*Assumptions!B7 -> 7200 | H45: =MIN(D45,G45) -> 7200 | I45: =(D45-H45)*Assumptions!C7 -> 1800 | J45: =D45-H45-I45 -> 0 | K45: =E45*(H45+I45*Assumptions!D7) -> 2259900 | L45: =D45*F45 -> 1476000 | M45: =K45-(H45+I45)*F45 -> 783900 | N45: =K45-L45 -> 783900 | O45: =J45*F45 -> 0 | P45: =IF(B45="In-Store",N45/V45,0) -> 391950 | Q45: =COUNTIFS('Product decisions'!$A$7:$A$32,A45,'Product decisions'!$C$7:$C$32,B45) -> 1 | R45: =COUNTIFS('Product decisions'!$A$7:$A$32,A45,'Product decisions'!$H$7:$H$32,B45) -> 1 | S45: =COUNTIFS('Product decisions'!$A$7:$A$32,A45,'Product decisions'!$I$7:$I$32,B45) -> 1 | T45: =COUNTIFS('Product decisions'!$A$7:$A$32,A45,'Product decisions'!$J$7:$J$32,B45) -> 0 | U45: =L45 -> 1476000 | V45: ='Source data'!D26 -> 2 | W45: =IF(K45=0,0,N45/K45) -> 0.34687376 | X45: =IF(L45=0,0,N45/L45) -> 0.53109756
A46: 7 ft Licensed Sitcom Character | B46: Online-Only | C46: Base | D46: =Assumptions!B40 -> 9000 | E46: ='Source data'!E26 -> 279 | F46: ='Source data'!F26 -> 164 | G46: ='Source data'!G26*Assumptions!$B$13*IF(B46="In-Store",1,Assumptions!$B$14)*Assumptions!B7 -> 5760 | H46: =MIN(D46,G46) -> 5760 | I46: =(D46-H46)*Assumptions!C7 -> 3240 | J46: =D46-H46-I46 -> 0 | K46: =E46*(H46+I46*Assumptions!D7) -> 2059020 | L46: =D46*F46 -> 1476000 | M46: =K46-(H46+I46)*F46 -> 583020 | N46: =K46-L46 -> 583020 | O46: =J46*F46 -> 0 | P46: =IF(B46="In-Store",N46/V46,0) -> 0 | Q46: =COUNTIFS('Product decisions'!$A$7:$A$32,A46,'Product decisions'!$C$7:$C$32,B46) -> 0 | R46: =COUNTIFS('Product decisions'!$A$7:$A$32,A46,'Product decisions'!$H$7:$H$32,B46) -> 0 | S46: =COUNTIFS('Product decisions'!$A$7:$A$32,A46,'Product decisions'!$I$7:$I$32,B46) -> 0 | T46: =COUNTIFS('Product decisions'!$A$7:$A$32,A46,'Product decisions'!$J$7:$J$32,B46) -> 0 | U46: =L46 -> 1476000 | V46: ='Source data'!D26 -> 2 | W46: =IF(K46=0,0,N46/K46) -> 0.28315412 | X46: =IF(L46=0,0,N46/L46) -> 0.395
A47: 8 ft Inflatable Black Cat | B47: In-Store | C47: Base | D47: =Assumptions!B41 -> 16000 | E47: ='Source data'!E27 -> 79 | F47: ='Source data'!F27 -> 40 | G47: ='Source data'!G27*Assumptions!$B$13*IF(B47="In-Store",1,Assumptions!$B$14)*Assumptions!B7 -> 12800 | H47: =MIN(D47,G47) -> 12800 | I47: =(D47-H47)*Assumptions!C7 -> 3200 | J47: =D47-H47-I47 -> 0 | K47: =E47*(H47+I47*Assumptions!D7) -> 1137600 | L47: =D47*F47 -> 640000 | M47: =K47-(H47+I47)*F47 -> 497600 | N47: =K47-L47 -> 497600 | O47: =J47*F47 -> 0 | P47: =IF(B47="In-Store",N47/V47,0) -> 497600 | Q47: =COUNTIFS('Product decisions'!$A$7:$A$32,A47,'Product decisions'!$C$7:$C$32,B47) -> 1 | R47: =COUNTIFS('Product decisions'!$A$7:$A$32,A47,'Product decisions'!$H$7:$H$32,B47) -> 1 | S47: =COUNTIFS('Product decisions'!$A$7:$A$32,A47,'Product decisions'!$I$7:$I$32,B47) -> 1 | T47: =COUNTIFS('Product decisions'!$A$7:$A$32,A47,'Product decisions'!$J$7:$J$32,B47) -> 1 | U47: =L47 -> 640000 | V47: ='Source data'!D27 -> 1 | W47: =IF(K47=0,0,N47/K47) -> 0.4374121 | X47: =IF(L47=0,0,N47/L47) -> 0.7775
A48: 8 ft Inflatable Black Cat | B48: Online-Only | C48: Base | D48: =Assumptions!B41 -> 16000 | E48: ='Source data'!E27 -> 79 | F48: ='Source data'!F27 -> 40 | G48: ='Source data'!G27*Assumptions!$B$13*IF(B48="In-Store",1,Assumptions!$B$14)*Assumptions!B7 -> 10240 | H48: =MIN(D48,G48) -> 10240 | I48: =(D48-H48)*Assumptions!C7 -> 5760 | J48: =D48-H48-I48 -> 0 | K48: =E48*(H48+I48*Assumptions!D7) -> 1036480 | L48: =D48*F48 -> 640000 | M48: =K48-(H48+I48)*F48 -> 396480 | N48: =K48-L48 -> 396480 | O48: =J48*F48 -> 0 | P48: =IF(B48="In-Store",N48/V48,0) -> 0 | Q48: =COUNTIFS('Product decisions'!$A$7:$A$32,A48,'Product decisions'!$C$7:$C$32,B48) -> 0 | R48: =COUNTIFS('Product decisions'!$A$7:$A$32,A48,'Product decisions'!$H$7:$H$32,B48) -> 0 | S48: =COUNTIFS('Product decisions'!$A$7:$A$32,A48,'Product decisions'!$I$7:$I$32,B48) -> 0 | T48: =COUNTIFS('Product decisions'!$A$7:$A$32,A48,'Product decisions'!$J$7:$J$32,B48) -> 0 | U48: =L48 -> 640000 | V48: ='Source data'!D27 -> 1 | W48: =IF(K48=0,0,N48/K48) -> 0.38252547 | X48: =IF(L48=0,0,N48/L48) -> 0.6195
A49: 12 ft Inflatable Haunted Tree | B49: In-Store | C49: Base | D49: =Assumptions!B42 -> 7000 | E49: ='Source data'!E28 -> 179 | F49: ='Source data'!F28 -> 88 | G49: ='Source data'!G28*Assumptions!$B$13*IF(B49="In-Store",1,Assumptions!$B$14)*Assumptions!B7 -> 5600 | H49: =MIN(D49,G49) -> 5600 | I49: =(D49-H49)*Assumptions!C7 -> 1400 | J49: =D49-H49-I49 -> 0 | K49: =E49*(H49+I49*Assumptions!D7) -> 1127700 | L49: =D49*F49 -> 616000 | M49: =K49-(H49+I49)*F49 -> 511700 | N49: =K49-L49 -> 511700 | O49: =J49*F49 -> 0 | P49: =IF(B49="In-Store",N49/V49,0) -> 255850 | Q49: =COUNTIFS('Product decisions'!$A$7:$A$32,A49,'Product decisions'!$C$7:$C$32,B49) -> 0 | R49: =COUNTIFS('Product decisions'!$A$7:$A$32,A49,'Product decisions'!$H$7:$H$32,B49) -> 0 | S49: =COUNTIFS('Product decisions'!$A$7:$A$32,A49,'Product decisions'!$I$7:$I$32,B49) -> 1 | T49: =COUNTIFS('Product decisions'!$A$7:$A$32,A49,'Product decisions'!$J$7:$J$32,B49) -> 1 | U49: =L49 -> 616000 | V49: ='Source data'!D28 -> 2 | W49: =IF(K49=0,0,N49/K49) -> 0.45375543 | X49: =IF(L49=0,0,N49/L49) -> 0.83068182
A50: 12 ft Inflatable Haunted Tree | B50: Online-Only | C50: Base | D50: =Assumptions!B42 -> 7000 | E50: ='Source data'!E28 -> 179 | F50: ='Source data'!F28 -> 88 | G50: ='Source data'!G28*Assumptions!$B$13*IF(B50="In-Store",1,Assumptions!$B$14)*Assumptions!B7 -> 4480 | H50: =MIN(D50,G50) -> 4480 | I50: =(D50-H50)*Assumptions!C7 -> 2520 | J50: =D50-H50-I50 -> 0 | K50: =E50*(H50+I50*Assumptions!D7) -> 1027460 | L50: =D50*F50 -> 616000 | M50: =K50-(H50+I50)*F50 -> 411460 | N50: =K50-L50 -> 411460 | O50: =J50*F50 -> 0 | P50: =IF(B50="In-Store",N50/V50,0) -> 0 | Q50: =COUNTIFS('Product decisions'!$A$7:$A$32,A50,'Product decisions'!$C$7:$C$32,B50) -> 1 | R50: =COUNTIFS('Product decisions'!$A$7:$A$32,A50,'Product decisions'!$H$7:$H$32,B50) -> 0 | S50: =COUNTIFS('Product decisions'!$A$7:$A$32,A50,'Product decisions'!$I$7:$I$32,B50) -> 0 | T50: =COUNTIFS('Product decisions'!$A$7:$A$32,A50,'Product decisions'!$J$7:$J$32,B50) -> 0 | U50: =L50 -> 616000 | V50: ='Source data'!D28 -> 2 | W50: =IF(K50=0,0,N50/K50) -> 0.40046328 | X50: =IF(L50=0,0,N50/L50) -> 0.66795455
A51: Fog Machine w/ Bluetooth Sound | B51: In-Store | C51: Base | D51: =Assumptions!B43 -> 20000 | E51: ='Source data'!E29 -> 89 | F51: ='Source data'!F29 -> 52 | G51: ='Source data'!G29*Assumptions!$B$13*IF(B51="In-Store",1,Assumptions!$B$14)*Assumptions!B7 -> 16000 | H51: =MIN(D51,G51) -> 16000 | I51: =(D51-H51)*Assumptions!C7 -> 4000 | J51: =D51-H51-I51 -> 0 | K51: =E51*(H51+I51*Assumptions!D7) -> 1602000 | L51: =D51*F51 -> 1040000 | M51: =K51-(H51+I51)*F51 -> 562000 | N51: =K51-L51 -> 562000 | O51: =J51*F51 -> 0 | P51: =IF(B51="In-Store",N51/V51,0) -> 562000 | Q51: =COUNTIFS('Product decisions'!$A$7:$A$32,A51,'Product decisions'!$C$7:$C$32,B51) -> 0 | R51: =COUNTIFS('Product decisions'!$A$7:$A$32,A51,'Product decisions'!$H$7:$H$32,B51) -> 1 | S51: =COUNTIFS('Product decisions'!$A$7:$A$32,A51,'Product decisions'!$I$7:$I$32,B51) -> 0 | T51: =COUNTIFS('Product decisions'!$A$7:$A$32,A51,'Product decisions'!$J$7:$J$32,B51) -> 0 | U51: =L51 -> 1040000 | V51: ='Source data'!D29 -> 1 | W51: =IF(K51=0,0,N51/K51) -> 0.35081149 | X51: =IF(L51=0,0,N51/L51) -> 0.54038462
A52: Fog Machine w/ Bluetooth Sound | B52: Online-Only | C52: Base | D52: =Assumptions!B43 -> 20000 | E52: ='Source data'!E29 -> 89 | F52: ='Source data'!F29 -> 52 | G52: ='Source data'!G29*Assumptions!$B$13*IF(B52="In-Store",1,Assumptions!$B$14)*Assumptions!B7 -> 12800 | H52: =MIN(D52,G52) -> 12800 | I52: =(D52-H52)*Assumptions!C7 -> 7200 | J52: =D52-H52-I52 -> 0 | K52: =E52*(H52+I52*Assumptions!D7) -> 1459600 | L52: =D52*F52 -> 1040000 | M52: =K52-(H52+I52)*F52 -> 419600 | N52: =K52-L52 -> 419600 | O52: =J52*F52 -> 0 | P52: =IF(B52="In-Store",N52/V52,0) -> 0 | Q52: =COUNTIFS('Product decisions'!$A$7:$A$32,A52,'Product decisions'!$C$7:$C$32,B52) -> 0 | R52: =COUNTIFS('Product decisions'!$A$7:$A$32,A52,'Product decisions'!$H$7:$H$32,B52) -> 0 | S52: =COUNTIFS('Product decisions'!$A$7:$A$32,A52,'Product decisions'!$I$7:$I$32,B52) -> 0 | T52: =COUNTIFS('Product decisions'!$A$7:$A$32,A52,'Product decisions'!$J$7:$J$32,B52) -> 0 | U52: =L52 -> 1040000 | V52: ='Source data'!D29 -> 1 | W52: =IF(K52=0,0,N52/K52) -> 0.28747602 | X52: =IF(L52=0,0,N52/L52) -> 0.40346154
A53: Animated Talking Portrait | B53: In-Store | C53: Base | D53: =Assumptions!B44 -> 9000 | E53: ='Source data'!E30 -> 39.98 | F53: ='Source data'!F30 -> 7 | G53: ='Source data'!G30*Assumptions!$B$13*IF(B53="In-Store",1,Assumptions!$B$14)*Assumptions!B7 -> 7200 | H53: =MIN(D53,G53) -> 7200 | I53: =(D53-H53)*Assumptions!C7 -> 1800 | J53: =D53-H53-I53 -> 0 | K53: =E53*(H53+I53*Assumptions!D7) -> 323838 | L53: =D53*F53 -> 63000 | M53: =K53-(H53+I53)*F53 -> 260838 | N53: =K53-L53 -> 260838 | O53: =J53*F53 -> 0 | P53: =IF(B53="In-Store",N53/V53,0) -> 260838 | Q53: =COUNTIFS('Product decisions'!$A$7:$A$32,A53,'Product decisions'!$C$7:$C$32,B53) -> 1 | R53: =COUNTIFS('Product decisions'!$A$7:$A$32,A53,'Product decisions'!$H$7:$H$32,B53) -> 0 | S53: =COUNTIFS('Product decisions'!$A$7:$A$32,A53,'Product decisions'!$I$7:$I$32,B53) -> 1 | T53: =COUNTIFS('Product decisions'!$A$7:$A$32,A53,'Product decisions'!$J$7:$J$32,B53) -> 1 | U53: =L53 -> 63000 | V53: ='Source data'!D30 -> 1 | W53: =IF(K53=0,0,N53/K53) -> 0.80545828 | X53: =IF(L53=0,0,N53/L53) -> 4.1402857
A54: Animated Talking Portrait | B54: Online-Only | C54: Base | D54: =Assumptions!B44 -> 9000 | E54: ='Source data'!E30 -> 39.98 | F54: ='Source data'!F30 -> 7 | G54: ='Source data'!G30*Assumptions!$B$13*IF(B54="In-Store",1,Assumptions!$B$14)*Assumptions!B7 -> 5760 | H54: =MIN(D54,G54) -> 5760 | I54: =(D54-H54)*Assumptions!C7 -> 3240 | J54: =D54-H54-I54 -> 0 | K54: =E54*(H54+I54*Assumptions!D7) -> 295052.4 | L54: =D54*F54 -> 63000 | M54: =K54-(H54+I54)*F54 -> 232052.4 | N54: =K54-L54 -> 232052.4 | O54: =J54*F54 -> 0 | P54: =IF(B54="In-Store",N54/V54,0) -> 0 | Q54: =COUNTIFS('Product decisions'!$A$7:$A$32,A54,'Product decisions'!$C$7:$C$32,B54) -> 0 | R54: =COUNTIFS('Product decisions'!$A$7:$A$32,A54,'Product decisions'!$H$7:$H$32,B54) -> 0 | S54: =COUNTIFS('Product decisions'!$A$7:$A$32,A54,'Product decisions'!$I$7:$I$32,B54) -> 0 | T54: =COUNTIFS('Product decisions'!$A$7:$A$32,A54,'Product decisions'!$J$7:$J$32,B54) -> 0 | U54: =L54 -> 63000 | V54: ='Source data'!D30 -> 1 | W54: =IF(K54=0,0,N54/K54) -> 0.78647861 | X54: =IF(L54=0,0,N54/L54) -> 3.6833714
A55: Solar Pathway Ghosts (4-pc) | B55: In-Store | C55: Base | D55: =Assumptions!B45 -> 12000 | E55: ='Source data'!E31 -> 44.98 | F55: ='Source data'!F31 -> 16 | G55: ='Source data'!G31*Assumptions!$B$13*IF(B55="In-Store",1,Assumptions!$B$14)*Assumptions!B7 -> 9600 | H55: =MIN(D55,G55) -> 9600 | I55: =(D55-H55)*Assumptions!C7 -> 2400 | J55: =D55-H55-I55 -> 0 | K55: =E55*(H55+I55*Assumptions!D7) -> 485784 | L55: =D55*F55 -> 192000 | M55: =K55-(H55+I55)*F55 -> 293784 | N55: =K55-L55 -> 293784 | O55: =J55*F55 -> 0 | P55: =IF(B55="In-Store",N55/V55,0) -> 293784 | Q55: =COUNTIFS('Product decisions'!$A$7:$A$32,A55,'Product decisions'!$C$7:$C$32,B55) -> 1 | R55: =COUNTIFS('Product decisions'!$A$7:$A$32,A55,'Product decisions'!$H$7:$H$32,B55) -> 0 | S55: =COUNTIFS('Product decisions'!$A$7:$A$32,A55,'Product decisions'!$I$7:$I$32,B55) -> 1 | T55: =COUNTIFS('Product decisions'!$A$7:$A$32,A55,'Product decisions'!$J$7:$J$32,B55) -> 1 | U55: =L55 -> 192000 | V55: ='Source data'!D31 -> 1 | W55: =IF(K55=0,0,N55/K55) -> 0.60476261 | X55: =IF(L55=0,0,N55/L55) -> 1.530125
A56: Solar Pathway Ghosts (4-pc) | B56: Online-Only | C56: Base | D56: =Assumptions!B45 -> 12000 | E56: ='Source data'!E31 -> 44.98 | F56: ='Source data'!F31 -> 16 | G56: ='Source data'!G31*Assumptions!$B$13*IF(B56="In-Store",1,Assumptions!$B$14)*Assumptions!B7 -> 7680 | H56: =MIN(D56,G56) -> 7680 | I56: =(D56-H56)*Assumptions!C7 -> 4320 | J56: =D56-H56-I56 -> 0 | K56: =E56*(H56+I56*Assumptions!D7) -> 442603.2 | L56: =D56*F56 -> 192000 | M56: =K56-(H56+I56)*F56 -> 250603.2 | N56: =K56-L56 -> 250603.2 | O56: =J56*F56 -> 0 | P56: =IF(B56="In-Store",N56/V56,0) -> 0 | Q56: =COUNTIFS('Product decisions'!$A$7:$A$32,A56,'Product decisions'!$C$7:$C$32,B56) -> 0 | R56: =COUNTIFS('Product decisions'!$A$7:$A$32,A56,'Product decisions'!$H$7:$H$32,B56) -> 0 | S56: =COUNTIFS('Product decisions'!$A$7:$A$32,A56,'Product decisions'!$I$7:$I$32,B56) -> 0 | T56: =COUNTIFS('Product decisions'!$A$7:$A$32,A56,'Product decisions'!$J$7:$J$32,B56) -> 0 | U56: =L56 -> 192000 | V56: ='Source data'!D31 -> 1 | W56: =IF(K56=0,0,N56/K56) -> 0.56620287 | X56: =IF(L56=0,0,N56/L56) -> 1.305225
A57: 24 in Light-Up Pumpkin Stack | B57: In-Store | C57: Base | D57: =Assumptions!B46 -> 22000 | E57: ='Source data'!E32 -> 29.98 | F57: ='Source data'!F32 -> 9 | G57: ='Source data'!G32*Assumptions!$B$13*IF(B57="In-Store",1,Assumptions!$B$14)*Assumptions!B7 -> 17600 | H57: =MIN(D57,G57) -> 17600 | I57: =(D57-H57)*Assumptions!C7 -> 4400 | J57: =D57-H57-I57 -> 0 | K57: =E57*(H57+I57*Assumptions!D7) -> 593604 | L57: =D57*F57 -> 198000 | M57: =K57-(H57+I57)*F57 -> 395604 | N57: =K57-L57 -> 395604 | O57: =J57*F57 -> 0 | P57: =IF(B57="In-Store",N57/V57,0) -> 395604 | Q57: =COUNTIFS('Product decisions'!$A$7:$A$32,A57,'Product decisions'!$C$7:$C$32,B57) -> 1 | R57: =COUNTIFS('Product decisions'!$A$7:$A$32,A57,'Product decisions'!$H$7:$H$32,B57) -> 1 | S57: =COUNTIFS('Product decisions'!$A$7:$A$32,A57,'Product decisions'!$I$7:$I$32,B57) -> 1 | T57: =COUNTIFS('Product decisions'!$A$7:$A$32,A57,'Product decisions'!$J$7:$J$32,B57) -> 1 | U57: =L57 -> 198000 | V57: ='Source data'!D32 -> 1 | W57: =IF(K57=0,0,N57/K57) -> 0.6664443 | X57: =IF(L57=0,0,N57/L57) -> 1.998
A58: 24 in Light-Up Pumpkin Stack | B58: Online-Only | C58: Base | D58: =Assumptions!B46 -> 22000 | E58: ='Source data'!E32 -> 29.98 | F58: ='Source data'!F32 -> 9 | G58: ='Source data'!G32*Assumptions!$B$13*IF(B58="In-Store",1,Assumptions!$B$14)*Assumptions!B7 -> 14080 | H58: =MIN(D58,G58) -> 14080 | I58: =(D58-H58)*Assumptions!C7 -> 7920 | J58: =D58-H58-I58 -> 0 | K58: =E58*(H58+I58*Assumptions!D7) -> 540839.2 | L58: =D58*F58 -> 198000 | M58: =K58-(H58+I58)*F58 -> 342839.2 | N58: =K58-L58 -> 342839.2 | O58: =J58*F58 -> 0 | P58: =IF(B58="In-Store",N58/V58,0) -> 0 | Q58: =COUNTIFS('Product decisions'!$A$7:$A$32,A58,'Product decisions'!$C$7:$C$32,B58) -> 0 | R58: =COUNTIFS('Product decisions'!$A$7:$A$32,A58,'Product decisions'!$H$7:$H$32,B58) -> 0 | S58: =COUNTIFS('Product decisions'!$A$7:$A$32,A58,'Product decisions'!$I$7:$I$32,B58) -> 0 | T58: =COUNTIFS('Product decisions'!$A$7:$A$32,A58,'Product decisions'!$J$7:$J$32,B58) -> 0 | U58: =L58 -> 198000 | V58: ='Source data'!D32 -> 1 | W58: =IF(K58=0,0,N58/K58) -> 0.63390228 | X58: =IF(L58=0,0,N58/L58) -> 1.7315111
A59: 12 ft Giant Skeleton | B59: In-Store | C59: Downside | D59: =Assumptions!B21 -> 40000 | E59: ='Source data'!E7 -> 299 | F59: ='Source data'!F7 -> 126 | G59: =IF(B59="In-Store",'Source data'!J7+Assumptions!$B$15*'Source data'!K7,'Source data'!K7+Assumptions!$B$15*'Source data'!J7)*'Source data'!H7/'Source data'!G7*Assumptions!B8 -> 19285 | H59: =MIN(D59,G59) -> 19285 | I59: =(D59-H59)*Assumptions!C8 -> 10357.5 | J59: =D59-H59-I59 -> 10357.5 | K59: =E59*(H59+I59*Assumptions!D8) -> 7314661.2 | L59: =D59*F59 -> 5040000 | M59: =K59-(H59+I59)*F59 -> 3579706.2 | N59: =K59-L59 -> 2274661.2 | O59: =J59*F59 -> 1305045 | P59: =IF(B59="In-Store",N59/V59,0) -> 758220.42 | Q59: =COUNTIFS('Product decisions'!$A$7:$A$32,A59,'Product decisions'!$C$7:$C$32,B59) -> 1 | R59: =COUNTIFS('Product decisions'!$A$7:$A$32,A59,'Product decisions'!$H$7:$H$32,B59) -> 0 | S59: =COUNTIFS('Product decisions'!$A$7:$A$32,A59,'Product decisions'!$I$7:$I$32,B59) -> 0 | T59: =COUNTIFS('Product decisions'!$A$7:$A$32,A59,'Product decisions'!$J$7:$J$32,B59) -> 1 | U59: =0 -> 0 | V59: ='Source data'!D7 -> 3 | W59: =IF(K59=0,0,N59/K59) -> 0.31097288 | X59: =IF(L59=0,0,N59/L59) -> 0.45132168
A60: 12 ft Giant Skeleton | B60: Online-Only | C60: Downside | D60: =Assumptions!B21 -> 40000 | E60: ='Source data'!E7 -> 299 | F60: ='Source data'!F7 -> 126 | G60: =IF(B60="In-Store",'Source data'!J7+Assumptions!$B$15*'Source data'!K7,'Source data'!K7+Assumptions!$B$15*'Source data'!J7)*'Source data'!H7/'Source data'!G7*Assumptions!B8 -> 20615 | H60: =MIN(D60,G60) -> 20615 | I60: =(D60-H60)*Assumptions!C8 -> 9692.5 | J60: =D60-H60-I60 -> 9692.5 | K60: =E60*(H60+I60*Assumptions!D8) -> 7612913.8 | L60: =D60*F60 -> 5040000 | M60: =K60-(H60+I60)*F60 -> 3794168.8 | N60: =K60-L60 -> 2572913.8 | O60: =J60*F60 -> 1221255 | P60: =IF(B60="In-Store",N60/V60,0) -> 0 | Q60: =COUNTIFS('Product decisions'!$A$7:$A$32,A60,'Product decisions'!$C$7:$C$32,B60) -> 0 | R60: =COUNTIFS('Product decisions'!$A$7:$A$32,A60,'Product decisions'!$H$7:$H$32,B60) -> 1 | S60: =COUNTIFS('Product decisions'!$A$7:$A$32,A60,'Product decisions'!$I$7:$I$32,B60) -> 1 | T60: =COUNTIFS('Product decisions'!$A$7:$A$32,A60,'Product decisions'!$J$7:$J$32,B60) -> 0 | U60: =0 -> 0 | V60: ='Source data'!D7 -> 3 | W60: =IF(K60=0,0,N60/K60) -> 0.33796702 | X60: =IF(L60=0,0,N60/L60) -> 0.51049876
A61: 9 ft Animated Pirate Ship | B61: In-Store | C61: Downside | D61: =Assumptions!B22 -> 9000 | E61: ='Source data'!E8 -> 399 | F61: ='Source data'!F8 -> 184 | G61: =IF(B61="In-Store",'Source data'!J8+Assumptions!$B$15*'Source data'!K8,'Source data'!K8+Assumptions!$B$15*'Source data'!J8)*'Source data'!H8/'Source data'!G8*Assumptions!B8 -> 2457 | H61: =MIN(D61,G61) -> 2457 | I61: =(D61-H61)*Assumptions!C8 -> 3271.5 | J61: =D61-H61-I61 -> 3271.5 | K61: =E61*(H61+I61*Assumptions!D8) -> 1633007.2 | L61: =D61*F61 -> 1656000 | M61: =K61-(H61+I61)*F61 -> 578963.25 | N61: =K61-L61 -> -22992.75 | O61: =J61*F61 -> 601956 | P61: =IF(B61="In-Store",N61/V61,0) -> -11496.375 | Q61: =COUNTIFS('Product decisions'!$A$7:$A$32,A61,'Product decisions'!$C$7:$C$32,B61) -> 0 | R61: =COUNTIFS('Product decisions'!$A$7:$A$32,A61,'Product decisions'!$H$7:$H$32,B61) -> 0 | S61: =COUNTIFS('Product decisions'!$A$7:$A$32,A61,'Product decisions'!$I$7:$I$32,B61) -> 0 | T61: =COUNTIFS('Product decisions'!$A$7:$A$32,A61,'Product decisions'!$J$7:$J$32,B61) -> 0 | U61: =0 -> 0 | V61: ='Source data'!D8 -> 2 | W61: =IF(K61=0,0,N61/K61) -> -0.014080005 | X61: =IF(L61=0,0,N61/L61) -> -0.013884511
A62: 9 ft Animated Pirate Ship | B62: Online-Only | C62: Downside | D62: =Assumptions!B22 -> 9000 | E62: ='Source data'!E8 -> 399 | F62: ='Source data'!F8 -> 184 | G62: =IF(B62="In-Store",'Source data'!J8+Assumptions!$B$15*'Source data'!K8,'Source data'!K8+Assumptions!$B$15*'Source data'!J8)*'Source data'!H8/'Source data'!G8*Assumptions!B8 -> 3213 | H62: =MIN(D62,G62) -> 3213 | I62: =(D62-H62)*Assumptions!C8 -> 2893.5 | J62: =D62-H62-I62 -> 2893.5 | K62: =E62*(H62+I62*Assumptions!D8) -> 1859240.2 | L62: =D62*F62 -> 1656000 | M62: =K62-(H62+I62)*F62 -> 735644.25 | N62: =K62-L62 -> 203240.25 | O62: =J62*F62 -> 532404 | P62: =IF(B62="In-Store",N62/V62,0) -> 0 | Q62: =COUNTIFS('Product decisions'!$A$7:$A$32,A62,'Product decisions'!$C$7:$C$32,B62) -> 1 | R62: =COUNTIFS('Product decisions'!$A$7:$A$32,A62,'Product decisions'!$H$7:$H$32,B62) -> 1 | S62: =COUNTIFS('Product decisions'!$A$7:$A$32,A62,'Product decisions'!$I$7:$I$32,B62) -> 0 | T62: =COUNTIFS('Product decisions'!$A$7:$A$32,A62,'Product decisions'!$J$7:$J$32,B62) -> 1 | U62: =0 -> 0 | V62: ='Source data'!D8 -> 2 | W62: =IF(K62=0,0,N62/K62) -> 0.1093136 | X62: =IF(L62=0,0,N62/L62) -> 0.12272962
A63: 7 ft Animated Reaper | B63: In-Store | C63: Downside | D63: =Assumptions!B23 -> 12000 | E63: ='Source data'!E9 -> 279 | F63: ='Source data'!F9 -> 107 | G63: =IF(B63="In-Store",'Source data'!J9+Assumptions!$B$15*'Source data'!K9,'Source data'!K9+Assumptions!$B$15*'Source data'!J9)*'Source data'!H9/'Source data'!G9*Assumptions!B8 -> 5355 | H63: =MIN(D63,G63) -> 5355 | I63: =(D63-H63)*Assumptions!C8 -> 3322.5 | J63: =D63-H63-I63 -> 3322.5 | K63: =E63*(H63+I63*Assumptions!D8) -> 1957533.8 | L63: =D63*F63 -> 1284000 | M63: =K63-(H63+I63)*F63 -> 1029041.2 | N63: =K63-L63 -> 673533.75 | O63: =J63*F63 -> 355507.5 | P63: =IF(B63="In-Store",N63/V63,0) -> 673533.75 | Q63: =COUNTIFS('Product decisions'!$A$7:$A$32,A63,'Product decisions'!$C$7:$C$32,B63) -> 1 | R63: =COUNTIFS('Product decisions'!$A$7:$A$32,A63,'Product decisions'!$H$7:$H$32,B63) -> 1 | S63: =COUNTIFS('Product decisions'!$A$7:$A$32,A63,'Product decisions'!$I$7:$I$32,B63) -> 1 | T63: =COUNTIFS('Product decisions'!$A$7:$A$32,A63,'Product decisions'!$J$7:$J$32,B63) -> 1 | U63: =0 -> 0 | V63: ='Source data'!D9 -> 1 | W63: =IF(K63=0,0,N63/K63) -> 0.34407261 | X63: =IF(L63=0,0,N63/L63) -> 0.524559
A64: 7 ft Animated Reaper | B64: Online-Only | C64: Downside | D64: =Assumptions!B23 -> 12000 | E64: ='Source data'!E9 -> 279 | F64: ='Source data'!F9 -> 107 | G64: =IF(B64="In-Store",'Source data'!J9+Assumptions!$B$15*'Source data'!K9,'Source data'!K9+Assumptions!$B$15*'Source data'!J9)*'Source data'!H9/'Source data'!G9*Assumptions!B8 -> 5355 | H64: =MIN(D64,G64) -> 5355 | I64: =(D64-H64)*Assumptions!C8 -> 3322.5 | J64: =D64-H64-I64 -> 3322.5 | K64: =E64*(H64+I64*Assumptions!D8) -> 1957533.8 | L64: =D64*F64 -> 1284000 | M64: =K64-(H64+I64)*F64 -> 1029041.2 | N64: =K64-L64 -> 673533.75 | O64: =J64*F64 -> 355507.5 | P64: =IF(B64="In-Store",N64/V64,0) -> 0 | Q64: =COUNTIFS('Product decisions'!$A$7:$A$32,A64,'Product decisions'!$C$7:$C$32,B64) -> 0 | R64: =COUNTIFS('Product decisions'!$A$7:$A$32,A64,'Product decisions'!$H$7:$H$32,B64) -> 0 | S64: =COUNTIFS('Product decisions'!$A$7:$A$32,A64,'Product decisions'!$I$7:$I$32,B64) -> 0 | T64: =COUNTIFS('Product decisions'!$A$7:$A$32,A64,'Product decisions'!$J$7:$J$32,B64) -> 0 | U64: =0 -> 0 | V64: ='Source data'!D9 -> 1 | W64: =IF(K64=0,0,N64/K64) -> 0.34407261 | X64: =IF(L64=0,0,N64/L64) -> 0.524559
A65: 5.5 ft LED Skeleton Pony | B65: In-Store | C65: Downside | D65: =Assumptions!B24 -> 14000 | E65: ='Source data'!E10 -> 129 | F65: ='Source data'!F10 -> 42 | G65: =IF(B65="In-Store",'Source data'!J10+Assumptions!$B$15*'Source data'!K10,'Source data'!K10+Assumptions!$B$15*'Source data'!J10)*'Source data'!H10/'Source data'!G10*Assumptions!B8 -> 6076 | H65: =MIN(D65,G65) -> 6076 | I65: =(D65-H65)*Assumptions!C8 -> 3962 | J65: =D65-H65-I65 -> 3962 | K65: =E65*(H65+I65*Assumptions!D8) -> 1039353 | L65: =D65*F65 -> 588000 | M65: =K65-(H65+I65)*F65 -> 617757 | N65: =K65-L65 -> 451353 | O65: =J65*F65 -> 166404 | P65: =IF(B65="In-Store",N65/V65,0) -> 451353 | Q65: =COUNTIFS('Product decisions'!$A$7:$A$32,A65,'Product decisions'!$C$7:$C$32,B65) -> 1 | R65: =COUNTIFS('Product decisions'!$A$7:$A$32,A65,'Product decisions'!$H$7:$H$32,B65) -> 1 | S65: =COUNTIFS('Product decisions'!$A$7:$A$32,A65,'Product decisions'!$I$7:$I$32,B65) -> 1 | T65: =COUNTIFS('Product decisions'!$A$7:$A$32,A65,'Product decisions'!$J$7:$J$32,B65) -> 1 | U65: =0 -> 0 | V65: ='Source data'!D10 -> 1 | W65: =IF(K65=0,0,N65/K65) -> 0.43426343 | X65: =IF(L65=0,0,N65/L65) -> 0.76760714
A66: 5.5 ft LED Skeleton Pony | B66: Online-Only | C66: Downside | D66: =Assumptions!B24 -> 14000 | E66: ='Source data'!E10 -> 129 | F66: ='Source data'!F10 -> 42 | G66: =IF(B66="In-Store",'Source data'!J10+Assumptions!$B$15*'Source data'!K10,'Source data'!K10+Assumptions!$B$15*'Source data'!J10)*'Source data'!H10/'Source data'!G10*Assumptions!B8 -> 5684 | H66: =MIN(D66,G66) -> 5684 | I66: =(D66-H66)*Assumptions!C8 -> 4158 | J66: =D66-H66-I66 -> 4158 | K66: =E66*(H66+I66*Assumptions!D8) -> 1001427 | L66: =D66*F66 -> 588000 | M66: =K66-(H66+I66)*F66 -> 588063 | N66: =K66-L66 -> 413427 | O66: =J66*F66 -> 174636 | P66: =IF(B66="In-Store",N66/V66,0) -> 0 | Q66: =COUNTIFS('Product decisions'!$A$7:$A$32,A66,'Product decisions'!$C$7:$C$32,B66) -> 0 | R66: =COUNTIFS('Product decisions'!$A$7:$A$32,A66,'Product decisions'!$H$7:$H$32,B66) -> 0 | S66: =COUNTIFS('Product decisions'!$A$7:$A$32,A66,'Product decisions'!$I$7:$I$32,B66) -> 0 | T66: =COUNTIFS('Product decisions'!$A$7:$A$32,A66,'Product decisions'!$J$7:$J$32,B66) -> 0 | U66: =0 -> 0 | V66: ='Source data'!D10 -> 1 | W66: =IF(K66=0,0,N66/K66) -> 0.41283788 | X66: =IF(L66=0,0,N66/L66) -> 0.70310714
A67: 10.5 ft Licensed Character Inflatable | B67: In-Store | C67: Downside | D67: =Assumptions!B25 -> 8000 | E67: ='Source data'!E11 -> 149 | F67: ='Source data'!F11 -> 132 | G67: =IF(B67="In-Store",'Source data'!J11+Assumptions!$B$15*'Source data'!K11,'Source data'!K11+Assumptions!$B$15*'Source data'!J11)*'Source data'!H11/'Source data'!G11*Assumptions!B8 -> 3332 | H67: =MIN(D67,G67) -> 3332 | I67: =(D67-H67)*Assumptions!C8 -> 2334 | J67: =D67-H67-I67 -> 2334 | K67: =E67*(H67+I67*Assumptions!D8) -> 670351 | L67: =D67*F67 -> 1056000 | M67: =K67-(H67+I67)*F67 -> -77561 | N67: =K67-L67 -> -385649 | O67: =J67*F67 -> 308088 | P67: =IF(B67="In-Store",N67/V67,0) -> -192824.5 | Q67: =COUNTIFS('Product decisions'!$A$7:$A$32,A67,'Product decisions'!$C$7:$C$32,B67) -> 0 | R67: =COUNTIFS('Product decisions'!$A$7:$A$32,A67,'Product decisions'!$H$7:$H$32,B67) -> 0 | S67: =COUNTIFS('Product decisions'!$A$7:$A$32,A67,'Product decisions'!$I$7:$I$32,B67) -> 0 | T67: =COUNTIFS('Product decisions'!$A$7:$A$32,A67,'Product decisions'!$J$7:$J$32,B67) -> 0 | U67: =0 -> 0 | V67: ='Source data'!D11 -> 2 | W67: =IF(K67=0,0,N67/K67) -> -0.57529414 | X67: =IF(L67=0,0,N67/L67) -> -0.36519792
A68: 10.5 ft Licensed Character Inflatable | B68: Online-Only | C68: Downside | D68: =Assumptions!B25 -> 8000 | E68: ='Source data'!E11 -> 149 | F68: ='Source data'!F11 -> 132 | G68: =IF(B68="In-Store",'Source data'!J11+Assumptions!$B$15*'Source data'!K11,'Source data'!K11+Assumptions!$B$15*'Source data'!J11)*'Source data'!H11/'Source data'!G11*Assumptions!B8 -> 3808 | H68: =MIN(D68,G68) -> 3808 | I68: =(D68-H68)*Assumptions!C8 -> 2096 | J68: =D68-H68-I68 -> 2096 | K68: =E68*(H68+I68*Assumptions!D8) -> 723544 | L68: =D68*F68 -> 1056000 | M68: =K68-(H68+I68)*F68 -> -55784 | N68: =K68-L68 -> -332456 | O68: =J68*F68 -> 276672 | P68: =IF(B68="In-Store",N68/V68,0) -> 0 | Q68: =COUNTIFS('Product decisions'!$A$7:$A$32,A68,'Product decisions'!$C$7:$C$32,B68) -> 0 | R68: =COUNTIFS('Product decisions'!$A$7:$A$32,A68,'Product decisions'!$H$7:$H$32,B68) -> 0 | S68: =COUNTIFS('Product decisions'!$A$7:$A$32,A68,'Product decisions'!$I$7:$I$32,B68) -> 0 | T68: =COUNTIFS('Product decisions'!$A$7:$A$32,A68,'Product decisions'!$J$7:$J$32,B68) -> 0 | U68: =0 -> 0 | V68: ='Source data'!D11 -> 2 | W68: =IF(K68=0,0,N68/K68) -> -0.45948277 | X68: =IF(L68=0,0,N68/L68) -> -0.31482576
A69: 9.5 ft Licensed Sandworm Inflatable | B69: In-Store | C69: Downside | D69: =Assumptions!B26 -> 5000 | E69: ='Source data'!E12 -> 269 | F69: ='Source data'!F12 -> 160 | G69: =IF(B69="In-Store",'Source data'!J12+Assumptions!$B$15*'Source data'!K12,'Source data'!K12+Assumptions!$B$15*'Source data'!J12)*'Source data'!H12/'Source data'!G12*Assumptions!B8 -> 1890 | H69: =MIN(D69,G69) -> 1890 | I69: =(D69-H69)*Assumptions!C8 -> 1555 | J69: =D69-H69-I69 -> 1555 | K69: =E69*(H69+I69*Assumptions!D8) -> 717557.5 | L69: =D69*F69 -> 800000 | M69: =K69-(H69+I69)*F69 -> 166357.5 | N69: =K69-L69 -> -82442.5 | O69: =J69*F69 -> 248800 | P69: =IF(B69="In-Store",N69/V69,0) -> -82442.5 | Q69: =COUNTIFS('Product decisions'!$A$7:$A$32,A69,'Product decisions'!$C$7:$C$32,B69) -> 1 | R69: =COUNTIFS('Product decisions'!$A$7:$A$32,A69,'Product decisions'!$H$7:$H$32,B69) -> 0 | S69: =COUNTIFS('Product decisions'!$A$7:$A$32,A69,'Product decisions'!$I$7:$I$32,B69) -> 0 | T69: =COUNTIFS('Product decisions'!$A$7:$A$32,A69,'Product decisions'!$J$7:$J$32,B69) -> 1 | U69: =0 -> 0 | V69: ='Source data'!D12 -> 1 | W69: =IF(K69=0,0,N69/K69) -> -0.11489323 | X69: =IF(L69=0,0,N69/L69) -> -0.10305312
A70: 9.5 ft Licensed Sandworm Inflatable | B70: Online-Only | C70: Downside | D70: =Assumptions!B26 -> 5000 | E70: ='Source data'!E12 -> 269 | F70: ='Source data'!F12 -> 160 | G70: =IF(B70="In-Store",'Source data'!J12+Assumptions!$B$15*'Source data'!K12,'Source data'!K12+Assumptions!$B$15*'Source data'!J12)*'Source data'!H12/'Source data'!G12*Assumptions!B8 -> 2310 | H70: =MIN(D70,G70) -> 2310 | I70: =(D70-H70)*Assumptions!C8 -> 1345 | J70: =D70-H70-I70 -> 1345 | K70: =E70*(H70+I70*Assumptions!D8) -> 802292.5 | L70: =D70*F70 -> 800000 | M70: =K70-(H70+I70)*F70 -> 217492.5 | N70: =K70-L70 -> 2292.5 | O70: =J70*F70 -> 215200 | P70: =IF(B70="In-Store",N70/V70,0) -> 0 | Q70: =COUNTIFS('Product decisions'!$A$7:$A$32,A70,'Product decisions'!$C$7:$C$32,B70) -> 0 | R70: =COUNTIFS('Product decisions'!$A$7:$A$32,A70,'Product decisions'!$H$7:$H$32,B70) -> 0 | S70: =COUNTIFS('Product decisions'!$A$7:$A$32,A70,'Product decisions'!$I$7:$I$32,B70) -> 0 | T70: =COUNTIFS('Product decisions'!$A$7:$A$32,A70,'Product decisions'!$J$7:$J$32,B70) -> 0 | U70: =0 -> 0 | V70: ='Source data'!D12 -> 1 | W70: =IF(K70=0,0,N70/K70) -> 0.0028574367 | X70: =IF(L70=0,0,N70/L70) -> 0.002865625
A71: 12 ft Reaper Inflatable | B71: In-Store | C71: Downside | D71: =Assumptions!B27 -> 6000 | E71: ='Source data'!E13 -> 119 | F71: ='Source data'!F13 -> 87 | G71: =IF(B71="In-Store",'Source data'!J13+Assumptions!$B$15*'Source data'!K13,'Source data'!K13+Assumptions!$B$15*'Source data'!J13)*'Source data'!H13/'Source data'!G13*Assumptions!B8 -> 1522.5 | H71: =MIN(D71,G71) -> 1522.5 | I71: =(D71-H71)*Assumptions!C8 -> 2238.75 | J71: =D71-H71-I71 -> 2238.75 | K71: =E71*(H71+I71*Assumptions!D8) -> 314383.12 | L71: =D71*F71 -> 522000 | M71: =K71-(H71+I71)*F71 -> -12845.625 | N71: =K71-L71 -> -207616.88 | O71: =J71*F71 -> 194771.25 | P71: =IF(B71="In-Store",N71/V71,0) -> -207616.88 | Q71: =COUNTIFS('Product decisions'!$A$7:$A$32,A71,'Product decisions'!$C$7:$C$32,B71) -> 0 | R71: =COUNTIFS('Product decisions'!$A$7:$A$32,A71,'Product decisions'!$H$7:$H$32,B71) -> 0 | S71: =COUNTIFS('Product decisions'!$A$7:$A$32,A71,'Product decisions'!$I$7:$I$32,B71) -> 0 | T71: =COUNTIFS('Product decisions'!$A$7:$A$32,A71,'Product decisions'!$J$7:$J$32,B71) -> 0 | U71: =0 -> 0 | V71: ='Source data'!D13 -> 1 | W71: =IF(K71=0,0,N71/K71) -> -0.66039446 | X71: =IF(L71=0,0,N71/L71) -> -0.39773348
A72: 12 ft Reaper Inflatable | B72: Online-Only | C72: Downside | D72: =Assumptions!B27 -> 6000 | E72: ='Source data'!E13 -> 119 | F72: ='Source data'!F13 -> 87 | G72: =IF(B72="In-Store",'Source data'!J13+Assumptions!$B$15*'Source data'!K13,'Source data'!K13+Assumptions!$B$15*'Source data'!J13)*'Source data'!H13/'Source data'!G13*Assumptions!B8 -> 1627.5 | H72: =MIN(D72,G72) -> 1627.5 | I72: =(D72-H72)*Assumptions!C8 -> 2186.25 | J72: =D72-H72-I72 -> 2186.25 | K72: =E72*(H72+I72*Assumptions!D8) -> 323754.38 | L72: =D72*F72 -> 522000 | M72: =K72-(H72+I72)*F72 -> -8041.875 | N72: =K72-L72 -> -198245.62 | O72: =J72*F72 -> 190203.75 | P72: =IF(B72="In-Store",N72/V72,0) -> 0 | Q72: =COUNTIFS('Product decisions'!$A$7:$A$32,A72,'Product decisions'!$C$7:$C$32,B72) -> 0 | R72: =COUNTIFS('Product decisions'!$A$7:$A$32,A72,'Product decisions'!$H$7:$H$32,B72) -> 0 | S72: =COUNTIFS('Product decisions'!$A$7:$A$32,A72,'Product decisions'!$I$7:$I$32,B72) -> 0 | T72: =COUNTIFS('Product decisions'!$A$7:$A$32,A72,'Product decisions'!$J$7:$J$32,B72) -> 0 | U72: =0 -> 0 | V72: ='Source data'!D13 -> 1 | W72: =IF(K72=0,0,N72/K72) -> -0.61233342 | X72: =IF(L72=0,0,N72/L72) -> -0.37978089
A73: 6 ft Scarecrow Inflatable | B73: In-Store | C73: Downside | D73: =Assumptions!B28 -> 20000 | E73: ='Source data'!E14 -> 59 | F73: ='Source data'!F14 -> 35 | G73: =IF(B73="In-Store",'Source data'!J14+Assumptions!$B$15*'Source data'!K14,'Source data'!K14+Assumptions!$B$15*'Source data'!J14)*'Source data'!H14/'Source data'!G14*Assumptions!B8 -> 9817.5 | H73: =MIN(D73,G73) -> 9817.5 | I73: =(D73-H73)*Assumptions!C8 -> 5091.25 | J73: =D73-H73-I73 -> 5091.25 | K73: =E73*(H73+I73*Assumptions!D8) -> 729424.38 | L73: =D73*F73 -> 700000 | M73: =K73-(H73+I73)*F73 -> 207618.12 | N73: =K73-L73 -> 29424.375 | O73: =J73*F73 -> 178193.75 | P73: =IF(B73="In-Store",N73/V73,0) -> 29424.375 | Q73: =COUNTIFS('Product decisions'!$A$7:$A$32,A73,'Product decisions'!$C$7:$C$32,B73) -> 1 | R73: =COUNTIFS('Product decisions'!$A$7:$A$32,A73,'Product decisions'!$H$7:$H$32,B73) -> 0 | S73: =COUNTIFS('Product decisions'!$A$7:$A$32,A73,'Product decisions'!$I$7:$I$32,B73) -> 0 | T73: =COUNTIFS('Product decisions'!$A$7:$A$32,A73,'Product decisions'!$J$7:$J$32,B73) -> 1 | U73: =0 -> 0 | V73: ='Source data'!D14 -> 1 | W73: =IF(K73=0,0,N73/K73) -> 0.040339172 | X73: =IF(L73=0,0,N73/L73) -> 0.042034821
A74: 6 ft Scarecrow Inflatable | B74: Online-Only | C74: Downside | D74: =Assumptions!B28 -> 20000 | E74: ='Source data'!E14 -> 59 | F74: ='Source data'!F14 -> 35 | G74: =IF(B74="In-Store",'Source data'!J14+Assumptions!$B$15*'Source data'!K14,'Source data'!K14+Assumptions!$B$15*'Source data'!J14)*'Source data'!H14/'Source data'!G14*Assumptions!B8 -> 8032.5 | H74: =MIN(D74,G74) -> 8032.5 | I74: =(D74-H74)*Assumptions!C8 -> 5983.75 | J74: =D74-H74-I74 -> 5983.75 | K74: =E74*(H74+I74*Assumptions!D8) -> 650438.12 | L74: =D74*F74 -> 700000 | M74: =K74-(H74+I74)*F74 -> 159869.38 | N74: =K74-L74 -> -49561.875 | O74: =J74*F74 -> 209431.25 | P74: =IF(B74="In-Store",N74/V74,0) -> 0 | Q74: =COUNTIFS('Product decisions'!$A$7:$A$32,A74,'Product decisions'!$C$7:$C$32,B74) -> 0 | R74: =COUNTIFS('Product decisions'!$A$7:$A$32,A74,'Product decisions'!$H$7:$H$32,B74) -> 0 | S74: =COUNTIFS('Product decisions'!$A$7:$A$32,A74,'Product decisions'!$I$7:$I$32,B74) -> 0 | T74: =COUNTIFS('Product decisions'!$A$7:$A$32,A74,'Product decisions'!$J$7:$J$32,B74) -> 0 | U74: =0 -> 0 | V74: ='Source data'!D14 -> 1 | W74: =IF(K74=0,0,N74/K74) -> -0.076197678 | X74: =IF(L74=0,0,N74/L74) -> -0.070802679
A75: 24 in Metal Tombstone | B75: In-Store | C75: Downside | D75: =Assumptions!B29 -> 30000 | E75: ='Source data'!E15 -> 24.98 | F75: ='Source data'!F15 -> 4.25 | G75: =IF(B75="In-Store",'Source data'!J15+Assumptions!$B$15*'Source data'!K15,'Source data'!K15+Assumptions!$B$15*'Source data'!J15)*'Source data'!H15/'Source data'!G15*Assumptions!B8 -> 14280 | H75: =MIN(D75,G75) -> 14280 | I75: =(D75-H75)*Assumptions!C8 -> 7860 | J75: =D75-H75-I75 -> 7860 | K75: =E75*(H75+I75*Assumptions!D8) -> 454885.8 | L75: =D75*F75 -> 127500 | M75: =K75-(H75+I75)*F75 -> 360790.8 | N75: =K75-L75 -> 327385.8 | O75: =J75*F75 -> 33405 | P75: =IF(B75="In-Store",N75/V75,0) -> 327385.8 | Q75: =COUNTIFS('Product decisions'!$A$7:$A$32,A75,'Product decisions'!$C$7:$C$32,B75) -> 1 | R75: =COUNTIFS('Product decisions'!$A$7:$A$32,A75,'Product decisions'!$H$7:$H$32,B75) -> 1 | S75: =COUNTIFS('Product decisions'!$A$7:$A$32,A75,'Product decisions'!$I$7:$I$32,B75) -> 1 | T75: =COUNTIFS('Product decisions'!$A$7:$A$32,A75,'Product decisions'!$J$7:$J$32,B75) -> 1 | U75: =0 -> 0 | V75: ='Source data'!D15 -> 1 | W75: =IF(K75=0,0,N75/K75) -> 0.71970987 | X75: =IF(L75=0,0,N75/L75) -> 2.5677318
A76: 24 in Metal Tombstone | B76: Online-Only | C76: Downside | D76: =Assumptions!B29 -> 30000 | E76: ='Source data'!E15 -> 24.98 | F76: ='Source data'!F15 -> 4.25 | G76: =IF(B76="In-Store",'Source data'!J15+Assumptions!$B$15*'Source data'!K15,'Source data'!K15+Assumptions!$B$15*'Source data'!J15)*'Source data'!H15/'Source data'!G15*Assumptions!B8 -> 10920 | H76: =MIN(D76,G76) -> 10920 | I76: =(D76-H76)*Assumptions!C8 -> 9540 | J76: =D76-H76-I76 -> 9540 | K76: =E76*(H76+I76*Assumptions!D8) -> 391936.2 | L76: =D76*F76 -> 127500 | M76: =K76-(H76+I76)*F76 -> 304981.2 | N76: =K76-L76 -> 264436.2 | O76: =J76*F76 -> 40545 | P76: =IF(B76="In-Store",N76/V76,0) -> 0 | Q76: =COUNTIFS('Product decisions'!$A$7:$A$32,A76,'Product decisions'!$C$7:$C$32,B76) -> 0 | R76: =COUNTIFS('Product decisions'!$A$7:$A$32,A76,'Product decisions'!$H$7:$H$32,B76) -> 0 | S76: =COUNTIFS('Product decisions'!$A$7:$A$32,A76,'Product decisions'!$I$7:$I$32,B76) -> 0 | T76: =COUNTIFS('Product decisions'!$A$7:$A$32,A76,'Product decisions'!$J$7:$J$32,B76) -> 0 | U76: =0 -> 0 | V76: ='Source data'!D15 -> 1 | W76: =IF(K76=0,0,N76/K76) -> 0.67469195 | X76: =IF(L76=0,0,N76/L76) -> 2.0740094
A77: 5 ft Skeleton Tombstone | B77: In-Store | C77: Downside | D77: =Assumptions!B30 -> 7000 | E77: ='Source data'!E16 -> 149 | F77: ='Source data'!F16 -> 52 | G77: =IF(B77="In-Store",'Source data'!J16+Assumptions!$B$15*'Source data'!K16,'Source data'!K16+Assumptions!$B$15*'Source data'!J16)*'Source data'!H16/'Source data'!G16*Assumptions!B8 -> 2842 | H77: =MIN(D77,G77) -> 2842 | I77: =(D77-H77)*Assumptions!C8 -> 2079 | J77: =D77-H77-I77 -> 2079 | K77: =E77*(H77+I77*Assumptions!D8) -> 578343.5 | L77: =D77*F77 -> 364000 | M77: =K77-(H77+I77)*F77 -> 322451.5 | N77: =K77-L77 -> 214343.5 | O77: =J77*F77 -> 108108 | P77: =IF(B77="In-Store",N77/V77,0) -> 214343.5 | Q77: =COUNTIFS('Product decisions'!$A$7:$A$32,A77,'Product decisions'!$C$7:$C$32,B77) -> 1 | R77: =COUNTIFS('Product decisions'!$A$7:$A$32,A77,'Product decisions'!$H$7:$H$32,B77) -> 1 | S77: =COUNTIFS('Product decisions'!$A$7:$A$32,A77,'Product decisions'!$I$7:$I$32,B77) -> 1 | T77: =COUNTIFS('Product decisions'!$A$7:$A$32,A77,'Product decisions'!$J$7:$J$32,B77) -> 1 | U77: =0 -> 0 | V77: ='Source data'!D16 -> 1 | W77: =IF(K77=0,0,N77/K77) -> 0.37061625 | X77: =IF(L77=0,0,N77/L77) -> 0.58885577
A78: 5 ft Skeleton Tombstone | B78: Online-Only | C78: Downside | D78: =Assumptions!B30 -> 7000 | E78: ='Source data'!E16 -> 149 | F78: ='Source data'!F16 -> 52 | G78: =IF(B78="In-Store",'Source data'!J16+Assumptions!$B$15*'Source data'!K16,'Source data'!K16+Assumptions!$B$15*'Source data'!J16)*'Source data'!H16/'Source data'!G16*Assumptions!B8 -> 3038 | H78: =MIN(D78,G78) -> 3038 | I78: =(D78-H78)*Assumptions!C8 -> 1981 | J78: =D78-H78-I78 -> 1981 | K78: =E78*(H78+I78*Assumptions!D8) -> 600246.5 | L78: =D78*F78 -> 364000 | M78: =K78-(H78+I78)*F78 -> 339258.5 | N78: =K78-L78 -> 236246.5 | O78: =J78*F78 -> 103012 | P78: =IF(B78="In-Store",N78/V78,0) -> 0 | Q78: =COUNTIFS('Product decisions'!$A$7:$A$32,A78,'Product decisions'!$C$7:$C$32,B78) -> 0 | R78: =COUNTIFS('Product decisions'!$A$7:$A$32,A78,'Product decisions'!$H$7:$H$32,B78) -> 0 | S78: =COUNTIFS('Product decisions'!$A$7:$A$32,A78,'Product decisions'!$I$7:$I$32,B78) -> 0 | T78: =COUNTIFS('Product decisions'!$A$7:$A$32,A78,'Product decisions'!$J$7:$J$32,B78) -> 0 | U78: =0 -> 0 | V78: ='Source data'!D16 -> 1 | W78: =IF(K78=0,0,N78/K78) -> 0.39358247 | X78: =IF(L78=0,0,N78/L78) -> 0.64902885
A79: LED Fog Machine | B79: In-Store | C79: Downside | D79: =Assumptions!B31 -> 25000 | E79: ='Source data'!E17 -> 59 | F79: ='Source data'!F17 -> 37 | G79: =IF(B79="In-Store",'Source data'!J17+Assumptions!$B$15*'Source data'!K17,'Source data'!K17+Assumptions!$B$15*'Source data'!J17)*'Source data'!H17/'Source data'!G17*Assumptions!B8 -> 4480 | H79: =MIN(D79,G79) -> 4480 | I79: =(D79-H79)*Assumptions!C8 -> 10260 | J79: =D79-H79-I79 -> 10260 | K79: =E79*(H79+I79*Assumptions!D8) -> 566990 | L79: =D79*F79 -> 925000 | M79: =K79-(H79+I79)*F79 -> 21610 | N79: =K79-L79 -> -358010 | O79: =J79*F79 -> 379620 | P79: =IF(B79="In-Store",N79/V79,0) -> -358010 | Q79: =COUNTIFS('Product decisions'!$A$7:$A$32,A79,'Product decisions'!$C$7:$C$32,B79) -> 0 | R79: =COUNTIFS('Product decisions'!$A$7:$A$32,A79,'Product decisions'!$H$7:$H$32,B79) -> 0 | S79: =COUNTIFS('Product decisions'!$A$7:$A$32,A79,'Product decisions'!$I$7:$I$32,B79) -> 0 | T79: =COUNTIFS('Product decisions'!$A$7:$A$32,A79,'Product decisions'!$J$7:$J$32,B79) -> 0 | U79: =0 -> 0 | V79: ='Source data'!D17 -> 1 | W79: =IF(K79=0,0,N79/K79) -> -0.63142207 | X79: =IF(L79=0,0,N79/L79) -> -0.38703784
A80: LED Fog Machine | B80: Online-Only | C80: Downside | D80: =Assumptions!B31 -> 25000 | E80: ='Source data'!E17 -> 59 | F80: ='Source data'!F17 -> 37 | G80: =IF(B80="In-Store",'Source data'!J17+Assumptions!$B$15*'Source data'!K17,'Source data'!K17+Assumptions!$B$15*'Source data'!J17)*'Source data'!H17/'Source data'!G17*Assumptions!B8 -> 3920 | H80: =MIN(D80,G80) -> 3920 | I80: =(D80-H80)*Assumptions!C8 -> 10540 | J80: =D80-H80-I80 -> 10540 | K80: =E80*(H80+I80*Assumptions!D8) -> 542210 | L80: =D80*F80 -> 925000 | M80: =K80-(H80+I80)*F80 -> 7190 | N80: =K80-L80 -> -382790 | O80: =J80*F80 -> 389980 | P80: =IF(B80="In-Store",N80/V80,0) -> 0 | Q80: =COUNTIFS('Product decisions'!$A$7:$A$32,A80,'Product decisions'!$C$7:$C$32,B80) -> 0 | R80: =COUNTIFS('Product decisions'!$A$7:$A$32,A80,'Product decisions'!$H$7:$H$32,B80) -> 0 | S80: =COUNTIFS('Product decisions'!$A$7:$A$32,A80,'Product decisions'!$I$7:$I$32,B80) -> 0 | T80: =COUNTIFS('Product decisions'!$A$7:$A$32,A80,'Product decisions'!$J$7:$J$32,B80) -> 0 | U80: =0 -> 0 | V80: ='Source data'!D17 -> 1 | W80: =IF(K80=0,0,N80/K80) -> -0.70598108 | X80: =IF(L80=0,0,N80/L80) -> -0.41382703
A81: Pathway Light Set (6-piece) | B81: In-Store | C81: Downside | D81: =Assumptions!B32 -> 18000 | E81: ='Source data'!E18 -> 34.98 | F81: ='Source data'!F18 -> 12 | G81: =IF(B81="In-Store",'Source data'!J18+Assumptions!$B$15*'Source data'!K18,'Source data'!K18+Assumptions!$B$15*'Source data'!J18)*'Source data'!H18/'Source data'!G18*Assumptions!B8 -> 9103.5 | H81: =MIN(D81,G81) -> 9103.5 | I81: =(D81-H81)*Assumptions!C8 -> 4448.25 | J81: =D81-H81-I81 -> 4448.25 | K81: =E81*(H81+I81*Assumptions!D8) -> 396240.32 | L81: =D81*F81 -> 216000 | M81: =K81-(H81+I81)*F81 -> 233619.32 | N81: =K81-L81 -> 180240.32 | O81: =J81*F81 -> 53379 | P81: =IF(B81="In-Store",N81/V81,0) -> 180240.32 | Q81: =COUNTIFS('Product decisions'!$A$7:$A$32,A81,'Product decisions'!$C$7:$C$32,B81) -> 1 | R81: =COUNTIFS('Product decisions'!$A$7:$A$32,A81,'Product decisions'!$H$7:$H$32,B81) -> 1 | S81: =COUNTIFS('Product decisions'!$A$7:$A$32,A81,'Product decisions'!$I$7:$I$32,B81) -> 1 | T81: =COUNTIFS('Product decisions'!$A$7:$A$32,A81,'Product decisions'!$J$7:$J$32,B81) -> 1 | U81: =0 -> 0 | V81: ='Source data'!D18 -> 1 | W81: =IF(K81=0,0,N81/K81) -> 0.45487628 | X81: =IF(L81=0,0,N81/L81) -> 0.83444594
A82: Pathway Light Set (6-piece) | B82: Online-Only | C82: Downside | D82: =Assumptions!B32 -> 18000 | E82: ='Source data'!E18 -> 34.98 | F82: ='Source data'!F18 -> 12 | G82: =IF(B82="In-Store",'Source data'!J18+Assumptions!$B$15*'Source data'!K18,'Source data'!K18+Assumptions!$B$15*'Source data'!J18)*'Source data'!H18/'Source data'!G18*Assumptions!B8 -> 6961.5 | H82: =MIN(D82,G82) -> 6961.5 | I82: =(D82-H82)*Assumptions!C8 -> 5519.25 | J82: =D82-H82-I82 -> 5519.25 | K82: =E82*(H82+I82*Assumptions!D8) -> 340044.95 | L82: =D82*F82 -> 216000 | M82: =K82-(H82+I82)*F82 -> 190275.95 | N82: =K82-L82 -> 124044.95 | O82: =J82*F82 -> 66231 | P82: =IF(B82="In-Store",N82/V82,0) -> 0 | Q82: =COUNTIFS('Product decisions'!$A$7:$A$32,A82,'Product decisions'!$C$7:$C$32,B82) -> 0 | R82: =COUNTIFS('Product decisions'!$A$7:$A$32,A82,'Product decisions'!$H$7:$H$32,B82) -> 0 | S82: =COUNTIFS('Product decisions'!$A$7:$A$32,A82,'Product decisions'!$I$7:$I$32,B82) -> 0 | T82: =COUNTIFS('Product decisions'!$A$7:$A$32,A82,'Product decisions'!$J$7:$J$32,B82) -> 0 | U82: =0 -> 0 | V82: ='Source data'!D18 -> 1 | W82: =IF(K82=0,0,N82/K82) -> 0.36478987 | X82: =IF(L82=0,0,N82/L82) -> 0.57428219
A83: 16 ft Inflatable Haunted Archway | B83: In-Store | C83: Downside | D83: =Assumptions!B33 -> 6000 | E83: ='Source data'!E19 -> 199 | F83: ='Source data'!F19 -> 95 | G83: =IF(B83="In-Store",'Source data'!J19+Assumptions!$B$15*'Source data'!K19,'Source data'!K19+Assumptions!$B$15*'Source data'!J19)*'Source data'!H19/'Source data'!G19*Assumptions!B8 -> 1785 | H83: =MIN(D83,G83) -> 1785 | I83: =(D83-H83)*Assumptions!C8 -> 2107.5 | J83: =D83-H83-I83 -> 2107.5 | K83: =E83*(H83+I83*Assumptions!D8) -> 564911.25 | L83: =D83*F83 -> 570000 | M83: =K83-(H83+I83)*F83 -> 195123.75 | N83: =K83-L83 -> -5088.75 | O83: =J83*F83 -> 200212.5 | P83: =IF(B83="In-Store",N83/V83,0) -> -1696.25 | Q83: =COUNTIFS('Product decisions'!$A$7:$A$32,A83,'Product decisions'!$C$7:$C$32,B83) -> 0 | R83: =COUNTIFS('Product decisions'!$A$7:$A$32,A83,'Product decisions'!$H$7:$H$32,B83) -> 0 | S83: =COUNTIFS('Product decisions'!$A$7:$A$32,A83,'Product decisions'!$I$7:$I$32,B83) -> 1 | T83: =COUNTIFS('Product decisions'!$A$7:$A$32,A83,'Product decisions'!$J$7:$J$32,B83) -> 0 | U83: =0 -> 0 | V83: ='Source data'!D19 -> 3 | W83: =IF(K83=0,0,N83/K83) -> -0.0090080521 | X83: =IF(L83=0,0,N83/L83) -> -0.0089276316
A84: 16 ft Inflatable Haunted Archway | B84: Online-Only | C84: Downside | D84: =Assumptions!B33 -> 6000 | E84: ='Source data'!E19 -> 199 | F84: ='Source data'!F19 -> 95 | G84: =IF(B84="In-Store",'Source data'!J19+Assumptions!$B$15*'Source data'!K19,'Source data'!K19+Assumptions!$B$15*'Source data'!J19)*'Source data'!H19/'Source data'!G19*Assumptions!B8 -> 3570 | H84: =MIN(D84,G84) -> 3570 | I84: =(D84-H84)*Assumptions!C8 -> 1215 | J84: =D84-H84-I84 -> 1215 | K84: =E84*(H84+I84*Assumptions!D8) -> 831322.5 | L84: =D84*F84 -> 570000 | M84: =K84-(H84+I84)*F84 -> 376747.5 | N84: =K84-L84 -> 261322.5 | O84: =J84*F84 -> 115425 | P84: =IF(B84="In-Store",N84/V84,0) -> 0 | Q84: =COUNTIFS('Product decisions'!$A$7:$A$32,A84,'Product decisions'!$C$7:$C$32,B84) -> 1 | R84: =COUNTIFS('Product decisions'!$A$7:$A$32,A84,'Product decisions'!$H$7:$H$32,B84) -> 1 | S84: =COUNTIFS('Product decisions'!$A$7:$A$32,A84,'Product decisions'!$I$7:$I$32,B84) -> 0 | T84: =COUNTIFS('Product decisions'!$A$7:$A$32,A84,'Product decisions'!$J$7:$J$32,B84) -> 1 | U84: =0 -> 0 | V84: ='Source data'!D19 -> 3 | W84: =IF(K84=0,0,N84/K84) -> 0.31434552 | X84: =IF(L84=0,0,N84/L84) -> 0.45846053
A85: Life-Size Animated Butler | B85: In-Store | C85: Downside | D85: =Assumptions!B34 -> 4000 | E85: ='Source data'!E20 -> 399 | F85: ='Source data'!F20 -> 150 | G85: =IF(B85="In-Store",'Source data'!J20+Assumptions!$B$15*'Source data'!K20,'Source data'!K20+Assumptions!$B$15*'Source data'!J20)*'Source data'!H20/'Source data'!G20*Assumptions!B8 -> 1260 | H85: =MIN(D85,G85) -> 1260 | I85: =(D85-H85)*Assumptions!C8 -> 1370 | J85: =D85-H85-I85 -> 1370 | K85: =E85*(H85+I85*Assumptions!D8) -> 776055 | L85: =D85*F85 -> 600000 | M85: =K85-(H85+I85)*F85 -> 381555 | N85: =K85-L85 -> 176055 | O85: =J85*F85 -> 205500 | P85: =IF(B85="In-Store",N85/V85,0) -> 88027.5 | Q85: =COUNTIFS('Product decisions'!$A$7:$A$32,A85,'Product decisions'!$C$7:$C$32,B85) -> 0 | R85: =COUNTIFS('Product decisions'!$A$7:$A$32,A85,'Product decisions'!$H$7:$H$32,B85) -> 0 | S85: =COUNTIFS('Product decisions'!$A$7:$A$32,A85,'Product decisions'!$I$7:$I$32,B85) -> 0 | T85: =COUNTIFS('Product decisions'!$A$7:$A$32,A85,'Product decisions'!$J$7:$J$32,B85) -> 0 | U85: =0 -> 0 | V85: ='Source data'!D20 -> 2 | W85: =IF(K85=0,0,N85/K85) -> 0.22685892 | X85: =IF(L85=0,0,N85/L85) -> 0.293425
A86: Life-Size Animated Butler | B86: Online-Only | C86: Downside | D86: =Assumptions!B34 -> 4000 | E86: ='Source data'!E20 -> 399 | F86: ='Source data'!F20 -> 150 | G86: =IF(B86="In-Store",'Source data'!J20+Assumptions!$B$15*'Source data'!K20,'Source data'!K20+Assumptions!$B$15*'Source data'!J20)*'Source data'!H20/'Source data'!G20*Assumptions!B8 -> 2520 | H86: =MIN(D86,G86) -> 2520 | I86: =(D86-H86)*Assumptions!C8 -> 740 | J86: =D86-H86-I86 -> 740 | K86: =E86*(H86+I86*Assumptions!D8) -> 1153110 | L86: =D86*F86 -> 600000 | M86: =K86-(H86+I86)*F86 -> 664110 | N86: =K86-L86 -> 553110 | O86: =J86*F86 -> 111000 | P86: =IF(B86="In-Store",N86/V86,0) -> 0 | Q86: =COUNTIFS('Product decisions'!$A$7:$A$32,A86,'Product decisions'!$C$7:$C$32,B86) -> 1 | R86: =COUNTIFS('Product decisions'!$A$7:$A$32,A86,'Product decisions'!$H$7:$H$32,B86) -> 1 | S86: =COUNTIFS('Product decisions'!$A$7:$A$32,A86,'Product decisions'!$I$7:$I$32,B86) -> 1 | T86: =COUNTIFS('Product decisions'!$A$7:$A$32,A86,'Product decisions'!$J$7:$J$32,B86) -> 1 | U86: =0 -> 0 | V86: ='Source data'!D20 -> 2 | W86: =IF(K86=0,0,N86/K86) -> 0.47966803 | X86: =IF(L86=0,0,N86/L86) -> 0.92185
A87: Animated Witch Cauldron | B87: In-Store | C87: Downside | D87: =Assumptions!B35 -> 5000 | E87: ='Source data'!E21 -> 79 | F87: ='Source data'!F21 -> 30 | G87: =IF(B87="In-Store",'Source data'!J21+Assumptions!$B$15*'Source data'!K21,'Source data'!K21+Assumptions!$B$15*'Source data'!J21)*'Source data'!H21/'Source data'!G21*Assumptions!B8 -> 1487.5 | H87: =MIN(D87,G87) -> 1487.5 | I87: =(D87-H87)*Assumptions!C8 -> 1756.25 | J87: =D87-H87-I87 -> 1756.25 | K87: =E87*(H87+I87*Assumptions!D8) -> 186884.38 | L87: =D87*F87 -> 150000 | M87: =K87-(H87+I87)*F87 -> 89571.875 | N87: =K87-L87 -> 36884.375 | O87: =J87*F87 -> 52687.5 | P87: =IF(B87="In-Store",N87/V87,0) -> 36884.375 | Q87: =COUNTIFS('Product decisions'!$A$7:$A$32,A87,'Product decisions'!$C$7:$C$32,B87) -> 0 | R87: =COUNTIFS('Product decisions'!$A$7:$A$32,A87,'Product decisions'!$H$7:$H$32,B87) -> 0 | S87: =COUNTIFS('Product decisions'!$A$7:$A$32,A87,'Product decisions'!$I$7:$I$32,B87) -> 0 | T87: =COUNTIFS('Product decisions'!$A$7:$A$32,A87,'Product decisions'!$J$7:$J$32,B87) -> 0 | U87: =0 -> 0 | V87: ='Source data'!D21 -> 1 | W87: =IF(K87=0,0,N87/K87) -> 0.19736468 | X87: =IF(L87=0,0,N87/L87) -> 0.24589583
A88: Animated Witch Cauldron | B88: Online-Only | C88: Downside | D88: =Assumptions!B35 -> 5000 | E88: ='Source data'!E21 -> 79 | F88: ='Source data'!F21 -> 30 | G88: =IF(B88="In-Store",'Source data'!J21+Assumptions!$B$15*'Source data'!K21,'Source data'!K21+Assumptions!$B$15*'Source data'!J21)*'Source data'!H21/'Source data'!G21*Assumptions!B8 -> 2975 | H88: =MIN(D88,G88) -> 2975 | I88: =(D88-H88)*Assumptions!C8 -> 1012.5 | J88: =D88-H88-I88 -> 1012.5 | K88: =E88*(H88+I88*Assumptions!D8) -> 275018.75 | L88: =D88*F88 -> 150000 | M88: =K88-(H88+I88)*F88 -> 155393.75 | N88: =K88-L88 -> 125018.75 | O88: =J88*F88 -> 30375 | P88: =IF(B88="In-Store",N88/V88,0) -> 0 | Q88: =COUNTIFS('Product decisions'!$A$7:$A$32,A88,'Product decisions'!$C$7:$C$32,B88) -> 0 | R88: =COUNTIFS('Product decisions'!$A$7:$A$32,A88,'Product decisions'!$H$7:$H$32,B88) -> 0 | S88: =COUNTIFS('Product decisions'!$A$7:$A$32,A88,'Product decisions'!$I$7:$I$32,B88) -> 1 | T88: =COUNTIFS('Product decisions'!$A$7:$A$32,A88,'Product decisions'!$J$7:$J$32,B88) -> 1 | U88: =0 -> 0 | V88: ='Source data'!D21 -> 1 | W88: =IF(K88=0,0,N88/K88) -> 0.45458264 | X88: =IF(L88=0,0,N88/L88) -> 0.83345833
A89: Halloween Doormat Assortment | B89: In-Store | C89: Downside | D89: =Assumptions!B36 -> 9000 | E89: ='Source data'!E22 -> 19.98 | F89: ='Source data'!F22 -> 12 | G89: =IF(B89="In-Store",'Source data'!J22+Assumptions!$B$15*'Source data'!K22,'Source data'!K22+Assumptions!$B$15*'Source data'!J22)*'Source data'!H22/'Source data'!G22*Assumptions!B8 -> 1417.5 | H89: =MIN(D89,G89) -> 1417.5 | I89: =(D89-H89)*Assumptions!C8 -> 3791.25 | J89: =D89-H89-I89 -> 3791.25 | K89: =E89*(H89+I89*Assumptions!D8) -> 66196.238 | L89: =D89*F89 -> 108000 | M89: =K89-(H89+I89)*F89 -> 3691.2375 | N89: =K89-L89 -> -41803.762 | O89: =J89*F89 -> 45495 | P89: =IF(B89="In-Store",N89/V89,0) -> -41803.762 | Q89: =COUNTIFS('Product decisions'!$A$7:$A$32,A89,'Product decisions'!$C$7:$C$32,B89) -> 0 | R89: =COUNTIFS('Product decisions'!$A$7:$A$32,A89,'Product decisions'!$H$7:$H$32,B89) -> 0 | S89: =COUNTIFS('Product decisions'!$A$7:$A$32,A89,'Product decisions'!$I$7:$I$32,B89) -> 0 | T89: =COUNTIFS('Product decisions'!$A$7:$A$32,A89,'Product decisions'!$J$7:$J$32,B89) -> 0 | U89: =0 -> 0 | V89: ='Source data'!D22 -> 1 | W89: =IF(K89=0,0,N89/K89) -> -0.63151267 | X89: =IF(L89=0,0,N89/L89) -> -0.38707188
A90: Halloween Doormat Assortment | B90: Online-Only | C90: Downside | D90: =Assumptions!B36 -> 9000 | E90: ='Source data'!E22 -> 19.98 | F90: ='Source data'!F22 -> 12 | G90: =IF(B90="In-Store",'Source data'!J22+Assumptions!$B$15*'Source data'!K22,'Source data'!K22+Assumptions!$B$15*'Source data'!J22)*'Source data'!H22/'Source data'!G22*Assumptions!B8 -> 2835 | H90: =MIN(D90,G90) -> 2835 | I90: =(D90-H90)*Assumptions!C8 -> 3082.5 | J90: =D90-H90-I90 -> 3082.5 | K90: =E90*(H90+I90*Assumptions!D8) -> 87437.475 | L90: =D90*F90 -> 108000 | M90: =K90-(H90+I90)*F90 -> 16427.475 | N90: =K90-L90 -> -20562.525 | O90: =J90*F90 -> 36990 | P90: =IF(B90="In-Store",N90/V90,0) -> 0 | Q90: =COUNTIFS('Product decisions'!$A$7:$A$32,A90,'Product decisions'!$C$7:$C$32,B90) -> 0 | R90: =COUNTIFS('Product decisions'!$A$7:$A$32,A90,'Product decisions'!$H$7:$H$32,B90) -> 0 | S90: =COUNTIFS('Product decisions'!$A$7:$A$32,A90,'Product decisions'!$I$7:$I$32,B90) -> 0 | T90: =COUNTIFS('Product decisions'!$A$7:$A$32,A90,'Product decisions'!$J$7:$J$32,B90) -> 0 | U90: =0 -> 0 | V90: ='Source data'!D22 -> 1 | W90: =IF(K90=0,0,N90/K90) -> -0.23516833 | X90: =IF(L90=0,0,N90/L90) -> -0.19039375
A91: 14 ft Giant Animated Dragon | B91: In-Store | C91: Downside | D91: =Assumptions!B37 -> 45000 | E91: ='Source data'!E23 -> 449 | F91: ='Source data'!F23 -> 240 | G91: ='Source data'!G23*Assumptions!$B$13*IF(B91="In-Store",1,Assumptions!$B$14)*Assumptions!B8 -> 25200 | H91: =MIN(D91,G91) -> 25200 | I91: =(D91-H91)*Assumptions!C8 -> 9900 | J91: =D91-H91-I91 -> 9900 | K91: =E91*(H91+I91*Assumptions!D8) -> 13537350 | L91: =D91*F91 -> 10800000 | M91: =K91-(H91+I91)*F91 -> 5113350 | N91: =K91-L91 -> 2737350 | O91: =J91*F91 -> 2376000 | P91: =IF(B91="In-Store",N91/V91,0) -> 684337.5 | Q91: =COUNTIFS('Product decisions'!$A$7:$A$32,A91,'Product decisions'!$C$7:$C$32,B91) -> 0 | R91: =COUNTIFS('Product decisions'!$A$7:$A$32,A91,'Product decisions'!$H$7:$H$32,B91) -> 1 | S91: =COUNTIFS('Product decisions'!$A$7:$A$32,A91,'Product decisions'!$I$7:$I$32,B91) -> 0 | T91: =COUNTIFS('Product decisions'!$A$7:$A$32,A91,'Product decisions'!$J$7:$J$32,B91) -> 0 | U91: =L91 -> 10800000 | V91: ='Source data'!D23 -> 4 | W91: =IF(K91=0,0,N91/K91) -> 0.20220723 | X91: =IF(L91=0,0,N91/L91) -> 0.25345833
A92: 14 ft Giant Animated Dragon | B92: Online-Only | C92: Downside | D92: =Assumptions!B37 -> 45000 | E92: ='Source data'!E23 -> 449 | F92: ='Source data'!F23 -> 240 | G92: ='Source data'!G23*Assumptions!$B$13*IF(B92="In-Store",1,Assumptions!$B$14)*Assumptions!B8 -> 20160 | H92: =MIN(D92,G92) -> 20160 | I92: =(D92-H92)*Assumptions!C8 -> 12420 | J92: =D92-H92-I92 -> 12420 | K92: =E92*(H92+I92*Assumptions!D8) -> 11840130 | L92: =D92*F92 -> 10800000 | M92: =K92-(H92+I92)*F92 -> 4020930 | N92: =K92-L92 -> 1040130 | O92: =J92*F92 -> 2980800 | P92: =IF(B92="In-Store",N92/V92,0) -> 0 | Q92: =COUNTIFS('Product decisions'!$A$7:$A$32,A92,'Product decisions'!$C$7:$C$32,B92) -> 0 | R92: =COUNTIFS('Product decisions'!$A$7:$A$32,A92,'Product decisions'!$H$7:$H$32,B92) -> 0 | S92: =COUNTIFS('Product decisions'!$A$7:$A$32,A92,'Product decisions'!$I$7:$I$32,B92) -> 0 | T92: =COUNTIFS('Product decisions'!$A$7:$A$32,A92,'Product decisions'!$J$7:$J$32,B92) -> 0 | U92: =L92 -> 10800000 | V92: ='Source data'!D23 -> 4 | W92: =IF(K92=0,0,N92/K92) -> 0.087847853 | X92: =IF(L92=0,0,N92/L92) -> 0.096308333
A93: 6 ft Licensed Movie Villain | B93: In-Store | C93: Downside | D93: =Assumptions!B38 -> 14000 | E93: ='Source data'!E24 -> 329 | F93: ='Source data'!F24 -> 215 | G93: ='Source data'!G24*Assumptions!$B$13*IF(B93="In-Store",1,Assumptions!$B$14)*Assumptions!B8 -> 7840 | H93: =MIN(D93,G93) -> 7840 | I93: =(D93-H93)*Assumptions!C8 -> 3080 | J93: =D93-H93-I93 -> 3080 | K93: =E93*(H93+I93*Assumptions!D8) -> 3086020 | L93: =D93*F93 -> 3010000 | M93: =K93-(H93+I93)*F93 -> 738220 | N93: =K93-L93 -> 76020 | O93: =J93*F93 -> 662200 | P93: =IF(B93="In-Store",N93/V93,0) -> 38010 | Q93: =COUNTIFS('Product decisions'!$A$7:$A$32,A93,'Product decisions'!$C$7:$C$32,B93) -> 0 | R93: =COUNTIFS('Product decisions'!$A$7:$A$32,A93,'Product decisions'!$H$7:$H$32,B93) -> 1 | S93: =COUNTIFS('Product decisions'!$A$7:$A$32,A93,'Product decisions'!$I$7:$I$32,B93) -> 0 | T93: =COUNTIFS('Product decisions'!$A$7:$A$32,A93,'Product decisions'!$J$7:$J$32,B93) -> 0 | U93: =L93 -> 3010000 | V93: ='Source data'!D24 -> 2 | W93: =IF(K93=0,0,N93/K93) -> 0.024633671 | X93: =IF(L93=0,0,N93/L93) -> 0.025255814
A94: 6 ft Licensed Movie Villain | B94: Online-Only | C94: Downside | D94: =Assumptions!B38 -> 14000 | E94: ='Source data'!E24 -> 329 | F94: ='Source data'!F24 -> 215 | G94: ='Source data'!G24*Assumptions!$B$13*IF(B94="In-Store",1,Assumptions!$B$14)*Assumptions!B8 -> 6272 | H94: =MIN(D94,G94) -> 6272 | I94: =(D94-H94)*Assumptions!C8 -> 3864 | J94: =D94-H94-I94 -> 3864 | K94: =E94*(H94+I94*Assumptions!D8) -> 2699116 | L94: =D94*F94 -> 3010000 | M94: =K94-(H94+I94)*F94 -> 519876 | N94: =K94-L94 -> -310884 | O94: =J94*F94 -> 830760 | P94: =IF(B94="In-Store",N94/V94,0) -> 0 | Q94: =COUNTIFS('Product decisions'!$A$7:$A$32,A94,'Product decisions'!$C$7:$C$32,B94) -> 0 | R94: =COUNTIFS('Product decisions'!$A$7:$A$32,A94,'Product decisions'!$H$7:$H$32,B94) -> 0 | S94: =COUNTIFS('Product decisions'!$A$7:$A$32,A94,'Product decisions'!$I$7:$I$32,B94) -> 0 | T94: =COUNTIFS('Product decisions'!$A$7:$A$32,A94,'Product decisions'!$J$7:$J$32,B94) -> 0 | U94: =L94 -> 3010000 | V94: ='Source data'!D24 -> 2 | W94: =IF(K94=0,0,N94/K94) -> -0.11517993 | X94: =IF(L94=0,0,N94/L94) -> -0.10328372
A95: 9 ft Licensed Franchise Inflatable | B95: In-Store | C95: Downside | D95: =Assumptions!B39 -> 12000 | E95: ='Source data'!E25 -> 159 | F95: ='Source data'!F25 -> 138 | G95: ='Source data'!G25*Assumptions!$B$13*IF(B95="In-Store",1,Assumptions!$B$14)*Assumptions!B8 -> 6720 | H95: =MIN(D95,G95) -> 6720 | I95: =(D95-H95)*Assumptions!C8 -> 2640 | J95: =D95-H95-I95 -> 2640 | K95: =E95*(H95+I95*Assumptions!D8) -> 1278360 | L95: =D95*F95 -> 1656000 | M95: =K95-(H95+I95)*F95 -> -13320 | N95: =K95-L95 -> -377640 | O95: =J95*F95 -> 364320 | P95: =IF(B95="In-Store",N95/V95,0) -> -188820 | Q95: =COUNTIFS('Product decisions'!$A$7:$A$32,A95,'Product decisions'!$C$7:$C$32,B95) -> 0 | R95: =COUNTIFS('Product decisions'!$A$7:$A$32,A95,'Product decisions'!$H$7:$H$32,B95) -> 0 | S95: =COUNTIFS('Product decisions'!$A$7:$A$32,A95,'Product decisions'!$I$7:$I$32,B95) -> 0 | T95: =COUNTIFS('Product decisions'!$A$7:$A$32,A95,'Product decisions'!$J$7:$J$32,B95) -> 0 | U95: =L95 -> 1656000 | V95: ='Source data'!D25 -> 2 | W95: =IF(K95=0,0,N95/K95) -> -0.29540974 | X95: =IF(L95=0,0,N95/L95) -> -0.22804348
A96: 9 ft Licensed Franchise Inflatable | B96: Online-Only | C96: Downside | D96: =Assumptions!B39 -> 12000 | E96: ='Source data'!E25 -> 159 | F96: ='Source data'!F25 -> 138 | G96: ='Source data'!G25*Assumptions!$B$13*IF(B96="In-Store",1,Assumptions!$B$14)*Assumptions!B8 -> 5376 | H96: =MIN(D96,G96) -> 5376 | I96: =(D96-H96)*Assumptions!C8 -> 3312 | J96: =D96-H96-I96 -> 3312 | K96: =E96*(H96+I96*Assumptions!D8) -> 1118088 | L96: =D96*F96 -> 1656000 | M96: =K96-(H96+I96)*F96 -> -80856 | N96: =K96-L96 -> -537912 | O96: =J96*F96 -> 457056 | P96: =IF(B96="In-Store",N96/V96,0) -> 0 | Q96: =COUNTIFS('Product decisions'!$A$7:$A$32,A96,'Product decisions'!$C$7:$C$32,B96) -> 0 | R96: =COUNTIFS('Product decisions'!$A$7:$A$32,A96,'Product decisions'!$H$7:$H$32,B96) -> 0 | S96: =COUNTIFS('Product decisions'!$A$7:$A$32,A96,'Product decisions'!$I$7:$I$32,B96) -> 0 | T96: =COUNTIFS('Product decisions'!$A$7:$A$32,A96,'Product decisions'!$J$7:$J$32,B96) -> 0 | U96: =L96 -> 1656000 | V96: ='Source data'!D25 -> 2 | W96: =IF(K96=0,0,N96/K96) -> -0.48109988 | X96: =IF(L96=0,0,N96/L96) -> -0.32482609
A97: 7 ft Licensed Sitcom Character | B97: In-Store | C97: Downside | D97: =Assumptions!B40 -> 9000 | E97: ='Source data'!E26 -> 279 | F97: ='Source data'!F26 -> 164 | G97: ='Source data'!G26*Assumptions!$B$13*IF(B97="In-Store",1,Assumptions!$B$14)*Assumptions!B8 -> 5040 | H97: =MIN(D97,G97) -> 5040 | I97: =(D97-H97)*Assumptions!C8 -> 1980 | J97: =D97-H97-I97 -> 1980 | K97: =E97*(H97+I97*Assumptions!D8) -> 1682370 | L97: =D97*F97 -> 1476000 | M97: =K97-(H97+I97)*F97 -> 531090 | N97: =K97-L97 -> 206370 | O97: =J97*F97 -> 324720 | P97: =IF(B97="In-Store",N97/V97,0) -> 103185 | Q97: =COUNTIFS('Product decisions'!$A$7:$A$32,A97,'Product decisions'!$C$7:$C$32,B97) -> 1 | R97: =COUNTIFS('Product decisions'!$A$7:$A$32,A97,'Product decisions'!$H$7:$H$32,B97) -> 1 | S97: =COUNTIFS('Product decisions'!$A$7:$A$32,A97,'Product decisions'!$I$7:$I$32,B97) -> 1 | T97: =COUNTIFS('Product decisions'!$A$7:$A$32,A97,'Product decisions'!$J$7:$J$32,B97) -> 0 | U97: =L97 -> 1476000 | V97: ='Source data'!D26 -> 2 | W97: =IF(K97=0,0,N97/K97) -> 0.12266624 | X97: =IF(L97=0,0,N97/L97) -> 0.13981707
